Workbook
Name L_Uses: Lookups!$A$5:$A$12
Name L_Centres: Lookups!$B$5:$B$29
Name L_YesNo: Lookups!$C$5:$C$6
Name L_Owner: Lookups!$D$5:$D$6
Name L_AreaUnit: Lookups!$E$5:$E$6
Name L_Occupier: Lookups!$F$5:$F$7
Name L_Group: Lookups!$G$5:$G$7
Name L_Scale: Lookups!$H$5:$H$11
Name L_Grades: Lookups!$I$5:$I$10
Name L_CostGrade: Lookups!$J$5:$J$10
Name L_GroupValue: Lookups!$K$5:$K$7
Name L_Tier: Lookups!$L$5:$L$29

Sheet Front
A1: Town Centre Activation Value Model
A3: Version 0.1, 23 October 2026 (pre-Budget; revise after the 28 October 2026 Budget)
A4: What It Does
A5: Estimates the value of bringing a vacant town centre unit in Gateshead into meanwhile use, against the public money it needs. It follows the MHCLG Appraisal Guide (4th edition, February 2026) and the Green Book (2026): welfare-based benefit-cost ratios for Gateshead and for the UK, each with its value for money category, with local GVA, jobs and visitor spend reported as Gateshead indicators outside the ratios.
A6: How to Use It
A7: 1. Enter up to five proposals on the Inputs sheet (yellow cells). One property and one use per column.
A8: 2. Pick the proposal to show in Settings. Results is the one-page summary, Sensitivity holds the switching values and Compare sets all five side by side.
A9: 3. Key in local reference data once on the Static Data sheet: STEAM spend per visit and the council's vacancy survey by centre.
A10: 4. Assumptions are protected. To use a better local figure, enter it in the Local override column with a reason; Results flags any override.
A11: Reading the Results
A12: Low takes the pessimistic end of every ranged assumption, high the optimistic end. Optimism bias follows the Treasury guidance: benefits are cut by up to 40% and costs raised by up to 51% according to the strength of the evidence. Evidence over five years old is graded 6, the weakest, as Treasury Table 7.B requires.
A13: The chance of a commercial let anyway is netted off the benefits. With a break clause the meanwhile use ends if a tenant appears; without one it blocks the let, and the model assumes the blocked tenant would have brought similar jobs and visitors, and counts the rates it would have paid as lost public income. Costs are not reduced.
... A16: Indicative appraisal, not a business case. Built on the register approved on 23 October 2026. To be revised after the 28 October 2026 Budget, which is expected to cut the Green Book discount rate to 3.0% and may bring a new GDP deflator file.

Sheet Inputs
A1: Inputs
A2: Yellow cells are inputs. Up to five proposals, one property and one use each. Blank optional cells use the evidence default.
B4: Input | C4: Proposal 1 | D4: Proposal 2 | E4: Proposal 3 | F4: Proposal 4 | G4: Proposal 5 | H4: Guidance
B5: Proposal
B6: Proposal name | H6: The worked example is hypothetical and describes no real unit
B7: Centre | H7: Local Plan Policy CS7. Metrocentre is outside the hierarchy
B8: Centre tier (filled in automatically) | C8: =IFERROR(INDEX(L_Tier,MATCH(C7,L_Centres,0)),"") | D8: =IFERROR(INDEX(L_Tier,MATCH(D7,L_Centres,0)),"") | E8: =IFERROR(INDEX(L_Tier,MATCH(E7,L_Centres,0)),"") | F8: =IFERROR(INDEX(L_Tier,MATCH(F7,L_Centres,0)),"") | G8: =IFERROR(INDEX(L_Tier,MATCH(G7,L_Centres,0)),"") | H8: Label and place scorecard only (Phase 1b decision 4)
B9: Use | H9: Health and wellbeing means activity-based uses; enter clinical services as a community hub with your own staffing
B10: The property
B11: Floor area (gross internal)
B12: Floor area unit | H12: Blank = sq ft
B13: Rateable value (£) | H13: From the free VOA 'Find a business rates valuation' service. Required: results stay blank without it
B14: Listed building? | H14: Listed empty buildings pay no empty rates
B15: Owner
B16: Book or market value if council-owned (£) | H16: Used for the 2% holding cost only if no security cost is entered
B17: Cost of keeping the unit empty, for security, inspection and maintenance (£ a year) | H17: The council's own figure; no published benchmark exists
B18: Chance the unit is let commercially anyway during the period (optional) | H18: Blank = council vacancy survey for the centre (Static Data), else row B1
B19: Can the landlord end the meanwhile lease for a commercial let? | H19: Standard meanwhile leases allow this. Blank = Yes
B20: The occupation
B21: Occupation period (months, up to 60) | H21: Required
B22: Rent paid by the occupier or its users (£ a year) | H22: The low value of the space (row V2)
B23: Rent paid by the council to a private landlord (£ a year) | H23: A transfer (row V4). Ignored where the council owns the unit
B24: Occupier type for business rates
B25: Eligible for the retail, hospitality and leisure multiplier?
B26: Discretionary relief on the remaining bill | H26: 100% = no rates paid
B27: Public costs
B28: Fit-out and works, capital, at the start (£) | H28: Optimism bias +51% at proposal stage (row C7)
B29: Share of optimism bias risk factors mitigated so far | H29: 0% at proposal stage; steps the fit-out uplift from 51% towards 4%
B30: Operator or management contract (£ a year) | H30: Optimism bias +41% (row C8)
B31: Utilities, insurance and other running costs (£ a year)
B32: Monitoring and evaluation (£ a year) | H32: Green Book 10.8
B33: Evidence behind the running and monitoring costs | H33: Treasury Table 7.A; sets their optimism bias. Blank = 4
B34: Council share of capital cost | H34: The rest from Pride in Place, UKSPF, NEMSA or other funders
B35: Council share of revenue costs
B36: Activity
B37: Staffing, FTE (optional) | H37: Blank = estimate from floor area
B38: or full-time staff (headcount)
B39: and part-time staff (headcount) | H39: 2 part-time = 1 FTE
B40: Share of the space in use against a fully used unit (optional) | H40: Blank = row J9
B41: Regular volunteers who would not otherwise volunteer (average number)
B42: Regular participants who would not otherwise take part (weekly or more) | H42: Not one-off visitors
B43: Main participant group | H43: Blank = adults 30-49, weekly cultural attendance
B44: Jobs filled by previously unemployed Gateshead residents (optional) | H44: Blank = estimate (row S3)
B45: Visitors a week | H45: Only their spend elsewhere in the centre counts (row D1)
B46: Share of their extra spend going on food and drink
B47: Share of visits that are new trips to the centre (optional) | H47: Blank = row X4
B48: Start-up businesses hosted
B49: All businesses or groups hosted
B50: Learners
B51: Accredited Level 2 qualifications achieved | H51: Sensitivity sheet only
B52: Accredited Level 3 qualifications achieved | H52: Sensitivity sheet only
B53: Chance of a permanent let afterwards that would not otherwise happen (optional) | H53: Used only if the legacy switch in Settings is Yes (row L3: no robust evidence). Enter it net of any let that would happen later anyway
B55: Place scorecard (MHCLG seven-point scale, Table 2). Score each line and give a short reason
B56: Frontage activated
B57: reason
B58: Daytime activity and footfall
B59: reason
B60: Evening activity
B61: reason
B62: Community use and inclusion
B63: reason
B64: Perception, safety and antisocial behaviour
B65: reason
B66: Fit with the centre's strategy
B67: reason

Sheet Results
A1: Results
A2: =IF(INDEX(Calculations!$D$6:$R$6,1,(Settings!$B$5-1)*3+2)=1,"Proposal "&Settings!$B$5&IF(INDEX(Inputs!$C$6:$G$6,1,Settings!$B$5)="","",", "&INDEX(Inputs!$C$6:$G$6,1,Settings!$B$5))&" ("&INDEX(Inputs!$C$9:$G$9,1,Settings!$B$5)&IF(INDEX(Inputs!$C$7:$G$7,1,Settings!$B$5)="","",", "&INDEX(Inputs!$C$7:$G$7,1,Settings!$B$5))&", "&TEXT(INDEX(Inputs!$C$21:$G$21,1,Settings!$B$5),"0")&" months)","Proposal "&Settings!$B$5&" has no results yet. Enter at least the use, the occupation period and the rateable value on the Inputs sheet")
A3: Version 0.1, 23 October 2026 (pre-Budget; revise after the 28 October 2026 Budget). Indicative appraisal following the MHCLG Appraisal Guide (2026), not a business case.
A5: Value for Money | B5: Gateshead | C5: UK
A6: Category (central) | B6: =IFERROR(INDEX(Calculations!$D$111:$R$111,1,(Settings!$B$5-1)*3+2),"") | C6: =IFERROR(INDEX(Calculations!$D$116:$R$116,1,(Settings!$B$5-1)*3+2),"")
A7: Category range (low to high) | B7: =INDEX(Calculations!$D$111:$R$111,1,(Settings!$B$5-1)*3+1)&" to "&INDEX(Calculations!$D$111:$R$111,1,(Settings!$B$5-1)*3+3) | C7: =INDEX(Calculations!$D$116:$R$116,1,(Settings!$B$5-1)*3+1)&" to "&INDEX(Calculations!$D$116:$R$116,1,(Settings!$B$5-1)*3+3)
A8: Benefit-cost ratio, central | B8: =IFERROR(INDEX(Calculations!$D$107:$R$107,1,(Settings!$B$5-1)*3+2),"") | C8: =IFERROR(INDEX(Calculations!$D$112:$R$112,1,(Settings!$B$5-1)*3+2),"")
A9: Benefit-cost ratio, low | B9: =IFERROR(INDEX(Calculations!$D$107:$R$107,1,(Settings!$B$5-1)*3+1),"") | C9: =IFERROR(INDEX(Calculations!$D$112:$R$112,1,(Settings!$B$5-1)*3+1),"")
A10: Benefit-cost ratio, high | B10: =IFERROR(INDEX(Calculations!$D$107:$R$107,1,(Settings!$B$5-1)*3+3),"") | C10: =IFERROR(INDEX(Calculations!$D$112:$R$112,1,(Settings!$B$5-1)*3+3),"")
A11: Present value of benefits | B11: =IFERROR(INDEX(Calculations!$D$102:$R$102,1,(Settings!$B$5-1)*3+2),"") | C11: =IFERROR(INDEX(Calculations!$D$103:$R$103,1,(Settings!$B$5-1)*3+2),"") | D11: =IFERROR("Rest of UK: "&TEXT(INDEX(Calculations!$D$104:$R$104,1,(Settings!$B$5-1)*3+2),"£#,##0"),"")
A12: Benefit-cost ratio without the offsetting transfers | B12: =IFERROR(INDEX(Calculations!$D$108:$R$108,1,(Settings!$B$5-1)*3+2),"") | C12: =IFERROR(INDEX(Calculations!$D$113:$R$113,1,(Settings!$B$5-1)*3+2),"")
A13: Net public cost | B13: =IFERROR(INDEX(Calculations!$D$91:$R$91,1,(Settings!$B$5-1)*3+2),"") | C13: =IFERROR(INDEX(Calculations!$D$91:$R$91,1,(Settings!$B$5-1)*3+2),"")
A14: Net present social value | B14: =IFERROR(INDEX(Calculations!$D$110:$R$110,1,(Settings!$B$5-1)*3+2),"") | C14: =IFERROR(INDEX(Calculations!$D$115:$R$115,1,(Settings!$B$5-1)*3+2),"")
A15: Robustness of the analysis | B15: =IFERROR(INDEX(Calculations!$D$118:$R$118,1,(Settings!$B$5-1)*3+2),"") | C15: =IFERROR(INDEX(Calculations!$D$118:$R$118,1,(Settings!$B$5-1)*3+2),"")
A17: Value for Money Statement
A18: =IF(INDEX(Calculations!$D$6:$R$6,1,(Settings!$B$5-1)*3+2)<>1,"","On central assumptions the proposal returns £"&TEXT(INDEX(Calculations!$D$107:$R$107,1,(Settings!$B$5-1)*3+2),"0.00")&" of benefits in Gateshead for each £1 of net public cost, including offsetting transfers such as rates relief (£"&TEXT(INDEX(Calculations!$D$108:$R$108,1,(Settings!$B$5-1)*3+2),"0.00")&" without them), which is "&INDEX(Calculations!$D$111:$R$111,1,(Settings!$B$5-1)*3+2)&" value for money, and £"&TEXT(INDEX(Calculations!$D$112:$R$112,1,(Settings!$B$5-1)*3+2),"0.00")&" across the UK ("&INDEX(Calculations!$D$116:$R$116,1,(Settings!$B$5-1)*3+2)&"). "&IF(INDEX(Calculations!$D$111:$R$111,1,(Settings!$B$5-1)*3+1)=INDEX(Calculations!$D$111:$R$111,1,(Settings!$B$5-1)*3+3),"The Gateshead category is "&INDEX(Calculations!$D$111:$R$111,1,(Settings!$B$5-1)*3+1)&" in every scenario.","Across the low and high scenarios the Gateshead category runs from "&INDEX(Calculations!$D$111:$R$111,1,(Settings!$B$5-1)*3+1)&" to "&INDEX(Calculations!$D$111:$R$111,1,(Settings!$B$5-1)*3+3)&".")&" The analysis is "&LOWER(INDEX(Calculations!$D$118:$R$118,1,(Settings!$B$5-1)*3+2))&" in robustness because the weakest evidence behind the benefits is grade "&INDEX(Calculations!$D$117:$R$117,1,(Settings!$B$5-1)*3+2)&" on the Treasury scale. Local output and jobs are reported below as Gateshead indicators and are not in the ratios, as the Green Book requires.")
A23: Benefits and Costs (central, present value) | B23: Gateshead | C23: UK | D23: Grade
A24: Value of the space | B24: =IFERROR(INDEX(Calculations!$D$53:$R$53,1,(Settings!$B$5-1)*3+2)*INDEX(Calculations!$D$95:$R$95,1,(Settings!$B$5-1)*3+2),"") | C24: =IFERROR(INDEX(Calculations!$D$53:$R$53,1,(Settings!$B$5-1)*3+2)*INDEX(Calculations!$D$95:$R$95,1,(Settings!$B$5-1)*3+2),"") | D24: =IFERROR(INDEX(Calculations!$D$52:$R$52,1,(Settings!$B$5-1)*3+2),"") | E24: =IFERROR(IF(INDEX(Calculations!$D$95:$R$95,1,(Settings!$B$5-1)*3+2)=0,"Outside the ratio (range rule): value "&TEXT(INDEX(Calculations!$D$53:$R$53,1,(Settings!$B$5-1)*3+2),"£#,##0"),""),"")
A25: Volunteering | B25: =IFERROR(INDEX(Calculations!$D$56:$R$56,1,(Settings!$B$5-1)*3+2)*INDEX(Calculations!$D$96:$R$96,1,(Settings!$B$5-1)*3+2),"") | C25: =IFERROR(INDEX(Calculations!$D$56:$R$56,1,(Settings!$B$5-1)*3+2)*INDEX(Calculations!$D$96:$R$96,1,(Settings!$B$5-1)*3+2),"") | E25: =IFERROR(IF(INDEX(Calculations!$D$96:$R$96,1,(Settings!$B$5-1)*3+2)=0,"Outside the ratio (range rule): value "&TEXT(INDEX(Calculations!$D$56:$R$56,1,(Settings!$B$5-1)*3+2),"£#,##0"),""),"")
A26: Regular participation | B26: =IFERROR(INDEX(Calculations!$D$59:$R$59,1,(Settings!$B$5-1)*3+2)*INDEX(Calculations!$D$97:$R$97,1,(Settings!$B$5-1)*3+2),"") | C26: =IFERROR(INDEX(Calculations!$D$59:$R$59,1,(Settings!$B$5-1)*3+2)*INDEX(Calculations!$D$97:$R$97,1,(Settings!$B$5-1)*3+2),"") | E26: =IFERROR(IF(INDEX(Calculations!$D$97:$R$97,1,(Settings!$B$5-1)*3+2)=0,"Outside the ratio (range rule): value "&TEXT(INDEX(Calculations!$D$59:$R$59,1,(Settings!$B$5-1)*3+2),"£#,##0"),""),"")
A27: Employment wellbeing | B27: =IFERROR(INDEX(Calculations!$D$63:$R$63,1,(Settings!$B$5-1)*3+2)*INDEX(Calculations!$D$98:$R$98,1,(Settings!$B$5-1)*3+2),"") | C27: =IFERROR(IF(Settings!$B$8="Yes",INDEX(Calculations!$D$63:$R$63,1,(Settings!$B$5-1)*3+2)*INDEX(Calculations!$D$98:$R$98,1,(Settings!$B$5-1)*3+2),0),"") | D27: =IFERROR(INDEX(Calculations!$D$61:$R$61,1,(Settings!$B$5-1)*3+2),"") | E27: =IFERROR(IF(INDEX(Calculations!$D$98:$R$98,1,(Settings!$B$5-1)*3+2)=0,"Outside the ratio (range rule): value "&TEXT(INDEX(Calculations!$D$63:$R$63,1,(Settings!$B$5-1)*3+2),"£#,##0"),""),"")
A28: Avoided empty-unit costs | B28: =IFERROR(INDEX(Calculations!$D$66:$R$66,1,(Settings!$B$5-1)*3+2)*INDEX(Calculations!$D$99:$R$99,1,(Settings!$B$5-1)*3+2),"") | C28: =IFERROR(INDEX(Calculations!$D$66:$R$66,1,(Settings!$B$5-1)*3+2)*INDEX(Calculations!$D$99:$R$99,1,(Settings!$B$5-1)*3+2),"") | D28: =IFERROR(INDEX(Calculations!$D$65:$R$65,1,(Settings!$B$5-1)*3+2),"") | E28: =IFERROR(IF(INDEX(Calculations!$D$99:$R$99,1,(Settings!$B$5-1)*3+2)=0,"Outside the ratio (range rule): value "&TEXT(INDEX(Calculations!$D$66:$R$66,1,(Settings!$B$5-1)*3+2),"£#,##0"),""),"")
A29: Legacy of a permanent let (if switched on) | B29: =IFERROR(INDEX(Calculations!$D$68:$R$68,1,(Settings!$B$5-1)*3+2)*INDEX(Calculations!$D$100:$R$100,1,(Settings!$B$5-1)*3+2)*IF(Settings!$B$9="Yes",1,0),"") | C29: =IFERROR(INDEX(Calculations!$D$68:$R$68,1,(Settings!$B$5-1)*3+2)*INDEX(Calculations!$D$100:$R$100,1,(Settings!$B$5-1)*3+2)*IF(Settings!$B$9="Yes",1,0),"") | E29: =IFERROR(IF(INDEX(Calculations!$D$100:$R$100,1,(Settings!$B$5-1)*3+2)=0,"Outside the ratio (range rule): value "&TEXT(INDEX(Calculations!$D$68:$R$68,1,(Settings!$B$5-1)*3+2),"£#,##0"),""),"")
A30: Transfers (offsetting) | B30: =IFERROR(INDEX(Calculations!$D$80:$R$80,1,(Settings!$B$5-1)*3+2),"") | C30: =IFERROR(INDEX(Calculations!$D$80:$R$80,1,(Settings!$B$5-1)*3+2),"")
A31: Fit-out | B31: =IFERROR(INDEX(Calculations!$D$83:$R$83,1,(Settings!$B$5-1)*3+2),"") | C31: =IFERROR(INDEX(Calculations!$D$83:$R$83,1,(Settings!$B$5-1)*3+2),"")
A32: Operator contract | B32: =IFERROR(INDEX(Calculations!$D$84:$R$84,1,(Settings!$B$5-1)*3+2),"") | C32: =IFERROR(INDEX(Calculations!$D$84:$R$84,1,(Settings!$B$5-1)*3+2),"")
A33: Running costs | B33: =IFERROR(INDEX(Calculations!$D$86:$R$86,1,(Settings!$B$5-1)*3+2),"") | C33: =IFERROR(INDEX(Calculations!$D$86:$R$86,1,(Settings!$B$5-1)*3+2),"")
A34: Monitoring and evaluation | B34: =IFERROR(INDEX(Calculations!$D$87:$R$87,1,(Settings!$B$5-1)*3+2),"") | C34: =IFERROR(INDEX(Calculations!$D$87:$R$87,1,(Settings!$B$5-1)*3+2),"")
A35: Rent to the landlord | B35: =IFERROR(INDEX(Calculations!$D$88:$R$88,1,(Settings!$B$5-1)*3+2),"") | C35: =IFERROR(INDEX(Calculations!$D$88:$R$88,1,(Settings!$B$5-1)*3+2),"")
A36: Rates income forgone | B36: =IFERROR(INDEX(Calculations!$D$89:$R$89,1,(Settings!$B$5-1)*3+2),"") | C36: =IFERROR(INDEX(Calculations!$D$89:$R$89,1,(Settings!$B$5-1)*3+2),"")
A37: Avoided council costs | B37: =IFERROR(INDEX(Calculations!$D$90:$R$90,1,(Settings!$B$5-1)*3+2),"") | C37: =IFERROR(INDEX(Calculations!$D$90:$R$90,1,(Settings!$B$5-1)*3+2),"")
A38: Net public cost | B38: =IFERROR(INDEX(Calculations!$D$91:$R$91,1,(Settings!$B$5-1)*3+2),"") | C38: =IFERROR(INDEX(Calculations!$D$91:$R$91,1,(Settings!$B$5-1)*3+2),"")
A39: Council share of cash and contract costs (excludes rates) | B39: =IFERROR(INDEX(Calculations!$D$93:$R$93,1,(Settings!$B$5-1)*3+2),"")
A40: Cash budget (nominal) | B40: =IFERROR(INDEX(Calculations!$D$92:$R$92,1,(Settings!$B$5-1)*3+2),"") | C40: =IFERROR(INDEX(Calculations!$D$92:$R$92,1,(Settings!$B$5-1)*3+2),"")
A42: Business as Usual (the unit stays empty), central | B42: Value
A43: Chance of a commercial let anyway during the period | B43: =IFERROR(INDEX(Calculations!$D$22:$R$22,1,(Settings!$B$5-1)*3+2),"")
A44: Empty rates paid by a private owner (£ a year) | B44: =IFERROR(INDEX(Calculations!$D$75:$R$75,1,(Settings!$B$5-1)*3+2),"")
A45: Cost of keeping the unit empty (£ a year, before a let anyway) | B45: =IFERROR(IF(INDEX(Calculations!$D$25:$R$25,1,(Settings!$B$5-1)*3+2)>0,INDEX(Calculations!$D$64:$R$64,1,(Settings!$B$5-1)*3+2)/INDEX(Calculations!$D$25:$R$25,1,(Settings!$B$5-1)*3+2),0),"")
A46: Rates bill a commercial tenant would pay (£ a year) | B46: =IFERROR(INDEX(Calculations!$D$71:$R$71,1,(Settings!$B$5-1)*3+2),"")
A48: Gateshead Indicators (outside the ratios) | B48: Low | C48: Central | D48: High
A49: Gross FTE while open | B49: =IFERROR(INDEX(Calculations!$D$35:$R$35,1,(Settings!$B$5-1)*3+1),"") | C49: =IFERROR(INDEX(Calculations!$D$35:$R$35,1,(Settings!$B$5-1)*3+2),"") | D49: =IFERROR(INDEX(Calculations!$D$35:$R$35,1,(Settings!$B$5-1)*3+3),"")
A50: Net FTE, Gateshead | B50: =IFERROR(INDEX(Calculations!$D$38:$R$38,1,(Settings!$B$5-1)*3+1),"") | C50: =IFERROR(INDEX(Calculations!$D$38:$R$38,1,(Settings!$B$5-1)*3+2),"") | D50: =IFERROR(INDEX(Calculations!$D$38:$R$38,1,(Settings!$B$5-1)*3+3),"")
A51: Net FTE, NEMSA | B51: =IFERROR(INDEX(Calculations!$D$40:$R$40,1,(Settings!$B$5-1)*3+1),"") | C51: =IFERROR(INDEX(Calculations!$D$40:$R$40,1,(Settings!$B$5-1)*3+2),"") | D51: =IFERROR(INDEX(Calculations!$D$40:$R$40,1,(Settings!$B$5-1)*3+3),"")
A52: Net FTE, UK | B52: =IFERROR(INDEX(Calculations!$D$41:$R$41,1,(Settings!$B$5-1)*3+1),"") | C52: =IFERROR(INDEX(Calculations!$D$41:$R$41,1,(Settings!$B$5-1)*3+2),"") | D52: =IFERROR(INDEX(Calculations!$D$41:$R$41,1,(Settings!$B$5-1)*3+3),"")
A53: GVA supported in Gateshead (present value) | B53: =IFERROR(INDEX(Calculations!$D$44:$R$44,1,(Settings!$B$5-1)*3+1),"") | C53: =IFERROR(INDEX(Calculations!$D$44:$R$44,1,(Settings!$B$5-1)*3+2),"") | D53: =IFERROR(INDEX(Calculations!$D$44:$R$44,1,(Settings!$B$5-1)*3+3),"")
A54: GVA from extra visitor spend (present value) | B54: =IFERROR(INDEX(Calculations!$D$124:$R$124,1,(Settings!$B$5-1)*3+1),"") | C54: =IFERROR(INDEX(Calculations!$D$124:$R$124,1,(Settings!$B$5-1)*3+2),"") | D54: =IFERROR(INDEX(Calculations!$D$124:$R$124,1,(Settings!$B$5-1)*3+3),"")
A55: Start-ups surviving one year | B55: =IFERROR(INDEX(Calculations!$D$125:$R$125,1,(Settings!$B$5-1)*3+1),"") | C55: =IFERROR(INDEX(Calculations!$D$125:$R$125,1,(Settings!$B$5-1)*3+2),"") | D55: =IFERROR(INDEX(Calculations!$D$125:$R$125,1,(Settings!$B$5-1)*3+3),"")
A56: Start-ups surviving three years | B56: =IFERROR(INDEX(Calculations!$D$126:$R$126,1,(Settings!$B$5-1)*3+1),"") | C56: =IFERROR(INDEX(Calculations!$D$126:$R$126,1,(Settings!$B$5-1)*3+2),"") | D56: =IFERROR(INDEX(Calculations!$D$126:$R$126,1,(Settings!$B$5-1)*3+3),"")
A57: ONS average FTE per local unit in this industry | B57: =IFERROR(INDEX(Calculations!$D$34:$R$34,1,(Settings!$B$5-1)*3+1),"") | C57: =IFERROR(INDEX(Calculations!$D$34:$R$34,1,(Settings!$B$5-1)*3+2),"") | D57: =IFERROR(INDEX(Calculations!$D$34:$R$34,1,(Settings!$B$5-1)*3+3),"")
A58: Gross FTE per business or group hosted | B58: =IFERROR(INDEX(Calculations!$D$45:$R$45,1,(Settings!$B$5-1)*3+1),"") | C58: =IFERROR(INDEX(Calculations!$D$45:$R$45,1,(Settings!$B$5-1)*3+2),"") | D58: =IFERROR(INDEX(Calculations!$D$45:$R$45,1,(Settings!$B$5-1)*3+3),"")
A59: Businesses or groups hosted (count) | C59: =N(INDEX(Inputs!$C$49:$G$49,1,Settings!$B$5))
A60: Learners (count) | C60: =N(INDEX(Inputs!$C$50:$G$50,1,Settings!$B$5))
A61: Regular volunteers (count) | C61: =N(INDEX(Inputs!$C$41:$G$41,1,Settings!$B$5))
A62: Regular participants (count) | C62: =N(INDEX(Inputs!$C$42:$G$42,1,Settings!$B$5))
A63: =IFERROR(IF(INDEX(Calculations!$D$45:$R$45,1,(Settings!$B$5-1)*3+2)>2*INDEX(Calculations!$D$34:$R$34,1,(Settings!$B$5-1)*3+2),"Check this estimate. FTE per business hosted is more than twice the ONS average for this industry; enter your own staffing if you have it",""),"")
A65: Place Scorecard (MHCLG seven-point scale) | B65: Score | F65: Reason
A66: Frontage activated | B66: =IF(INDEX(Inputs!$C$56:$G$56,1,Settings!$B$5)="","Not scored",INDEX(Inputs!$C$56:$G$56,1,Settings!$B$5)) | F66: =IF(INDEX(Inputs!$C$57:$G$57,1,Settings!$B$5)="","",INDEX(Inputs!$C$57:$G$57,1,Settings!$B$5))
A67: Daytime activity and footfall | B67: =IF(INDEX(Inputs!$C$58:$G$58,1,Settings!$B$5)="","Not scored",INDEX(Inputs!$C$58:$G$58,1,Settings!$B$5)) | F67: =IF(INDEX(Inputs!$C$59:$G$59,1,Settings!$B$5)="","",INDEX(Inputs!$C$59:$G$59,1,Settings!$B$5))
A68: Evening activity | B68: =IF(INDEX(Inputs!$C$60:$G$60,1,Settings!$B$5)="","Not scored",INDEX(Inputs!$C$60:$G$60,1,Settings!$B$5)) | F68: =IF(INDEX(Inputs!$C$61:$G$61,1,Settings!$B$5)="","",INDEX(Inputs!$C$61:$G$61,1,Settings!$B$5))
A69: Community use and inclusion | B69: =IF(INDEX(Inputs!$C$62:$G$62,1,Settings!$B$5)="","Not scored",INDEX(Inputs!$C$62:$G$62,1,Settings!$B$5)) | F69: =IF(INDEX(Inputs!$C$63:$G$63,1,Settings!$B$5)="","",INDEX(Inputs!$C$63:$G$63,1,Settings!$B$5))
A70: Perception, safety and antisocial behaviour | B70: =IF(INDEX(Inputs!$C$64:$G$64,1,Settings!$B$5)="","Not scored",INDEX(Inputs!$C$64:$G$64,1,Settings!$B$5)) | F70: =IF(INDEX(Inputs!$C$65:$G$65,1,Settings!$B$5)="","",INDEX(Inputs!$C$65:$G$65,1,Settings!$B$5))
A71: Fit with the centre's strategy | B71: =IF(INDEX(Inputs!$C$66:$G$66,1,Settings!$B$5)="","Not scored",INDEX(Inputs!$C$66:$G$66,1,Settings!$B$5)) | F71: =IF(INDEX(Inputs!$C$67:$G$67,1,Settings!$B$5)="","",INDEX(Inputs!$C$67:$G$67,1,Settings!$B$5))
A73: =IF(COUNTA(Assumptions!K5:K200)>0,COUNTA(Assumptions!K5:K200)&" assumption(s) overridden locally: see the Assumptions sheet","No local overrides of the register")
A75: Chart data | B75: Central | C75: Minus | D75: Plus
A76: Gateshead | B76: =IFERROR(INDEX(Calculations!$D$107:$R$107,1,(Settings!$B$5-1)*3+2),0) | C76: =IFERROR(INDEX(Calculations!$D$107:$R$107,1,(Settings!$B$5-1)*3+2)-INDEX(Calculations!$D$107:$R$107,1,(Settings!$B$5-1)*3+1),0) | D76: =IFERROR(INDEX(Calculations!$D$107:$R$107,1,(Settings!$B$5-1)*3+3)-INDEX(Calculations!$D$107:$R$107,1,(Settings!$B$5-1)*3+2),0)
A77: UK | B77: =IFERROR(INDEX(Calculations!$D$112:$R$112,1,(Settings!$B$5-1)*3+2),0) | C77: =IFERROR(INDEX(Calculations!$D$112:$R$112,1,(Settings!$B$5-1)*3+2)-INDEX(Calculations!$D$112:$R$112,1,(Settings!$B$5-1)*3+1),0) | D77: =IFERROR(INDEX(Calculations!$D$112:$R$112,1,(Settings!$B$5-1)*3+3)-INDEX(Calculations!$D$112:$R$112,1,(Settings!$B$5-1)*3+2),0)

Sheet Sensitivity
A1: Sensitivity and Switching Values
A2: For the proposal chosen in Settings. Switching values show how far the evidence would have to move to change the value for money category.
A4: Test | B4: Gateshead | C4: UK | D4: Reading
A5: Fall in benefits that would drop the category one band | B5: =IFERROR(IF(IF((INDEX(Calculations!$D$107:$R$107,1,(Settings!$B$5-1)*3+2))>=4,4,IF((INDEX(Calculations!$D$107:$R$107,1,(Settings!$B$5-1)*3+2))>=2,2,IF((INDEX(Calculations!$D$107:$R$107,1,(Settings!$B$5-1)*3+2))>=1.5,1.5,IF((INDEX(Calculations!$D$107:$R$107,1,(Settings!$B$5-1)*3+2))>=1,1,0))))=0,"Already Poor or below",1-IF((INDEX(Calculations!$D$107:$R$107,1,(Settings!$B$5-1)*3+2))>=4,4,IF((INDEX(Calculations!$D$107:$R$107,1,(Settings!$B$5-1)*3+2))>=2,2,IF((INDEX(Calculations!$D$107:$R$107,1,(Settings!$B$5-1)*3+2))>=1.5,1.5,IF((INDEX(Calculations!$D$107:$R$107,1,(Settings!$B$5-1)*3+2))>=1,1,0))))*(INDEX(Calculations!$D$91:$R$91,1,(Settings!$B$5-1)*3+2))/(INDEX(Calculations!$D$102:$R$102,1,(Settings!$B$5-1)*3+2))),"") | C5: =IFERROR(IF(IF((INDEX(Calculations!$D$112:$R$112,1,(Settings!$B$5-1)*3+2))>=4,4,IF((INDEX(Calculations!$D$112:$R$112,1,(Settings!$B$5-1)*3+2))>=2,2,IF((INDEX(Calculations!$D$112:$R$112,1,(Settings!$B$5-1)*3+2))>=1.5,1.5,IF((INDEX(Calculations!$D$112:$R$112,1,(Settings!$B$5-1)*3+2))>=1,1,0))))=0,"Already Poor or below",1-IF((INDEX(Calculations!$D$112:$R$112,1,(Settings!$B$5-1)*3+2))>=4,4,IF((INDEX(Calculations!$D$112:$R$112,1,(Settings!$B$5-1)*3+2))>=2,2,IF((INDEX(Calculations!$D$112:$R$112,1,(Settings!$B$5-1)*3+2))>=1.5,1.5,IF((INDEX(Calculations!$D$112:$R$112,1,(Settings!$B$5-1)*3+2))>=1,1,0))))*(INDEX(Calculations!$D$91:$R$91,1,(Settings!$B$5-1)*3+2))/(INDEX(Calculations!$D$103:$R$103,1,(Settings!$B$5-1)*3+2))),"") | D5: Switching value (Green Book 6.104)
A6: Extra benefits needed to reach the next category | B6: =IFERROR(IF(IF((INDEX(Calculations!$D$107:$R$107,1,(Settings!$B$5-1)*3+2))<0,0,IF((INDEX(Calculations!$D$107:$R$107,1,(Settings!$B$5-1)*3+2))<1,1,IF((INDEX(Calculations!$D$107:$R$107,1,(Settings!$B$5-1)*3+2))<1.5,1.5,IF((INDEX(Calculations!$D$107:$R$107,1,(Settings!$B$5-1)*3+2))<2,2,IF((INDEX(Calculations!$D$107:$R$107,1,(Settings!$B$5-1)*3+2))<4,4,"")))))="","Already Very High",IF((INDEX(Calculations!$D$107:$R$107,1,(Settings!$B$5-1)*3+2))<0,0,IF((INDEX(Calculations!$D$107:$R$107,1,(Settings!$B$5-1)*3+2))<1,1,IF((INDEX(Calculations!$D$107:$R$107,1,(Settings!$B$5-1)*3+2))<1.5,1.5,IF((INDEX(Calculations!$D$107:$R$107,1,(Settings!$B$5-1)*3+2))<2,2,IF((INDEX(Calculations!$D$107:$R$107,1,(Settings!$B$5-1)*3+2))<4,4,"")))))*(INDEX(Calculations!$D$91:$R$91,1,(Settings!$B$5-1)*3+2))-(INDEX(Calculations!$D$102:$R$102,1,(Settings!$B$5-1)*3+2))),"") | C6: =IFERROR(IF(IF((INDEX(Calculations!$D$112:$R$112,1,(Settings!$B$5-1)*3+2))<0,0,IF((INDEX(Calculations!$D$112:$R$112,1,(Settings!$B$5-1)*3+2))<1,1,IF((INDEX(Calculations!$D$112:$R$112,1,(Settings!$B$5-1)*3+2))<1.5,1.5,IF((INDEX(Calculations!$D$112:$R$112,1,(Settings!$B$5-1)*3+2))<2,2,IF((INDEX(Calculations!$D$112:$R$112,1,(Settings!$B$5-1)*3+2))<4,4,"")))))="","Already Very High",IF((INDEX(Calculations!$D$112:$R$112,1,(Settings!$B$5-1)*3+2))<0,0,IF((INDEX(Calculations!$D$112:$R$112,1,(Settings!$B$5-1)*3+2))<1,1,IF((INDEX(Calculations!$D$112:$R$112,1,(Settings!$B$5-1)*3+2))<1.5,1.5,IF((INDEX(Calculations!$D$112:$R$112,1,(Settings!$B$5-1)*3+2))<2,2,IF((INDEX(Calculations!$D$112:$R$112,1,(Settings!$B$5-1)*3+2))<4,4,"")))))*(INDEX(Calculations!$D$91:$R$91,1,(Settings!$B$5-1)*3+2))-(INDEX(Calculations!$D$103:$R$103,1,(Settings!$B$5-1)*3+2))),"")
A7: Residents feeling more pride in place needed to reach the next category | B7: =IFERROR(IF(IF((INDEX(Calculations!$D$107:$R$107,1,(Settings!$B$5-1)*3+2))<0,0,IF((INDEX(Calculations!$D$107:$R$107,1,(Settings!$B$5-1)*3+2))<1,1,IF((INDEX(Calculations!$D$107:$R$107,1,(Settings!$B$5-1)*3+2))<1.5,1.5,IF((INDEX(Calculations!$D$107:$R$107,1,(Settings!$B$5-1)*3+2))<2,2,IF((INDEX(Calculations!$D$107:$R$107,1,(Settings!$B$5-1)*3+2))<4,4,"")))))="","",(IF((INDEX(Calculations!$D$107:$R$107,1,(Settings!$B$5-1)*3+2))<0,0,IF((INDEX(Calculations!$D$107:$R$107,1,(Settings!$B$5-1)*3+2))<1,1,IF((INDEX(Calculations!$D$107:$R$107,1,(Settings!$B$5-1)*3+2))<1.5,1.5,IF((INDEX(Calculations!$D$107:$R$107,1,(Settings!$B$5-1)*3+2))<2,2,IF((INDEX(Calculations!$D$107:$R$107,1,(Settings!$B$5-1)*3+2))<4,4,"")))))*(INDEX(Calculations!$D$91:$R$91,1,(Settings!$B$5-1)*3+2))-(INDEX(Calculations!$D$102:$R$102,1,(Settings!$B$5-1)*3+2)))/(Assumptions!$O$86*(INDEX(Calculations!$D$15:$R$15,1,(Settings!$B$5-1)*3+2)))),"") | C7: =IFERROR(IF(IF((INDEX(Calculations!$D$112:$R$112,1,(Settings!$B$5-1)*3+2))<0,0,IF((INDEX(Calculations!$D$112:$R$112,1,(Settings!$B$5-1)*3+2))<1,1,IF((INDEX(Calculations!$D$112:$R$112,1,(Settings!$B$5-1)*3+2))<1.5,1.5,IF((INDEX(Calculations!$D$112:$R$112,1,(Settings!$B$5-1)*3+2))<2,2,IF((INDEX(Calculations!$D$112:$R$112,1,(Settings!$B$5-1)*3+2))<4,4,"")))))="","",(IF((INDEX(Calculations!$D$112:$R$112,1,(Settings!$B$5-1)*3+2))<0,0,IF((INDEX(Calculations!$D$112:$R$112,1,(Settings!$B$5-1)*3+2))<1,1,IF((INDEX(Calculations!$D$112:$R$112,1,(Settings!$B$5-1)*3+2))<1.5,1.5,IF((INDEX(Calculations!$D$112:$R$112,1,(Settings!$B$5-1)*3+2))<2,2,IF((INDEX(Calculations!$D$112:$R$112,1,(Settings!$B$5-1)*3+2))<4,4,"")))))*(INDEX(Calculations!$D$91:$R$91,1,(Settings!$B$5-1)*3+2))-(INDEX(Calculations!$D$103:$R$103,1,(Settings!$B$5-1)*3+2)))/(Assumptions!$O$86*(INDEX(Calculations!$D$15:$R$15,1,(Settings!$B$5-1)*3+2)))),"") | D7: At £4,620 a person a year (HACT value used by MHCLG); switching test only, never in a ratio (decision 6)
A8: People moved from moderate to mild loneliness needed to reach the next category | B8: =IFERROR(IF(IF((INDEX(Calculations!$D$107:$R$107,1,(Settings!$B$5-1)*3+2))<0,0,IF((INDEX(Calculations!$D$107:$R$107,1,(Settings!$B$5-1)*3+2))<1,1,IF((INDEX(Calculations!$D$107:$R$107,1,(Settings!$B$5-1)*3+2))<1.5,1.5,IF((INDEX(Calculations!$D$107:$R$107,1,(Settings!$B$5-1)*3+2))<2,2,IF((INDEX(Calculations!$D$107:$R$107,1,(Settings!$B$5-1)*3+2))<4,4,"")))))="","",(IF((INDEX(Calculations!$D$107:$R$107,1,(Settings!$B$5-1)*3+2))<0,0,IF((INDEX(Calculations!$D$107:$R$107,1,(Settings!$B$5-1)*3+2))<1,1,IF((INDEX(Calculations!$D$107:$R$107,1,(Settings!$B$5-1)*3+2))<1.5,1.5,IF((INDEX(Calculations!$D$107:$R$107,1,(Settings!$B$5-1)*3+2))<2,2,IF((INDEX(Calculations!$D$107:$R$107,1,(Settings!$B$5-1)*3+2))<4,4,"")))))*(INDEX(Calculations!$D$91:$R$91,1,(Settings!$B$5-1)*3+2))-(INDEX(Calculations!$D$102:$R$102,1,(Settings!$B$5-1)*3+2)))/(Assumptions!$O$85*(INDEX(Calculations!$D$15:$R$15,1,(Settings!$B$5-1)*3+2)))),"") | C8: =IFERROR(IF(IF((INDEX(Calculations!$D$112:$R$112,1,(Settings!$B$5-1)*3+2))<0,0,IF((INDEX(Calculations!$D$112:$R$112,1,(Settings!$B$5-1)*3+2))<1,1,IF((INDEX(Calculations!$D$112:$R$112,1,(Settings!$B$5-1)*3+2))<1.5,1.5,IF((INDEX(Calculations!$D$112:$R$112,1,(Settings!$B$5-1)*3+2))<2,2,IF((INDEX(Calculations!$D$112:$R$112,1,(Settings!$B$5-1)*3+2))<4,4,"")))))="","",(IF((INDEX(Calculations!$D$112:$R$112,1,(Settings!$B$5-1)*3+2))<0,0,IF((INDEX(Calculations!$D$112:$R$112,1,(Settings!$B$5-1)*3+2))<1,1,IF((INDEX(Calculations!$D$112:$R$112,1,(Settings!$B$5-1)*3+2))<1.5,1.5,IF((INDEX(Calculations!$D$112:$R$112,1,(Settings!$B$5-1)*3+2))<2,2,IF((INDEX(Calculations!$D$112:$R$112,1,(Settings!$B$5-1)*3+2))<4,4,"")))))*(INDEX(Calculations!$D$91:$R$91,1,(Settings!$B$5-1)*3+2))-(INDEX(Calculations!$D$103:$R$103,1,(Settings!$B$5-1)*3+2)))/(Assumptions!$O$85*(INDEX(Calculations!$D$15:$R$15,1,(Settings!$B$5-1)*3+2)))),"") | D8: Loneliness value, causality unclear (row S6); sensitivity only
A9: Value of accredited qualifications (not in the ratios) | B9: =IFERROR((INDEX(Calculations!$D$127:$R$127,1,(Settings!$B$5-1)*3+2)),"") | C9: =IFERROR((INDEX(Calculations!$D$127:$R$127,1,(Settings!$B$5-1)*3+2)),"") | D9: Earnings values that overlap GVA (rows S10, S11)
A10: Benefit-cost ratio with streams outside the range rule put back (MHCLG 5.92 switching test) | B10: =IFERROR((INDEX(Calculations!$D$109:$R$109,1,(Settings!$B$5-1)*3+2)),"") | C10: =IFERROR((INDEX(Calculations!$D$114:$R$114,1,(Settings!$B$5-1)*3+2)),"") | D10: If this changes the category, the excluded stream matters to the value for money judgement
A11: Benefit-cost ratio without the offsetting transfers | B11: =IFERROR((INDEX(Calculations!$D$108:$R$108,1,(Settings!$B$5-1)*3+2)),"") | C11: =IFERROR((INDEX(Calculations!$D$113:$R$113,1,(Settings!$B$5-1)*3+2)),"") | D11: Shows how much of the ratio is rates relief and rent
A12: Benefit-cost ratio without optimism bias on fit-out and operator costs | B12: =IFERROR((INDEX(Calculations!$D$102:$R$102,1,(Settings!$B$5-1)*3+2))/((INDEX(Calculations!$D$91:$R$91,1,(Settings!$B$5-1)*3+2))-(INDEX(Calculations!$D$83:$R$83,1,(Settings!$B$5-1)*3+2))+(INDEX(Calculations!$D$83:$R$83,1,(Settings!$B$5-1)*3+2))/(1+(INDEX(Calculations!$D$82:$R$82,1,(Settings!$B$5-1)*3+2)))-(INDEX(Calculations!$D$84:$R$84,1,(Settings!$B$5-1)*3+2))+(INDEX(Calculations!$D$84:$R$84,1,(Settings!$B$5-1)*3+2))/(1+Assumptions!$O$19/100)),"") | C12: =IFERROR((INDEX(Calculations!$D$103:$R$103,1,(Settings!$B$5-1)*3+2))/((INDEX(Calculations!$D$91:$R$91,1,(Settings!$B$5-1)*3+2))-(INDEX(Calculations!$D$83:$R$83,1,(Settings!$B$5-1)*3+2))+(INDEX(Calculations!$D$83:$R$83,1,(Settings!$B$5-1)*3+2))/(1+(INDEX(Calculations!$D$82:$R$82,1,(Settings!$B$5-1)*3+2)))-(INDEX(Calculations!$D$84:$R$84,1,(Settings!$B$5-1)*3+2))+(INDEX(Calculations!$D$84:$R$84,1,(Settings!$B$5-1)*3+2))/(1+Assumptions!$O$19/100)),"") | D12: Shows how much the optimism bias uplifts matter
A14: To test the announced 3.0% discount rate, change it on the Settings sheet. The ratios recalculate throughout.

Sheet Compare
A1: Compare Proposals
A2: All five proposals on central assumptions, with the low to high range.
A4: Measure | B4: Proposal 1 | C4: Proposal 2 | D4: Proposal 3 | E4: Proposal 4 | F4: Proposal 5
A5: Name | B5: =IF(Inputs!C6="","",Inputs!C6) | C5: =IF(Inputs!D6="","",Inputs!D6) | D5: =IF(Inputs!E6="","",Inputs!E6) | E5: =IF(Inputs!F6="","",Inputs!F6) | F5: =IF(Inputs!G6="","",Inputs!G6)
A6: Use | B6: =IF(Inputs!C9="","",Inputs!C9) | C6: =IF(Inputs!D9="","",Inputs!D9) | D6: =IF(Inputs!E9="","",Inputs!E9) | E6: =IF(Inputs!F9="","",Inputs!F9) | F6: =IF(Inputs!G9="","",Inputs!G9)
A7: Centre | B7: =IF(Inputs!C7="","",Inputs!C7) | C7: =IF(Inputs!D7="","",Inputs!D7) | D7: =IF(Inputs!E7="","",Inputs!E7) | E7: =IF(Inputs!F7="","",Inputs!F7) | F7: =IF(Inputs!G7="","",Inputs!G7)
A8: Category, Gateshead | B8: =Calculations!E111 | C8: =Calculations!H111 | D8: =Calculations!K111 | E8: =Calculations!N111 | F8: =Calculations!Q111
A9: Benefit-cost ratio, Gateshead (central) | B9: =Calculations!E107 | C9: =Calculations!H107 | D9: =Calculations!K107 | E9: =Calculations!N107 | F9: =Calculations!Q107
A10: Range, Gateshead | B10: =IF(Calculations!D107="","",TEXT(Calculations!D107,"0.00")&" to "&TEXT(Calculations!F107,"0.00")) | C10: =IF(Calculations!G107="","",TEXT(Calculations!G107,"0.00")&" to "&TEXT(Calculations!I107,"0.00")) | D10: =IF(Calculations!J107="","",TEXT(Calculations!J107,"0.00")&" to "&TEXT(Calculations!L107,"0.00")) | E10: =IF(Calculations!M107="","",TEXT(Calculations!M107,"0.00")&" to "&TEXT(Calculations!O107,"0.00")) | F10: =IF(Calculations!P107="","",TEXT(Calculations!P107,"0.00")&" to "&TEXT(Calculations!R107,"0.00"))
A11: Category, UK | B11: =Calculations!E116 | C11: =Calculations!H116 | D11: =Calculations!K116 | E11: =Calculations!N116 | F11: =Calculations!Q116
A12: Benefit-cost ratio, UK (central) | B12: =Calculations!E112 | C12: =Calculations!H112 | D12: =Calculations!K112 | E12: =Calculations!N112 | F12: =Calculations!Q112
A13: Robustness | B13: =Calculations!E118 | C13: =Calculations!H118 | D13: =Calculations!K118 | E13: =Calculations!N118 | F13: =Calculations!Q118
A14: Net public cost | B14: =Calculations!E91 | C14: =Calculations!H91 | D14: =Calculations!K91 | E14: =Calculations!N91 | F14: =Calculations!Q91
A15: Council cost | B15: =Calculations!E93 | C15: =Calculations!H93 | D15: =Calculations!K93 | E15: =Calculations!N93 | F15: =Calculations!Q93
A16: Net FTE, Gateshead | B16: =Calculations!E38 | C16: =Calculations!H38 | D16: =Calculations!K38 | E16: =Calculations!N38 | F16: =Calculations!Q38
A17: GVA supported in Gateshead | B17: =Calculations!E44 | C17: =Calculations!H44 | D17: =Calculations!K44 | E17: =Calculations!N44 | F17: =Calculations!Q44
A18: GVA from visitor spend | B18: =Calculations!E124 | C18: =Calculations!H124 | D18: =Calculations!K124 | E18: =Calculations!N124 | F18: =Calculations!Q124

Sheet Settings
A1: Settings
A2: Changeable settings. Defaults follow current Treasury and MHCLG guidance.
A4: Setting | B4: Value | C4: Note
A5: Proposal shown on Results and Sensitivity (1 to 5) | B5: 1 | C5: Pick the proposal column
A6: Discount rate (real) | B6: =Assumptions!$O$5/100 | C6: Green Book 3.5%. The Chancellor has announced 3.0% at the 28 October 2026 Budget; type 3.0% here to test it until the guidance is revised
A7: Discount rate for wellbeing values | B7: =Assumptions!$O$6/100 | C7: Green Book health rate 1.5%
A8: Count employment wellbeing in the UK lens? | B8: No | C8: No by default. Green Book 8.41 assumes full displacement of jobs nationally, and Yes needs evidence signed off by a chief economist (8.42 to 8.43)
A9: Include the legacy of a permanent let in the ratios? | B9: No | C9: Off by default (decision 5). Uses the officer's chance of a permanent let that would not otherwise happen, at market rent for 10 years (row L2)

Sheet Static Data
A1: Static Data
A2: Reference figures keyed in once and reused until the next edition. Each has its edition date, and the status turns red after 12 months.
A4: Item | B4: Value | C4: Price year or unit | D4: Edition or date | E4: Source | F4: Status
A5: STEAM Gateshead day-visitor spend per visit (optional; overrides row X1) | C5: 2025 | E5: STEAM (keyed in by the economic intelligence team) | F5: =IF(B5="","Not entered",IF(ISNUMBER(D5),IF(TODAY()-D5>365,"Due for update","Current"),"Enter the edition date"))
A6: Small business multiplier (RV under £51,000) | B6: 0.432 | C6: 2026-27 | D6: 46318 | E6: GOV.UK, Estimate your business rates | F6: =IF(B6="","Not entered",IF(ISNUMBER(D6),IF(TODAY()-D6>365,"Due for update","Current"),"Enter the edition date"))
A7: Small business multiplier, retail, hospitality and leisure | B7: 0.382 | C7: 2026-27 | D7: 46318 | E7: GOV.UK, Estimate your business rates | F7: =IF(B7="","Not entered",IF(ISNUMBER(D7),IF(TODAY()-D7>365,"Due for update","Current"),"Enter the edition date"))
A8: Standard multiplier (RV £51,000 to £499,999) | B8: 0.48 | C8: 2026-27 | D8: 46318 | E8: GOV.UK, Estimate your business rates | F8: =IF(B8="","Not entered",IF(ISNUMBER(D8),IF(TODAY()-D8>365,"Due for update","Current"),"Enter the edition date"))
A9: Standard multiplier, retail, hospitality and leisure | B9: 0.43 | C9: 2026-27 | D9: 46318 | E9: GOV.UK, Estimate your business rates | F9: =IF(B9="","Not entered",IF(ISNUMBER(D9),IF(TODAY()-D9>365,"Due for update","Current"),"Enter the edition date"))
A10: Multiplier for RV £500,000 and over | B10: 0.508 | C10: 2026-27 | D10: 46318 | E10: GOV.UK, Estimate your business rates | F10: =IF(B10="","Not entered",IF(ISNUMBER(D10),IF(TODAY()-D10>365,"Due for update","Current"),"Enter the edition date"))
A11: Empty properties below this RV are exempt until reoccupied | B11: 2900 | C11: £ RV | D11: 46318 | E11: GOV.UK, Empty property relief | F11: =IF(B11="","Not entered",IF(ISNUMBER(D11),IF(TODAY()-D11>365,"Due for update","Current"),"Enter the edition date"))
A12: Small business rate relief: 100% up to this RV | B12: 12000 | C12: £ RV | D12: 46318 | E12: GOV.UK, Small business rate relief | F12: =IF(B12="","Not entered",IF(ISNUMBER(D12),IF(TODAY()-D12>365,"Due for update","Current"),"Enter the edition date"))
A13: Small business rate relief: tapers to 0% at this RV | B13: 15000 | C13: £ RV | D13: 46318 | E13: GOV.UK, Small business rate relief | F13: =IF(B13="","Not entered",IF(ISNUMBER(D13),IF(TODAY()-D13>365,"Due for update","Current"),"Enter the edition date"))
A14: Mandatory charitable rate relief | B14: 0.8 | C14: share | D14: 46318 | E14: GOV.UK, Charitable rate relief | F14: =IF(B14="","Not entered",IF(ISNUMBER(D14),IF(TODAY()-D14>365,"Due for update","Current"),"Enter the edition date"))
A15: Occupation that restarts the empty exemption | B15: 13 | C15: weeks | D15: 46318 | E15: SI 2024/323, in force 1 April 2024 | F15: =IF(B15="","Not entered",IF(ISNUMBER(D15),IF(TODAY()-D15>365,"Due for update","Current"),"Enter the edition date"))
A16: Empty property exemption | B16: 3 | C16: months | D16: 46318 | E16: GOV.UK, Empty property relief | F16: =IF(B16="","Not entered",IF(ISNUMBER(D16),IF(TODAY()-D16>365,"Due for update","Current"),"Enter the edition date"))
A18: GDP deflator, calendar years (2025 = 100), HM Treasury September 2026 file
A19: Year | B19: Index
A20: 2015 | B20: 72.6589
A21: 2016 | B21: 73.9044
A22: 2017 | B22: 74.99
A23: 2018 | B23: 76.4375
A24: 2019 | B24: 78.3418
A25: 2020 | B25: 82.2004
A26: 2021 | B26: 82.7095
A27: 2022 | B27: 87.4661
A28: 2023 | B28: 92.9927
A29: 2024 | B29: 96.5672
A30: 2025 | B30: 100
A31: 2026 | B31: 102.1831
A33: Council vacancy survey by centre (feeds the chance of a let anyway, row B1)
A34: Centre | B34: Tier | C34: Vacant units at first survey | D34: Of which still vacant at second survey | E34: Months between surveys | F34: Second survey date | G34: Annual re-let rate
A35: Gateshead Primary Shopping Area | B35: Gateshead Primary Shopping Area | G35: =IF(OR(C35="",C35=0,E35=""),"",1-(D35/C35)^(12/E35))
A36: Blaydon | B36: District Centre | G36: =IF(OR(C36="",C36=0,E36=""),"",1-(D36/C36)^(12/E36))
A37: Birtley | B37: District Centre | G37: =IF(OR(C37="",C37=0,E37=""),"",1-(D37/C37)^(12/E37))
A38: Coatsworth Road | B38: District Centre | G38: =IF(OR(C38="",C38=0,E38=""),"",1-(D38/C38)^(12/E38))
A39: Felling | B39: District Centre | G39: =IF(OR(C39="",C39=0,E39=""),"",1-(D39/C39)^(12/E39))
A40: Low Fell | B40: District Centre | G40: =IF(OR(C40="",C40=0,E40=""),"",1-(D40/C40)^(12/E40))
A41: Ryton | B41: District Centre | G41: =IF(OR(C41="",C41=0,E41=""),"",1-(D41/C41)^(12/E41))
A42: Whickham | B42: District Centre | G42: =IF(OR(C42="",C42=0,E42=""),"",1-(D42/C42)^(12/E42))
A43: Wrekenton | B43: District Centre | G43: =IF(OR(C43="",C43=0,E43=""),"",1-(D43/C43)^(12/E43))
A44: Askew Road | B44: Local Centre | G44: =IF(OR(C44="",C44=0,E44=""),"",1-(D44/C44)^(12/E44))
A45: Chopwell | B45: Local Centre | G45: =IF(OR(C45="",C45=0,E45=""),"",1-(D45/C45)^(12/E45))
A46: Crawcrook | B46: Local Centre | G46: =IF(OR(C46="",C46=0,E46=""),"",1-(D46/C46)^(12/E46))
... A59: Outside the hierarchy | B59: Outside the hierarchy | G59: =IF(OR(C59="",C59=0,E59=""),"",1-(D59/C59)^(12/E59))

Sheet Assumptions
A1: Assumptions
A2: From the approved register (research/register). The sheet is protected. Change a value only through the Local override column, with a reason; Results shows any override.
A4: ID | B4: Stream | C4: Parameter | D4: Applies to | E4: Unit | F4: Low | G4: Central | H4: High | I4: Pessimistic end | J4: Grade | K4: Local override | L4: Override reason | M4: Override grade | N4: Value, low scenario | O4: Value, central | P4: Value, high scenario | Q4: Grade used | R4: Source | S4: Edition | T4: Location | U4: Quote | V4: Notes | W4: Link
A5: A1 | B5: Prices and time | C5: Discount rate (social time preference rate) | D5: All costs and non-wellbeing benefits | E5: % a year | G5: 3.5 | J5: Rule | N5: =IF(K5<>"",K5,IF(I5="high",IF(H5="",G5,H5),IF(I5="low",IF(F5="",G5,F5),G5))) | O5: =IF(K5<>"",K5,G5) | P5: =IF(K5<>"",K5,IF(I5="high",IF(F5="",G5,F5),IF(I5="low",IF(H5="",G5,H5),G5))) | Q5: =IF(M5<>"",M5,J5) | R5: HM Treasury, Green Book 2026 | S5: February 2026 | T5: 6.54; discounting guidance 2.1 | U5: 3.5% in real terms for short-term proposals | V5: Watch item. The Chancellor has announced a cut to 3.0% and further Green Book reforms at the 28 October 2026 Budget (GOV.UK news, 'PM puts communities first in government investment rules shake up', 22 October 2026). The published Green Book still says 3.5%, so 3.5% stays until the revised guidance is published; editable in Settings | W5: Open source
A6: A2 | B6: Prices and time | C6: Health discount rate for wellbeing values | D6: All WELLBY-based values | E6: % a year | G6: 1.5 | J6: Rule | N6: =IF(K6<>"",K6,IF(I6="high",IF(H6="",G6,H6),IF(I6="low",IF(F6="",G6,F6),G6))) | O6: =IF(K6<>"",K6,G6) | P6: =IF(K6<>"",K6,IF(I6="high",IF(F6="",G6,F6),IF(I6="low",IF(H6="",G6,H6),G6))) | Q6: =IF(M6<>"",M6,J6) | R6: HM Treasury, Green Book supplementary guidance: discounting | S6: February 2026 | T6: 2.16 to 2.17 | U6: These health and life effects should be discounted at a lower rate of 1.5% | W6: Open source
A7: A3 | B7: Prices and time | C7: Price base | D7: All £ values | E7: year | G7: 2026-27 | J7: Rule | N7: =IF(K7<>"",K7,IF(I7="high",IF(H7="",G7,H7),IF(I7="low",IF(F7="",G7,F7),G7))) | O7: =IF(K7<>"",K7,G7) | P7: =IF(K7<>"",K7,IF(I7="high",IF(F7="",G7,F7),IF(I7="low",IF(H7="",G7,H7),G7))) | Q7: =IF(M7<>"",M7,J7) | R7: HM Treasury GDP deflators, September 2026 (Quarterly National Accounts) | S7: 1 October 2026 | T7: Financial-year and calendar-year columns | U7: Outturn data are as at the Quarterly National Accounts from ONS - last updated 30 September 2026. Forecast data are consistent with OBR EFO data as at the Spring Statement 3 March 2026. | V7: 2026-27 index 102.006 (2025-26 = 100), calendar 2026 index 102.183 (2025 = 100), both from OBR forecast growth. A new file is likely after the 28 October 2026 Budget | W7: Open source
A8: A4 | B8: Prices and time | C8: Uprating factor, 2019 calendar prices to 2026 | D8: Values quoted in 2019 prices | E8: multiplier | G8: 1.3043 | J8: Rule | N8: =IF(K8<>"",K8,IF(I8="high",IF(H8="",G8,H8),IF(I8="low",IF(F8="",G8,F8),G8))) | O8: =IF(K8<>"",K8,G8) | P8: =IF(K8<>"",K8,IF(I8="high",IF(F8="",G8,F8),IF(I8="low",IF(H8="",G8,H8),G8))) | Q8: =IF(M8<>"",M8,J8) | R8: HM Treasury GDP deflators, September 2026 | S8: 1 October 2026 | T8: Calendar-year column (ONS series MNF2) | U8: 2019 = 78.3418; 2026 = 102.183 (2025 = 100) | V8: Our calculation | W8: Open source
A9: A5 | B9: Prices and time | C9: WELLBY uprating factor, 2019 to 2026 prices and 2025 values | D9: All WELLBY-based values in 2019 prices | E9: multiplier | G9: 1.3221 | J9: Rule | N9: =IF(K9<>"",K9,IF(I9="high",IF(H9="",G9,H9),IF(I9="low",IF(F9="",G9,F9),G9))) | O9: =IF(K9<>"",K9,G9) | P9: =IF(K9<>"",K9,IF(I9="high",IF(F9="",G9,F9),IF(I9="low",IF(H9="",G9,H9),G9))) | Q9: =IF(M9<>"",M9,J9) | R9: HM Treasury, Wellbeing Guidance for Appraisal (2021), Annex 2; ONS IHXW | S9: Guidance July 2021; IHXW released 30 September 2026 | T9: Annex 2 uprating formula | U9: the WELLBY value should always be uprated to the appraisal base year using the formula above | V9: Deflator ratio 1.3043 x (real GDP per head 2025 42,313 / 2019 41,875) ^ 1.3. Real growth to 2025, the latest outturn year; our calculation | W9: Open source
A10: A6 | B10: Prices and time | C10: Value of one WELLBY | D10: Wellbeing values | E10: £ per WELLBY | F10: 13220.874 | G10: 17187.137 | H10: 21153.399 | I10: low | J10: Rule | N10: =IF(K10<>"",K10,IF(I10="high",IF(H10="",G10,H10),IF(I10="low",IF(F10="",G10,F10),G10))) | O10: =IF(K10<>"",K10,G10) | P10: =IF(K10<>"",K10,IF(I10="high",IF(F10="",G10,F10),IF(I10="low",IF(H10="",G10,H10),G10))) | Q10: =IF(M10<>"",M10,J10) | R10: HM Treasury, Wellbeing Guidance for Appraisal (2021) | S10: July 2021 (page updated 18 November 2022) | T10: Box 7 and Annex 2 | U10: multiplying by £13,000 [Low: £10,000, High £16,000]. This is the recommended standard value of one wellbeing adjusted life year | V10: 2019 values £10,000 / £13,000 / £16,000 uprated by A5 | W10: Open source
A11: A7 | B11: Prices and time | C11: Appraisal period | D11: All proposals | E11: years | G11: Occupation period | J11: Rule | N11: =IF(K11<>"",K11,IF(I11="high",IF(H11="",G11,H11),IF(I11="low",IF(F11="",G11,F11),G11))) | O11: =IF(K11<>"",K11,G11) | P11: =IF(K11<>"",K11,IF(I11="high",IF(F11="",G11,F11),IF(I11="low",IF(H11="",G11,H11),G11))) | Q11: =IF(M11<>"",M11,J11) | R11: HM Treasury, Green Book 2026 | S11: February 2026 | T11: 6.11 and 6.13 | U11: short defined-period proposals should consider the end of the contract (paraphrase of 6.13) | V11: Decision 11. Anything after the occupation period goes through the legacy switch (rows L1 to L3) | W11: Open source
A12: C1 | B12: Confidence and optimism bias | C12: Confidence grade 1: benefit reduction and cost uplift | D12: Benefit streams, and revenue cost lines other than C7 and C8 | E12: % | G12: benefits -0%, costs +0% | J12: Rule | N12: =IF(K12<>"",K12,IF(I12="high",IF(H12="",G12,H12),IF(I12="low",IF(F12="",G12,F12),G12))) | O12: =IF(K12<>"",K12,G12) | P12: =IF(K12<>"",K12,IF(I12="high",IF(F12="",G12,F12),IF(I12="low",IF(H12="",G12,H12),G12))) | Q12: =IF(M12<>"",M12,J12) | R12: HM Treasury, Supporting public service transformation: CBA guidance for local partnerships | S12: April 2014 | T12: Tables 7.A and 7.B; 7.18 to 7.19 | U12: The confidence grade which the CBA model applies to the data is determined by the lowest assessment in any of the descriptive columns. | V12: Displayed as High (1 to 2), Medium (3 to 4), Low (5 to 6). Decision 4. Applied literally in this register, so data over 5 years old is grade 6 | W12: Open source
A13: C2 | B13: Confidence and optimism bias | C13: Confidence grade 2: benefit reduction and cost uplift | D13: Benefit streams, and revenue cost lines other than C7 and C8 | E13: % | G13: benefits -5%, costs +5% | J13: Rule | N13: =IF(K13<>"",K13,IF(I13="high",IF(H13="",G13,H13),IF(I13="low",IF(F13="",G13,F13),G13))) | O13: =IF(K13<>"",K13,G13) | P13: =IF(K13<>"",K13,IF(I13="high",IF(F13="",G13,F13),IF(I13="low",IF(H13="",G13,H13),G13))) | Q13: =IF(M13<>"",M13,J13) | R13: HM Treasury, Supporting public service transformation: CBA guidance for local partnerships | S13: April 2014 | T13: Tables 7.A and 7.B; 7.18 to 7.19 | U13: The confidence grade which the CBA model applies to the data is determined by the lowest assessment in any of the descriptive columns. | V13: Displayed as High (1 to 2), Medium (3 to 4), Low (5 to 6). Decision 4. Applied literally in this register, so data over 5 years old is grade 6 | W13: Open source
A14: C3 | B14: Confidence and optimism bias | C14: Confidence grade 3: benefit reduction and cost uplift | D14: Benefit streams, and revenue cost lines other than C7 and C8 | E14: % | G14: benefits -10%, costs +10% | J14: Rule | N14: =IF(K14<>"",K14,IF(I14="high",IF(H14="",G14,H14),IF(I14="low",IF(F14="",G14,F14),G14))) | O14: =IF(K14<>"",K14,G14) | P14: =IF(K14<>"",K14,IF(I14="high",IF(F14="",G14,F14),IF(I14="low",IF(H14="",G14,H14),G14))) | Q14: =IF(M14<>"",M14,J14) | R14: HM Treasury, Supporting public service transformation: CBA guidance for local partnerships | S14: April 2014 | T14: Tables 7.A and 7.B; 7.18 to 7.19 | U14: The confidence grade which the CBA model applies to the data is determined by the lowest assessment in any of the descriptive columns. | V14: Displayed as High (1 to 2), Medium (3 to 4), Low (5 to 6). Decision 4. Applied literally in this register, so data over 5 years old is grade 6 | W14: Open source
A15: C4 | B15: Confidence and optimism bias | C15: Confidence grade 4: benefit reduction and cost uplift | D15: Benefit streams, and revenue cost lines other than C7 and C8 | E15: % | G15: benefits -15%, costs +15% | J15: Rule | N15: =IF(K15<>"",K15,IF(I15="high",IF(H15="",G15,H15),IF(I15="low",IF(F15="",G15,F15),G15))) | O15: =IF(K15<>"",K15,G15) | P15: =IF(K15<>"",K15,IF(I15="high",IF(F15="",G15,F15),IF(I15="low",IF(H15="",G15,H15),G15))) | Q15: =IF(M15<>"",M15,J15) | R15: HM Treasury, Supporting public service transformation: CBA guidance for local partnerships | S15: April 2014 | T15: Tables 7.A and 7.B; 7.18 to 7.19 | U15: The confidence grade which the CBA model applies to the data is determined by the lowest assessment in any of the descriptive columns. | V15: Displayed as High (1 to 2), Medium (3 to 4), Low (5 to 6). Decision 4. Applied literally in this register, so data over 5 years old is grade 6 | W15: Open source
A16: C5 | B16: Confidence and optimism bias | C16: Confidence grade 5: benefit reduction and cost uplift | D16: Benefit streams, and revenue cost lines other than C7 and C8 | E16: % | G16: benefits -25%, costs +25% | J16: Rule | N16: =IF(K16<>"",K16,IF(I16="high",IF(H16="",G16,H16),IF(I16="low",IF(F16="",G16,F16),G16))) | O16: =IF(K16<>"",K16,G16) | P16: =IF(K16<>"",K16,IF(I16="high",IF(F16="",G16,F16),IF(I16="low",IF(H16="",G16,H16),G16))) | Q16: =IF(M16<>"",M16,J16) | R16: HM Treasury, Supporting public service transformation: CBA guidance for local partnerships | S16: April 2014 | T16: Tables 7.A and 7.B; 7.18 to 7.19 | U16: The confidence grade which the CBA model applies to the data is determined by the lowest assessment in any of the descriptive columns. | V16: Displayed as High (1 to 2), Medium (3 to 4), Low (5 to 6). Decision 4. Applied literally in this register, so data over 5 years old is grade 6 | W16: Open source
A17: C6 | B17: Confidence and optimism bias | C17: Confidence grade 6: benefit reduction and cost uplift | D17: Benefit streams, and revenue cost lines other than C7 and C8 | E17: % | G17: benefits -40%, costs +40% | J17: Rule | N17: =IF(K17<>"",K17,IF(I17="high",IF(H17="",G17,H17),IF(I17="low",IF(F17="",G17,F17),G17))) | O17: =IF(K17<>"",K17,G17) | P17: =IF(K17<>"",K17,IF(I17="high",IF(F17="",G17,F17),IF(I17="low",IF(H17="",G17,H17),G17))) | Q17: =IF(M17<>"",M17,J17) | R17: HM Treasury, Supporting public service transformation: CBA guidance for local partnerships | S17: April 2014 | T17: Tables 7.A and 7.B; 7.18 to 7.19 | U17: The confidence grade which the CBA model applies to the data is determined by the lowest assessment in any of the descriptive columns. | V17: Displayed as High (1 to 2), Medium (3 to 4), Low (5 to 6). Decision 4. Applied literally in this register, so data over 5 years old is grade 6 | W17: Open source
A18: C7 | B18: Confidence and optimism bias | C18: Capital fit-out optimism bias | D18: Fit-out and works costs | E18: % uplift | F18: 4 | G18: 51 | H18: 51 | I18: high | J18: Rule | N18: =IF(K18<>"",K18,IF(I18="high",IF(H18="",G18,H18),IF(I18="low",IF(F18="",G18,F18),G18))) | O18: =IF(K18<>"",K18,G18) | P18: =IF(K18<>"",K18,IF(I18="high",IF(F18="",G18,F18),IF(I18="low",IF(H18="",G18,H18),G18))) | Q18: =IF(M18<>"",M18,J18) | R18: HM Treasury, Supplementary Green Book guidance: optimism bias; MHCLG Appraisal Guide Annex F | S18: 2013 page date; MHCLG February 2026 | T18: Step Two heading before 3.11; Table 1 (non-standard buildings); MHCLG Annex F F7 | U18: Always start with the upper bound | V18: Non-standard buildings include refurbishment projects (paraphrase of the guidance's definitions). Starts at 51% at proposal stage and steps towards 4% as the Treasury mitigation questions are answered (stage selector). Decision 10 | W18: Open source
A19: C8 | B19: Confidence and optimism bias | C19: Contracted operator cost optimism bias | D19: Operator or management contract costs | E19: % uplift | F19: 0 | G19: 41 | H19: 41 | I19: high | J19: Rule | N19: =IF(K19<>"",K19,IF(I19="high",IF(H19="",G19,H19),IF(I19="low",IF(F19="",G19,F19),G19))) | O19: =IF(K19<>"",K19,G19) | P19: =IF(K19<>"",K19,IF(I19="high",IF(F19="",G19,F19),IF(I19="low",IF(H19="",G19,H19),G19))) | Q19: =IF(M19<>"",M19,J19) | R19: HM Treasury, Supplementary Green Book guidance: optimism bias | S19: 2013 page date | T19: Table 1 (outsourcing); 4.1 | U19: Mott MacDonald was unable to recommend sound upper and lower bound optimism bias levels for operating expenditure (except for outsourcing projects) | V19: Applying the outsourcing bound to a meanwhile operator contract is our judgement, labelled as such | W19: Open source
A20: C9 | B20: Confidence and optimism bias | C20: Value for money categories | D20: Results | E20: benefit-cost ratio bands | G20: Very High >=4; High 2-4; Medium 1.5-2; Acceptable 1-1.5; Poor 0-1; Very Poor <0 | J20: Rule | N20: =IF(K20<>"",K20,IF(I20="high",IF(H20="",G20,H20),IF(I20="low",IF(F20="",G20,F20),G20))) | O20: =IF(K20<>"",K20,G20) | P20: =IF(K20<>"",K20,IF(I20="high",IF(F20="",G20,F20),IF(I20="low",IF(H20="",G20,H20),G20))) | Q20: =IF(M20<>"",M20,J20) | R20: MHCLG Appraisal Guide, 4th edition | S20: February 2026 | T20: 3.55 | U20: The following VfM categories can be defined where public sector costs are positive | W20: Open source
A21: C10 | B21: Confidence and optimism bias | C21: Range rule for uncertain streams | D21: Any monetised stream | E21: ratio | G21: 4 | J21: Rule | N21: =IF(K21<>"",K21,IF(I21="high",IF(H21="",G21,H21),IF(I21="low",IF(F21="",G21,F21),G21))) | O21: =IF(K21<>"",K21,G21) | P21: =IF(K21<>"",K21,IF(I21="high",IF(F21="",G21,F21),IF(I21="low",IF(H21="",G21,H21),G21))) | Q21: =IF(M21<>"",M21,J21) | R21: MHCLG Appraisal Guide, 4th edition | S21: February 2026 | T21: 5.92 | U21: where the uncertain range exceeds four times the midpoint, the monetised figure is not reported and switching values are used instead (paraphrase) | V21: Watch item. The rule sits in the guide's health valuation context; applying it to every stream is our extension | W21: Open source
A22: B1 | B22: Business as Usual | C22: Chance the unit is let commercially anyway during the occupation period | D22: BAU column, all proposals | E22: % | F22: 10 | G22: 20 | H22: 40 | I22: high | J22: 6 | N22: =IF(K22<>"",K22,IF(I22="high",IF(H22="",G22,H22),IF(I22="low",IF(F22="",G22,F22),G22))) | O22: =IF(K22<>"",K22,G22) | P22: =IF(K22<>"",K22,IF(I22="high",IF(F22="",G22,F22),IF(I22="low",IF(H22="",G22,H22),G22))) | Q22: =IF(M22<>"",M22,J22) | R22: Open Doors Pilot Programme evaluation (IFF Research for MHCLG); HSRA explanatory memorandum | S22: November 2020; 2024 | T22: Executive summary (counterfactual exercise); EM 5.2 | U22: Three of the five landlords who were not part of the Open Doors scheme ... said their properties were vacant at the time of interview (Open Doors). Over eight in ten of these vacant properties have been empty for more than two years (Whythawk 2021, quoted in EM 5.2). | V22: High = Open Doors counterfactual (2 of 5 not reported vacant; tiny sample). Low and central are our judgement for units vacant over a year. Override with the council's own vacancy register where held | W22: Open source
A23: B2 | B23: Business as Usual | C23: Empty property rates exemption | D23: BAU rates position | E23: months | G23: 3 | J23: Rule | N23: =IF(K23<>"",K23,IF(I23="high",IF(H23="",G23,H23),IF(I23="low",IF(F23="",G23,F23),G23))) | O23: =IF(K23<>"",K23,G23) | P23: =IF(K23<>"",K23,IF(I23="high",IF(F23="",G23,F23),IF(I23="low",IF(H23="",G23,H23),G23))) | Q23: =IF(M23<>"",M23,J23) | R23: GOV.UK, Empty property relief | S23: Checked 23 October 2026 | T23: Standard relief | U23: you do not have to pay business rates on your empty property for 3 months | V23: After 3 months most owners pay full rates. Listed buildings and RV under £2,900 exempt until reoccupied | W23: Open source
A24: B3 | B24: Business as Usual | C24: Occupation needed to restart the empty rates exemption | D24: Transfer line (landlord rates) | E24: weeks | G24: 13 | J24: Rule | N24: =IF(K24<>"",K24,IF(I24="high",IF(H24="",G24,H24),IF(I24="low",IF(F24="",G24,F24),G24))) | O24: =IF(K24<>"",K24,G24) | P24: =IF(K24<>"",K24,IF(I24="high",IF(F24="",G24,F24),IF(I24="low",IF(H24="",G24,H24),G24))) | Q24: =IF(M24<>"",M24,J24) | R24: Non-Domestic Rating (Unoccupied Property) (England) (Amendment) Regulations 2024, SI 2024/323 | S24: In force 1 April 2024 | T24: Regulation 2 | U24: in regulation 5 (continuous occupation), for "six weeks" substitute "13 weeks" | V24: A meanwhile occupation of 13 weeks or more restarts the landlord's 3-month exemption afterwards: a transfer from the council to the landlord | W24: Open source
A25: B4 | B25: Business as Usual | C25: Business rates multipliers 2026-27 | D25: Rates lines | E25: pence per £ RV | G25: Small RHL 38.2; small other 43.2; standard RHL 43.0; standard other 48.0; RV £500,000+ 50.8 | J25: Rule | N25: =IF(K25<>"",K25,IF(I25="high",IF(H25="",G25,H25),IF(I25="low",IF(F25="",G25,F25),G25))) | O25: =IF(K25<>"",K25,G25) | P25: =IF(K25<>"",K25,IF(I25="high",IF(F25="",G25,F25),IF(I25="low",IF(H25="",G25,H25),G25))) | Q25: =IF(M25<>"",M25,J25) | R25: GOV.UK, Estimate your business rates | S25: Checked 23 October 2026 | T25: England, 2026 to 2027 | U25: 43.2 pence if your rateable value is below £51,000 ... 38.2 pence if your rateable value is below £51,000 | V25: RHL rates apply to eligible occupied properties only; small multipliers apply where RV is below £51,000 | W25: Open source
A26: B5 | B26: Business as Usual | C26: Small business rate relief | D26: Occupier rates, transfer line | E26: RV thresholds | G26: 100% to £12,000; tapers to 0% at £15,000 | J26: Rule | N26: =IF(K26<>"",K26,IF(I26="high",IF(H26="",G26,H26),IF(I26="low",IF(F26="",G26,F26),G26))) | O26: =IF(K26<>"",K26,G26) | P26: =IF(K26<>"",K26,IF(I26="high",IF(F26="",G26,F26),IF(I26="low",IF(H26="",G26,H26),G26))) | Q26: =IF(M26<>"",M26,J26) | R26: GOV.UK, Small business rate relief | S26: Checked 23 October 2026 | T26: Thresholds | U26: You will not pay business rates on a property with a rateable value of £12,000 or less | W26: Open source
A27: B6 | B27: Business as Usual | C27: Charitable rate relief | D27: Occupier rates where a charity occupies | E27: % | G27: 80 | H27: 100 | J27: Rule | N27: =IF(K27<>"",K27,IF(I27="high",IF(H27="",G27,H27),IF(I27="low",IF(F27="",G27,F27),G27))) | O27: =IF(K27<>"",K27,G27) | P27: =IF(K27<>"",K27,IF(I27="high",IF(F27="",G27,F27),IF(I27="low",IF(H27="",G27,H27),G27))) | Q27: =IF(M27<>"",M27,J27) | R27: GOV.UK, Charitable rate relief | S27: Checked 23 October 2026 | U27: Charitable rate relief gives you up to 80% off your business rates bill ... Your local council may also be able to top up the discount | V27: High = 100% where the council tops up with discretionary relief (as in Open Doors, where the programme paid the remaining 20%) | W27: Open source
A28: B7 | B28: Business as Usual | C28: Holding cost of a council-owned empty unit | D28: BAU cost, council-owned units only | E28: % of existing value a year | G28: 2 | J28: Rule | N28: =IF(K28<>"",K28,IF(I28="high",IF(H28="",G28,H28),IF(I28="low",IF(F28="",G28,F28),G28))) | O28: =IF(K28<>"",K28,G28) | P28: =IF(K28<>"",K28,IF(I28="high",IF(F28="",G28,F28),IF(I28="low",IF(H28="",G28,H28),G28))) | Q28: =IF(M28<>"",M28,J28) | R28: MHCLG Appraisal Guide technical annex | S28: 18 February 2026 | T28: Annex A10 and D17 | U28: industry standards indicate these can be assumed to be 2% of the existing value of the land per year | V28: Alternative to B9, used only without site-specific evidence: the annex holding cost covers maintenance and security. It applies to the unit's book or market value; with an existing use value of zero (B8) it gives zero, so B9 carries the cost | W28: Open source
A29: B8 | B29: Business as Usual | C29: Existing use value of a long-vacant unit | D29: Value of space | E29: £ | G29: 0 | J29: Rule | N29: =IF(K29<>"",K29,IF(I29="high",IF(H29="",G29,H29),IF(I29="low",IF(F29="",G29,F29),G29))) | O29: =IF(K29<>"",K29,G29) | P29: =IF(K29<>"",K29,IF(I29="high",IF(F29="",G29,F29),IF(I29="low",IF(H29="",G29,H29),G29))) | Q29: =IF(M29<>"",M29,J29) | R29: MHCLG Appraisal Guide technical annex | S29: 18 February 2026 | T29: Annex A7 | U29: where there is no active economic use of the site and there will not be for the foreseeable future without public sector intervention, it may be appropriate to apply an existing use value of zero | W29: Open source
A30: B9 | B30: Business as Usual | C30: Security, inspection and maintenance of an empty unit | D30: BAU cost | E30: £ a year | G30: User input | J30: 6 | N30: =IF(K30<>"",K30,IF(I30="high",IF(H30="",G30,H30),IF(I30="low",IF(F30="",G30,F30),G30))) | O30: =IF(K30<>"",K30,G30) | P30: =IF(K30<>"",K30,IF(I30="high",IF(F30="",G30,F30),IF(I30="low",IF(H30="",G30,H30),G30))) | Q30: =IF(M30<>"",M30,J30) | R30: No published benchmark found | V30: Evidence gap. Officer enters the council's own cost; flagged until entered
A31: V1 | B31: Value of the space | C31: Market rent (high value of the space) | D31: Both ratios | E31: £ a year | G31: Unit rateable value x V3 | J31: 3 | N31: =IF(K31<>"",K31,IF(I31="high",IF(H31="",G31,H31),IF(I31="low",IF(F31="",G31,F31),G31))) | O31: =IF(K31<>"",K31,G31) | P31: =IF(K31<>"",K31,IF(I31="high",IF(F31="",G31,F31),IF(I31="low",IF(H31="",G31,H31),G31))) | Q31: =IF(M31<>"",M31,J31) | R31: GOV.UK, How your rates are calculated; VOA Find a business rates valuation (per property) | S31: 2026 rating list, valuation date 1 April 2024 | U31: This is its open market rental value on 1 April 2024, based on an estimate by the Valuation Office (VO). | V31: Officer looks up the unit's rateable value (free, per property). The bulk VOA list needs a restricted licence and is not used | W31: Open source
A32: V2 | B32: Value of the space | C32: Rent a comparable meanwhile occupier pays (low value of the space) | D32: Both ratios | E32: £ a year | G32: Rent actually agreed | J32: 5 | N32: =IF(K32<>"",K32,IF(I32="high",IF(H32="",G32,H32),IF(I32="low",IF(F32="",G32,F32),G32))) | O32: =IF(K32<>"",K32,G32) | P32: =IF(K32<>"",K32,IF(I32="high",IF(F32="",G32,F32),IF(I32="low",IF(H32="",G32,H32),G32))) | Q32: =IF(M32<>"",M32,J32) | R32: Revealed preference: the occupier's own rent | T32: Green Book 8.6 valuation hierarchy (market prices first) | V32: Zero where the occupier pays no rent. Central = midpoint of V1 and V2 (our judgement). Grade 5 so the 25% benefit cut applies; decision 2. V1 and V2 are both netted for the chance of a let anyway (B1)
A33: V3 | B33: Value of the space | C33: Uprating, 2024-25 rental values to 2026-27 | D33: V1 | E33: multiplier | G33: 1.0542 | J33: Rule | N33: =IF(K33<>"",K33,IF(I33="high",IF(H33="",G33,H33),IF(I33="low",IF(F33="",G33,F33),G33))) | O33: =IF(K33<>"",K33,G33) | P33: =IF(K33<>"",K33,IF(I33="high",IF(F33="",G33,F33),IF(I33="low",IF(H33="",G33,H33),G33))) | Q33: =IF(M33<>"",M33,J33) | R33: HM Treasury GDP deflators, September 2026 | S33: 1 October 2026 | T33: Financial-year column | U33: 2024-25 = 96.757; 2026-27 = 102.006 | V33: Our calculation; a general price deflator, not a rent index | W33: Open source
A34: V4 | B34: Value of the space | C34: Rent paid by the council to a private landlord | D34: Cost and transfer lines | E34: £ a year | G34: Officer input | J34: Rule | N34: =IF(K34<>"",K34,IF(I34="high",IF(H34="",G34,H34),IF(I34="low",IF(F34="",G34,F34),G34))) | O34: =IF(K34<>"",K34,G34) | P34: =IF(K34<>"",K34,IF(I34="high",IF(F34="",G34,F34),IF(I34="low",IF(H34="",G34,H34),G34))) | Q34: =IF(M34<>"",M34,J34) | R34: MHCLG Appraisal Guide, 4th edition | S34: February 2026 | T34: 3.34 and footnote 15 | V34: Decisions 2 and 12. A transfer: counted in net public cost with an equal offsetting benefit to the landlord. The value of the space (V1, V2) is the occupier's use of it, a separate benefit, so nothing is counted twice. Rent the occupier pays is a transfer between private parties and is left out | W34: Open source
A35: J1 | B35: Jobs | C35: Employment density (floor area per FTE) | D35: Pop-up retail | E35: m2 per FTE | F35: 15 | G35: 17.5 | H35: 20 | I35: high | J35: 6 | N35: =IF(K35<>"",K35,IF(I35="high",IF(H35="",G35,H35),IF(I35="low",IF(F35="",G35,F35),G35))) | O35: =IF(K35<>"",K35,G35) | P35: =IF(K35<>"",K35,IF(I35="high",IF(F35="",G35,F35),IF(I35="low",IF(H35="",G35,H35),G35))) | Q35: =IF(M35<>"",M35,J35) | R35: HCA Employment Density Guide, 3rd edition (Bilfinger GVA) | S35: November 2015 | T35: Section 4 density matrix, page 29 | U35: A1 retail, high street (NIA) | V35: Low density = more jobs. Central is the midpoint (our calculation). The Guide says it should not be relied on for appraisals needing central government approval; the method note says so | W35: Open source
A36: J2 | B36: Jobs | C36: Employment density (floor area per FTE) | D36: Food and drink | E36: m2 per FTE | F36: 15 | G36: 17.5 | H36: 20 | I36: high | J36: 6 | N36: =IF(K36<>"",K36,IF(I36="high",IF(H36="",G36,H36),IF(I36="low",IF(F36="",G36,F36),G36))) | O36: =IF(K36<>"",K36,G36) | P36: =IF(K36<>"",K36,IF(I36="high",IF(F36="",G36,F36),IF(I36="low",IF(H36="",G36,H36),G36))) | Q36: =IF(M36<>"",M36,J36) | R36: HCA Employment Density Guide, 3rd edition (Bilfinger GVA) | S36: November 2015 | T36: Section 4 density matrix, page 29 | U36: A3 restaurants and cafes (NIA) | V36: Low density = more jobs. Central is the midpoint (our calculation). The Guide says it should not be relied on for appraisals needing central government approval; the method note says so | W36: Open source
A37: J3 | B37: Jobs | C37: Employment density (floor area per FTE) | D37: Creative studios and makers | E37: m2 per FTE | F37: 15 | G37: 27.5 | H37: 40 | I37: high | J37: 6 | N37: =IF(K37<>"",K37,IF(I37="high",IF(H37="",G37,H37),IF(I37="low",IF(F37="",G37,F37),G37))) | O37: =IF(K37<>"",K37,G37) | P37: =IF(K37<>"",K37,IF(I37="high",IF(F37="",G37,F37),IF(I37="low",IF(H37="",G37,H37),G37))) | Q37: =IF(M37<>"",M37,J37) | R37: HCA Employment Density Guide, 3rd edition (Bilfinger GVA) | S37: November 2015 | T37: Section 4 density matrix, page 29 | U37: Studio 20-40; maker spaces 15-40 (various) | V37: Low density = more jobs. Central is the midpoint (our calculation). The Guide says it should not be relied on for appraisals needing central government approval; the method note says so | W37: Open source
A38: J4 | B38: Jobs | C38: Employment density (floor area per FTE) | D38: Workspace and co-working | E38: m2 per FTE | F38: 10 | G38: 28.5 | H38: 47 | I38: high | J38: 6 | N38: =IF(K38<>"",K38,IF(I38="high",IF(H38="",G38,H38),IF(I38="low",IF(F38="",G38,F38),G38))) | O38: =IF(K38<>"",K38,G38) | P38: =IF(K38<>"",K38,IF(I38="high",IF(F38="",G38,F38),IF(I38="low",IF(H38="",G38,H38),G38))) | Q38: =IF(M38<>"",M38,J38) | R38: HCA Employment Density Guide, 3rd edition (Bilfinger GVA) | S38: November 2015 | T38: Section 4 density matrix, page 29 | U38: Co-working 10-15; managed workspace 12-47 (various) | V38: Low density = more jobs. Central is the midpoint (our calculation). The Guide says it should not be relied on for appraisals needing central government approval; the method note says so | W38: Open source
A39: J5 | B39: Jobs | C39: Employment density (floor area per FTE) | D39: Health and wellbeing | E39: m2 per FTE | F39: 65 | G39: 82.5 | H39: 100 | I39: high | J39: 6 | N39: =IF(K39<>"",K39,IF(I39="high",IF(H39="",G39,H39),IF(I39="low",IF(F39="",G39,F39),G39))) | O39: =IF(K39<>"",K39,G39) | P39: =IF(K39<>"",K39,IF(I39="high",IF(F39="",G39,F39),IF(I39="low",IF(H39="",G39,H39),G39))) | Q39: =IF(M39<>"",M39,J39) | R39: HCA Employment Density Guide, 3rd edition (Bilfinger GVA) | S39: November 2015 | T39: Section 4 density matrix, page 29 | U39: Fitness centres: mid-market 65, budget 100 (GIA) | V39: Low density = more jobs. Central is the midpoint (our calculation). The Guide says it should not be relied on for appraisals needing central government approval; the method note says so | W39: Open source
A40: J6 | B40: Jobs | C40: Employment density (floor area per FTE) | D40: Arts, culture and events | E40: m2 per FTE | F40: 30 | G40: Officer staffing, else J18 | H40: 300 | I40: high | J40: 6 | N40: =IF(K40<>"",K40,IF(I40="high",IF(H40="",G40,H40),IF(I40="low",IF(F40="",G40,F40),G40))) | O40: =IF(K40<>"",K40,G40) | P40: =IF(K40<>"",K40,IF(I40="high",IF(F40="",G40,F40),IF(I40="low",IF(H40="",G40,H40),G40))) | Q40: =IF(M40<>"",M40,J40) | R40: HCA Employment Density Guide, 3rd edition | S40: November 2015 | T40: Section 4 matrix; 5.14 to 5.16 | U40: Visitor and cultural attractions 30-300 (GIA) | V40: The Guide says a single density is 'impossible' for cultural uses and that its venue proxies 'should not be used as the basis for specific calculations themselves' (5.16). 30 to 300 is kept only as a plausibility check on the officer's figure | W40: Open source
A41: J7 | B41: Jobs | C41: Employment density (floor area per FTE) | D41: Community hub | E41: m2 per FTE | G41: No published density | J41: 6 | N41: =IF(K41<>"",K41,IF(I41="high",IF(H41="",G41,H41),IF(I41="low",IF(F41="",G41,F41),G41))) | O41: =IF(K41<>"",K41,G41) | P41: =IF(K41<>"",K41,IF(I41="high",IF(F41="",G41,F41),IF(I41="low",IF(H41="",G41,H41),G41))) | Q41: =IF(M41<>"",M41,J41) | R41: HCA Employment Density Guide, 3rd edition | S41: November 2015 | T41: 5.25 to 5.29 | U41: no 'general' employment density | V41: Use the officer's own staffing figure, else the ONS FTE per local unit for the matching industry (J16) | W41: Open source
A42: J8 | B42: Jobs | C42: Employment density (floor area per FTE) | D42: Training and skills | E42: m2 per FTE | G42: No published density | J42: 6 | N42: =IF(K42<>"",K42,IF(I42="high",IF(H42="",G42,H42),IF(I42="low",IF(F42="",G42,F42),G42))) | O42: =IF(K42<>"",K42,G42) | P42: =IF(K42<>"",K42,IF(I42="high",IF(F42="",G42,F42),IF(I42="low",IF(H42="",G42,H42),G42))) | Q42: =IF(M42<>"",M42,J42) | R42: HCA Employment Density Guide, 3rd edition | S42: November 2015 | T42: 5.25 to 5.29 | U42: no 'general' employment density | V42: Use the officer's own staffing figure, else the ONS FTE per local unit for the matching industry (J17) | W42: Open source
A43: J9 | B43: Jobs | C43: Activity factor: share of the space in use, against a fully occupied unit | D43: All uses | E43: % | F43: 50 | G43: 70 | H43: 90 | I43: low | J43: 6 | N43: =IF(K43<>"",K43,IF(I43="high",IF(H43="",G43,H43),IF(I43="low",IF(F43="",G43,F43),G43))) | O43: =IF(K43<>"",K43,G43) | P43: =IF(K43<>"",K43,IF(I43="high",IF(F43="",G43,F43),IF(I43="low",IF(H43="",G43,H43),G43))) | Q43: =IF(M43<>"",M43,J43) | R43: HCA Employment Density Guide, 3rd edition | S43: November 2015 | T43: 2.15 to 2.16 | U43: There is no 'rule of thumb' to allocate a vacancy rate ... sensitivity analysis is used to generate a number of vacancy rate scenarios (e.g. 50%, 70%, 90%) | V43: The Guide's scenarios are for building vacancy; we use them for how fully a meanwhile unit is used (studios let, hours open), which is our extension. Open Doors sites were in use for 56% to 83% of available hours in February 2020. The officer can replace this with opening hours as a share of a full-time week | W43: Open source
A44: J10 | B44: Jobs | C44: Part-time to full-time conversion | D44: Officer staffing override | E44: part-time posts per FTE | G44: 2 | J44: 6 | N44: =IF(K44<>"",K44,IF(I44="high",IF(H44="",G44,H44),IF(I44="low",IF(F44="",G44,F44),G44))) | O44: =IF(K44<>"",K44,G44) | P44: =IF(K44<>"",K44,IF(I44="high",IF(F44="",G44,F44),IF(I44="low",IF(H44="",G44,H44),G44))) | Q44: =IF(M44<>"",M44,J44) | R44: HCA Employment Density Guide, 3rd edition | S44: November 2015 | T44: 2.20 to 2.22 | U44: A ratio of 2:1 part-time staff to FTE should therefore be applied. | W44: Open source
A45: J11 | B45: Jobs | C45: Net to gross internal area, retail units | D45: Floor area conversion | E45: % | G45: 90 | J45: 6 | N45: =IF(K45<>"",K45,IF(I45="high",IF(H45="",G45,H45),IF(I45="low",IF(F45="",G45,F45),G45))) | O45: =IF(K45<>"",K45,G45) | P45: =IF(K45<>"",K45,IF(I45="high",IF(F45="",G45,F45),IF(I45="low",IF(H45="",G45,H45),G45))) | Q45: =IF(M45<>"",M45,J45) | R45: HCA Employment Density Guide, 3rd edition | S45: November 2015 | T45: 2.10 | U45: for retail units the net to gross internal area relationship can be in the region of 90% | V45: Other uses: gross typically 15% to 20% above net (2.10 to 2.12) | W45: Open source
A46: J12 | B46: Jobs | C46: FTE per local unit, SIC 47 (cross-check) | D46: Pop-up retail | E46: FTE per local unit | F46: 6.3157 | G46: 8.3832 | H46: 8.3832 | J46: 3 | N46: =IF(K46<>"",K46,IF(I46="high",IF(H46="",G46,H46),IF(I46="low",IF(F46="",G46,F46),G46))) | O46: =IF(K46<>"",K46,G46) | P46: =IF(K46<>"",K46,IF(I46="high",IF(F46="",G46,F46),IF(I46="low",IF(H46="",G46,H46),G46))) | Q46: =IF(M46<>"",M46,J46) | R46: ONS BRES 2024 (NOMIS NM_189_1) and UK Business Counts March 2025 (NOMIS NM_141_1) | S46: BRES 2024 (next: 18 November 2026); UKBC March 2025 | T46: Gateshead, North East, England and Wales | V46: Central = Gateshead; low and high = lowest and highest of Gateshead, North East and England and Wales. FTE = full-time + part-time / 2. Averages are pulled up by larger units. BRES cells are rounded; our calculation | W46: Open source
A47: J13 | B47: Jobs | C47: FTE per local unit, SIC 56 (cross-check) | D47: Food and drink | E47: FTE per local unit | F47: 5.8979 | G47: 5.9406 | H47: 7.1031 | J47: 3 | N47: =IF(K47<>"",K47,IF(I47="high",IF(H47="",G47,H47),IF(I47="low",IF(F47="",G47,F47),G47))) | O47: =IF(K47<>"",K47,G47) | P47: =IF(K47<>"",K47,IF(I47="high",IF(F47="",G47,F47),IF(I47="low",IF(H47="",G47,H47),G47))) | Q47: =IF(M47<>"",M47,J47) | R47: ONS BRES 2024 (NOMIS NM_189_1) and UK Business Counts March 2025 (NOMIS NM_141_1) | S47: BRES 2024 (next: 18 November 2026); UKBC March 2025 | T47: Gateshead, North East, England and Wales | V47: Central = Gateshead; low and high = lowest and highest of Gateshead, North East and England and Wales. FTE = full-time + part-time / 2. Averages are pulled up by larger units. BRES cells are rounded; our calculation | W47: Open source
A48: J14 | B48: Jobs | C48: FTE per local unit, SIC 90 (cross-check) | D48: Creative studios and makers | E48: FTE per local unit | F48: 2.2414 | G48: 2.4074 | H48: 2.4074 | J48: 3 | N48: =IF(K48<>"",K48,IF(I48="high",IF(H48="",G48,H48),IF(I48="low",IF(F48="",G48,F48),G48))) | O48: =IF(K48<>"",K48,G48) | P48: =IF(K48<>"",K48,IF(I48="high",IF(F48="",G48,F48),IF(I48="low",IF(H48="",G48,H48),G48))) | Q48: =IF(M48<>"",M48,J48) | R48: ONS BRES 2024 (NOMIS NM_189_1) and UK Business Counts March 2025 (NOMIS NM_141_1) | S48: BRES 2024 (next: 18 November 2026); UKBC March 2025 | T48: Gateshead, North East, England and Wales | V48: Central = North East; low and high from North East and England and Wales only. For Gateshead, BRES 2024 shows 500 employees in SIC 90 while all 60 of its local units employ fewer than 10 (March 2026 size-band count; the March 2025 unit count is also 60), so the two sources disagree for this cell and the Gateshead figure is not used. FTE = full-time + part-time / 2; our calculation | W48: Open source
A49: J15 | B49: Jobs | C49: FTE per local unit, SIC 74 (cross-check) | D49: Workspace and co-working | E49: FTE per local unit | F49: 2.3018 | G49: 5.6481 | H49: 5.6481 | J49: 3 | N49: =IF(K49<>"",K49,IF(I49="high",IF(H49="",G49,H49),IF(I49="low",IF(F49="",G49,F49),G49))) | O49: =IF(K49<>"",K49,G49) | P49: =IF(K49<>"",K49,IF(I49="high",IF(F49="",G49,F49),IF(I49="low",IF(H49="",G49,H49),G49))) | Q49: =IF(M49<>"",M49,J49) | R49: ONS BRES 2024 (NOMIS NM_189_1) and UK Business Counts March 2025 (NOMIS NM_141_1) | S49: BRES 2024 (next: 18 November 2026); UKBC March 2025 | T49: Gateshead, North East, England and Wales | V49: Central = Gateshead; low and high = lowest and highest of Gateshead, North East and England and Wales. FTE = full-time + part-time / 2. Averages are pulled up by larger units. BRES cells are rounded; our calculation | W49: Open source
A50: J16 | B50: Jobs | C50: FTE per local unit, SIC 94 (cross-check) | D50: Community hub | E50: FTE per local unit | F50: 7.8427 | G50: 9.2308 | H50: 9.2308 | J50: 3 | N50: =IF(K50<>"",K50,IF(I50="high",IF(H50="",G50,H50),IF(I50="low",IF(F50="",G50,F50),G50))) | O50: =IF(K50<>"",K50,G50) | P50: =IF(K50<>"",K50,IF(I50="high",IF(F50="",G50,F50),IF(I50="low",IF(H50="",G50,H50),G50))) | Q50: =IF(M50<>"",M50,J50) | R50: ONS BRES 2024 (NOMIS NM_189_1) and UK Business Counts March 2025 (NOMIS NM_141_1) | S50: BRES 2024 (next: 18 November 2026); UKBC March 2025 | T50: Gateshead, North East, England and Wales | V50: Central = Gateshead; low and high = lowest and highest of Gateshead, North East and England and Wales. FTE = full-time + part-time / 2. Averages are pulled up by larger units. BRES cells are rounded; our calculation | W50: Open source
A51: J17 | B51: Jobs | C51: FTE per local unit, SIC 8559 (cross-check) | D51: Training and skills | E51: FTE per local unit | F51: 9.7131 | G51: 11.4286 | H51: 13.4058 | J51: 3 | N51: =IF(K51<>"",K51,IF(I51="high",IF(H51="",G51,H51),IF(I51="low",IF(F51="",G51,F51),G51))) | O51: =IF(K51<>"",K51,G51) | P51: =IF(K51<>"",K51,IF(I51="high",IF(F51="",G51,F51),IF(I51="low",IF(H51="",G51,H51),G51))) | Q51: =IF(M51<>"",M51,J51) | R51: ONS BRES 2024 (NOMIS NM_189_1) and UK Business Counts March 2025 (NOMIS NM_141_1) | S51: BRES 2024 (next: 18 November 2026); UKBC March 2025 | T51: Gateshead, North East, England and Wales | V51: Central = Gateshead; low and high = lowest and highest of Gateshead, North East and England and Wales. FTE = full-time + part-time / 2. Averages are pulled up by larger units. BRES cells are rounded; our calculation | W51: Open source
A52: J18 | B52: Jobs | C52: FTE per local unit, SIC 90 (cross-check) | D52: Arts, culture and events | E52: FTE per local unit | F52: 2.2414 | G52: 2.4074 | H52: 2.4074 | J52: 3 | N52: =IF(K52<>"",K52,IF(I52="high",IF(H52="",G52,H52),IF(I52="low",IF(F52="",G52,F52),G52))) | O52: =IF(K52<>"",K52,G52) | P52: =IF(K52<>"",K52,IF(I52="high",IF(F52="",G52,F52),IF(I52="low",IF(H52="",G52,H52),G52))) | Q52: =IF(M52<>"",M52,J52) | R52: ONS BRES 2024 (NOMIS NM_189_1) and UK Business Counts March 2025 (NOMIS NM_141_1) | S52: BRES 2024 (next: 18 November 2026); UKBC March 2025 | T52: Gateshead, North East, England and Wales | V52: Central = North East; low and high from North East and England and Wales only. For Gateshead, BRES 2024 shows 500 employees in SIC 90 while all 60 of its local units employ fewer than 10 (March 2026 size-band count; the March 2025 unit count is also 60), so the two sources disagree for this cell and the Gateshead figure is not used. FTE = full-time + part-time / 2; our calculation | W52: Open source
A53: J19 | B53: Jobs | C53: FTE per local unit, SIC 9313 (cross-check) | D53: Health and wellbeing | E53: FTE per local unit | F53: 2.375 | G53: 2.375 | H53: 5.4516 | J53: 3 | N53: =IF(K53<>"",K53,IF(I53="high",IF(H53="",G53,H53),IF(I53="low",IF(F53="",G53,F53),G53))) | O53: =IF(K53<>"",K53,G53) | P53: =IF(K53<>"",K53,IF(I53="high",IF(F53="",G53,F53),IF(I53="low",IF(H53="",G53,H53),G53))) | Q53: =IF(M53<>"",M53,J53) | R53: ONS BRES 2024 (NOMIS NM_189_1) and UK Business Counts March 2025 (NOMIS NM_141_1) | S53: BRES 2024 (next: 18 November 2026); UKBC March 2025 | T53: Gateshead, North East, England and Wales | V53: Central = Gateshead; low and high = lowest and highest of Gateshead, North East and England and Wales. FTE = full-time + part-time / 2. Averages are pulled up by larger units. BRES cells are rounded; our calculation | W53: Open source
A54: J20 | B54: Jobs | C54: Displacement of jobs at Gateshead level | D54: Retail and food and drink | E54: % | F54: 50 | G54: 50 | H54: 75 | I54: high | J54: 6 | N54: =IF(K54<>"",K54,IF(I54="high",IF(H54="",G54,H54),IF(I54="low",IF(F54="",G54,F54),G54))) | O54: =IF(K54<>"",K54,G54) | P54: =IF(K54<>"",K54,IF(I54="high",IF(F54="",G54,F54),IF(I54="low",IF(H54="",G54,H54),G54))) | Q54: =IF(M54<>"",M54,J54) | R54: HCA Additionality Guide, 4th edition | S54: 2014 | T54: Table 4.8 ready reckoner (medium 50%, high 75%) | U54: About half of the activity would be displaced (medium) | V54: High because retail is a high displacement sector, as MHCLG's land value additionality framework (technical annex Figure 2) also says; using that framework for jobs is our extension | W54: Open source
A55: J21 | B55: Jobs | C55: Displacement of jobs at Gateshead level | D55: Creative, workspace, arts, health and wellbeing | E55: % | F55: 17 | G55: 38 | H55: 50 | I55: high | J55: 6 | N55: =IF(K55<>"",K55,IF(I55="high",IF(H55="",G55,H55),IF(I55="low",IF(F55="",G55,F55),G55))) | O55: =IF(K55<>"",K55,G55) | P55: =IF(K55<>"",K55,IF(I55="high",IF(F55="",G55,F55),IF(I55="low",IF(H55="",G55,H55),G55))) | Q55: =IF(M55<>"",M55,J55) | R55: HCA Additionality Guide, 4th edition | S55: 2014 | T55: Table 4.5 (City Challenge final evaluation) | U55: Development: 17% within the City Challenge area, 38% at district level (paraphrase of Table 4.5) | V55: Central = district level, which matches a Gateshead lens. High = ready reckoner medium (Table 4.8) | W55: Open source
A56: J22 | B56: Jobs | C56: Displacement of jobs at Gateshead level | D56: Community hub and training | E56: % | F56: 8 | G56: 31 | H56: 50 | I56: high | J56: 6 | N56: =IF(K56<>"",K56,IF(I56="high",IF(H56="",G56,H56),IF(I56="low",IF(F56="",G56,F56),G56))) | O56: =IF(K56<>"",K56,G56) | P56: =IF(K56<>"",K56,IF(I56="high",IF(F56="",G56,F56),IF(I56="low",IF(H56="",G56,H56),G56))) | Q56: =IF(M56<>"",M56,J56) | R56: HCA Additionality Guide, 4th edition | S56: 2014 | T56: Table 4.5 (City Challenge final evaluation) | U56: Training and education: 8% within the City Challenge area, 31% at district level (paraphrase of Table 4.5) | V56: Central = district level. High = ready reckoner medium (Table 4.8) | W56: Open source
A57: J23 | B57: Jobs | C57: Leakage of workplace jobs and GVA | D57: Gateshead lens | E57: % | G57: 0 | J57: Rule | N57: =IF(K57<>"",K57,IF(I57="high",IF(H57="",G57,H57),IF(I57="low",IF(F57="",G57,F57),G57))) | O57: =IF(K57<>"",K57,G57) | P57: =IF(K57<>"",K57,IF(I57="high",IF(F57="",G57,F57),IF(I57="low",IF(H57="",G57,H57),G57))) | Q57: =IF(M57<>"",M57,J57) | R57: Our judgement | V57: Jobs and GVA located in Gateshead are Gateshead outputs by construction, so no leakage applies to them. Leakage applies only to resident outcomes (row S3). One of the Additionality Guide's worked examples used 10%, for resident-based effects
A58: J24 | B58: Jobs | C58: Local multiplier (Gateshead level) | D58: All uses, Gateshead lens | E58: multiplier | F58: 1.05 | G58: 1.1 | H58: 1.15 | I58: low | J58: 6 | N58: =IF(K58<>"",K58,IF(I58="high",IF(H58="",G58,H58),IF(I58="low",IF(F58="",G58,F58),G58))) | O58: =IF(K58<>"",K58,G58) | P58: =IF(K58<>"",K58,IF(I58="high",IF(F58="",G58,F58),IF(I58="low",IF(H58="",G58,H58),G58))) | Q58: =IF(M58<>"",M58,J58) | R58: HCA Additionality Guide, 4th edition; MHCLG Appraisal Guide | S58: 2014; February 2026 | T58: Table 4.14 (neighbourhood level); MHCLG 6.25 | U58: neighbourhood level low 1.05, medium 1.1, high 1.15 (compiled from Table 4.14) | V58: Milton Keynes Bletchley business case used 1.1. Not used in the UK lens (Green Book 6.43) | W58: Open source
A59: J25 | B59: Jobs | C59: Additional jobs at UK level | D59: UK lens | E59: % | G59: 0 | J59: Rule | N59: =IF(K59<>"",K59,IF(I59="high",IF(H59="",G59,H59),IF(I59="low",IF(F59="",G59,F59),G59))) | O59: =IF(K59<>"",K59,G59) | P59: =IF(K59<>"",K59,IF(I59="high",IF(F59="",G59,F59),IF(I59="low",IF(H59="",G59,H59),G59))) | Q59: =IF(M59<>"",M59,J59) | R59: HM Treasury, Green Book 2026 | S59: February 2026 | T59: 8.41 | U59: principle of full displacement of jobs ... every job created by the proposal will be filled by a worker who vacates a different job elsewhere | W59: Open source
A60: J26 | B60: Jobs | C60: GVA per FTE, 47 | D60: Pop-up retail | E60: £ per FTE a year | F60: 54217.758 | G60: 66966.412 | H60: 66966.412 | I60: low | J60: 3 | N60: =IF(K60<>"",K60,IF(I60="high",IF(H60="",G60,H60),IF(I60="low",IF(F60="",G60,F60),G60))) | O60: =IF(K60<>"",K60,G60) | P60: =IF(K60<>"",K60,IF(I60="high",IF(F60="",G60,F60),IF(I60="low",IF(H60="",G60,H60),G60))) | Q60: =IF(M60<>"",M60,J60) | R60: ONS regional GVA (balanced) by industry, current prices; BRES 2024 | S60: Published 23 September 2026 (2024 data) | T60: Table 3 (local authorities) and Table 1c (ITL1); NOMIS NM_189_1 | V60: Gateshead indicator only (decision 1). GVA includes self-employed income while BRES counts employees and working owners, so per-FTE figures run high where self-employment is common (arts, personal services). 2024 values uprated to 2026. Our calculation | W60: Open source
A61: J27 | B61: Jobs | C61: GVA per FTE, I (55-56) | D61: Food and drink | E61: £ per FTE a year | F61: 35314.873 | G61: 43527.216 | H61: 43988.571 | I61: low | J61: 3 | N61: =IF(K61<>"",K61,IF(I61="high",IF(H61="",G61,H61),IF(I61="low",IF(F61="",G61,F61),G61))) | O61: =IF(K61<>"",K61,G61) | P61: =IF(K61<>"",K61,IF(I61="high",IF(F61="",G61,F61),IF(I61="low",IF(H61="",G61,H61),G61))) | Q61: =IF(M61<>"",M61,J61) | R61: ONS regional GVA (balanced) by industry, current prices; BRES 2024 | S61: Published 23 September 2026 (2024 data) | T61: Table 3 (local authorities) and Table 1c (ITL1); NOMIS NM_189_1 | V61: Gateshead indicator only (decision 1). GVA includes self-employed income while BRES counts employees and working owners, so per-FTE figures run high where self-employment is common (arts, personal services). 2024 values uprated to 2026. Our calculation | W61: Open source
A62: J28 | B62: Jobs | C62: GVA per FTE, R (90-93) | D62: Creative studios and makers | E62: £ per FTE a year | F62: 59459.859 | G62: 71285.802 | H62: 71285.802 | I62: low | J62: 3 | N62: =IF(K62<>"",K62,IF(I62="high",IF(H62="",G62,H62),IF(I62="low",IF(F62="",G62,F62),G62))) | O62: =IF(K62<>"",K62,G62) | P62: =IF(K62<>"",K62,IF(I62="high",IF(F62="",G62,F62),IF(I62="low",IF(H62="",G62,H62),G62))) | Q62: =IF(M62<>"",M62,J62) | R62: ONS regional GVA (balanced) by industry, current prices; BRES 2024 | S62: Published 23 September 2026 (2024 data) | T62: Table 3 (local authorities) and Table 1c (ITL1); NOMIS NM_189_1 | V62: Gateshead indicator only (decision 1). GVA includes self-employed income while BRES counts employees and working owners, so per-FTE figures run high where self-employment is common (arts, personal services). 2024 values uprated to 2026. Our calculation | W62: Open source
A63: J29 | B63: Jobs | C63: GVA per FTE, M (69-75) | D63: Workspace and co-working | E63: £ per FTE a year | F63: 45264.707 | G63: 45264.707 | H63: 88617.326 | I63: low | J63: 3 | N63: =IF(K63<>"",K63,IF(I63="high",IF(H63="",G63,H63),IF(I63="low",IF(F63="",G63,F63),G63))) | O63: =IF(K63<>"",K63,G63) | P63: =IF(K63<>"",K63,IF(I63="high",IF(F63="",G63,F63),IF(I63="low",IF(H63="",G63,H63),G63))) | Q63: =IF(M63<>"",M63,J63) | R63: ONS regional GVA (balanced) by industry, current prices; BRES 2024 | S63: Published 23 September 2026 (2024 data) | T63: Table 3 (local authorities) and Table 1c (ITL1); NOMIS NM_189_1 | V63: Gateshead indicator only (decision 1). GVA includes self-employed income while BRES counts employees and working owners, so per-FTE figures run high where self-employment is common (arts, personal services). 2024 values uprated to 2026. Our calculation | W63: Open source
A64: J30 | B64: Jobs | C64: GVA per FTE, S (94-96) | D64: Community hub | E64: £ per FTE a year | F64: 42487.049 | G64: 42487.049 | H64: 81236.694 | I64: low | J64: 3 | N64: =IF(K64<>"",K64,IF(I64="high",IF(H64="",G64,H64),IF(I64="low",IF(F64="",G64,F64),G64))) | O64: =IF(K64<>"",K64,G64) | P64: =IF(K64<>"",K64,IF(I64="high",IF(F64="",G64,F64),IF(I64="low",IF(H64="",G64,H64),G64))) | Q64: =IF(M64<>"",M64,J64) | R64: ONS regional GVA (balanced) by industry, current prices; BRES 2024 | S64: Published 23 September 2026 (2024 data) | T64: Table 3 (local authorities) and Table 1c (ITL1); NOMIS NM_189_1 | V64: Gateshead indicator only (decision 1). GVA includes self-employed income while BRES counts employees and working owners, so per-FTE figures run high where self-employment is common (arts, personal services). 2024 values uprated to 2026. Our calculation | W64: Open source
A65: J31 | B65: Jobs | C65: GVA per FTE, P (85) | D65: Training and skills | E65: £ per FTE a year | F65: 63104.145 | G65: 63104.145 | H65: 73594.697 | I65: low | J65: 3 | N65: =IF(K65<>"",K65,IF(I65="high",IF(H65="",G65,H65),IF(I65="low",IF(F65="",G65,F65),G65))) | O65: =IF(K65<>"",K65,G65) | P65: =IF(K65<>"",K65,IF(I65="high",IF(F65="",G65,F65),IF(I65="low",IF(H65="",G65,H65),G65))) | Q65: =IF(M65<>"",M65,J65) | R65: ONS regional GVA (balanced) by industry, current prices; BRES 2024 | S65: Published 23 September 2026 (2024 data) | T65: Table 3 (local authorities) and Table 1c (ITL1); NOMIS NM_189_1 | V65: Gateshead indicator only (decision 1). GVA includes self-employed income while BRES counts employees and working owners, so per-FTE figures run high where self-employment is common (arts, personal services). 2024 values uprated to 2026. Our calculation | W65: Open source
A66: J32 | B66: Jobs | C66: GVA per FTE, R (90-93) | D66: Arts, culture and events | E66: £ per FTE a year | F66: 59459.859 | G66: 71285.802 | H66: 71285.802 | I66: low | J66: 3 | N66: =IF(K66<>"",K66,IF(I66="high",IF(H66="",G66,H66),IF(I66="low",IF(F66="",G66,F66),G66))) | O66: =IF(K66<>"",K66,G66) | P66: =IF(K66<>"",K66,IF(I66="high",IF(F66="",G66,F66),IF(I66="low",IF(H66="",G66,H66),G66))) | Q66: =IF(M66<>"",M66,J66) | R66: ONS regional GVA (balanced) by industry, current prices; BRES 2024 | S66: Published 23 September 2026 (2024 data) | T66: Table 3 (local authorities) and Table 1c (ITL1); NOMIS NM_189_1 | V66: Gateshead indicator only (decision 1). GVA includes self-employed income while BRES counts employees and working owners, so per-FTE figures run high where self-employment is common (arts, personal services). 2024 values uprated to 2026. Our calculation | W66: Open source
A67: J33 | B67: Jobs | C67: GVA per FTE, R (90-93) | D67: Health and wellbeing | E67: £ per FTE a year | F67: 59459.859 | G67: 71285.802 | H67: 71285.802 | I67: low | J67: 3 | N67: =IF(K67<>"",K67,IF(I67="high",IF(H67="",G67,H67),IF(I67="low",IF(F67="",G67,F67),G67))) | O67: =IF(K67<>"",K67,G67) | P67: =IF(K67<>"",K67,IF(I67="high",IF(F67="",G67,F67),IF(I67="low",IF(H67="",G67,H67),G67))) | Q67: =IF(M67<>"",M67,J67) | R67: ONS regional GVA (balanced) by industry, current prices; BRES 2024 | S67: Published 23 September 2026 (2024 data) | T67: Table 3 (local authorities) and Table 1c (ITL1); NOMIS NM_189_1 | V67: Gateshead indicator only (decision 1). GVA includes self-employed income while BRES counts employees and working owners, so per-FTE figures run high where self-employment is common (arts, personal services). 2024 values uprated to 2026. Our calculation | W67: Open source
A68: J34 | B68: Jobs | C68: Displacement of jobs at NEMSA level | D68: All uses except community hub and training | E68: % | F68: 50 | G68: 71 | H68: 89 | I68: high | J68: 6 | N68: =IF(K68<>"",K68,IF(I68="high",IF(H68="",G68,H68),IF(I68="low",IF(F68="",G68,F68),G68))) | O68: =IF(K68<>"",K68,G68) | P68: =IF(K68<>"",K68,IF(I68="high",IF(F68="",G68,F68),IF(I68="low",IF(H68="",G68,H68),G68))) | Q68: =IF(M68<>"",M68,J68) | R68: HCA Additionality Guide, 4th edition | S68: 2014 | T68: Table 4.5 (City Challenge final evaluation) | U68: Development: 71% at county level, 89% at region level (paraphrase of Table 4.5) | V68: NEMSA column only, indicator. Central = county level, the closest match to the seven NEMSA authorities; high = region level; low = ready reckoner medium (Table 4.8) | W68: Open source
A69: J35 | B69: Jobs | C69: Displacement of jobs at NEMSA level | D69: Community hub and training | E69: % | F69: 50 | G69: 77 | H69: 78 | I69: high | J69: 6 | N69: =IF(K69<>"",K69,IF(I69="high",IF(H69="",G69,H69),IF(I69="low",IF(F69="",G69,F69),G69))) | O69: =IF(K69<>"",K69,G69) | P69: =IF(K69<>"",K69,IF(I69="high",IF(F69="",G69,F69),IF(I69="low",IF(H69="",G69,H69),G69))) | Q69: =IF(M69<>"",M69,J69) | R69: HCA Additionality Guide, 4th edition | S69: 2014 | T69: Table 4.5 (City Challenge final evaluation) | U69: Training and education: 77% at county level, 78% at region level (paraphrase of Table 4.5) | V69: NEMSA column only, indicator. Low = ready reckoner medium (Table 4.8) | W69: Open source
A70: J36 | B70: Jobs | C70: Local multiplier (NEMSA level) | D70: All uses, NEMSA column | E70: multiplier | F70: 1.3 | G70: 1.5 | H70: 1.7 | I70: low | J70: 6 | N70: =IF(K70<>"",K70,IF(I70="high",IF(H70="",G70,H70),IF(I70="low",IF(F70="",G70,F70),G70))) | O70: =IF(K70<>"",K70,G70) | P70: =IF(K70<>"",K70,IF(I70="high",IF(F70="",G70,F70),IF(I70="low",IF(H70="",G70,H70),G70))) | Q70: =IF(M70<>"",M70,J70) | R70: HCA Additionality Guide, 4th edition | S70: 2014 | T70: Table 4.14 (regional level) | U70: Composite multiplier (Regional level) 1.3 1.5 1.7 (table cells) | V70: NEMSA column only, indicator | W70: Open source
A71: X1 | B71: Visitors | C71: Spend per visit | D71: Visitor stream, Gateshead indicator only | E71: £ per visit | F71: 16.3276 | G71: 24.7247 | H71: 27.8551 | I71: low | J71: 6 | N71: =IF(K71<>"",K71,IF(I71="high",IF(H71="",G71,H71),IF(I71="low",IF(F71="",G71,F71),G71))) | O71: =IF(K71<>"",K71,G71) | P71: =IF(K71<>"",K71,IF(I71="high",IF(F71="",G71,F71),IF(I71="low",IF(H71="",G71,H71),G71))) | Q71: =IF(M71<>"",M71,J71) | R71: MHCLG Towns Fund evaluation, Value for Money Annex | S71: 17 July 2026 | T71: Table A.2 and the paragraphs that follow it | U71: when allowing the benefits to persist for 7 years, the spending per visit hour needs to be only £17.5 ... the average spend per visit to a high street in 2025 prices is £27.26 | V71: All three from the annex, on high street visits (Phase 1b decision 2). Low = £17.5 per visit hour (MHCLG's 7-year break-even test) x 53.1 minutes' baseline dwell. Central = £26.5 per visit hour (MHCLG's working assumption; 'No value for average spend per visit hour is available – number assumed') x 53.1 minutes. High = £27.26 per visit (Southwark-based, 2025 prices), which MHCLG uses to corroborate the assumption. Hour-based values in 2024/25 prices. Tourism day visits were considered and left out as a different trip type and source (Tyne and Wear £58.69 a trip, 2023 to 2025). STEAM Gateshead goes on the Static Data tab as a local override | W71: Open source
A72: X2 | B72: Visitors | C72: GVA share of spend, shops | D72: Visitor stream, Gateshead indicator only | E72: % of turnover | F72: 0.2076 | G72: 0.2076 | H72: 0.2905 | I72: low | J72: 4 | N72: =IF(K72<>"",K72,IF(I72="high",IF(H72="",G72,H72),IF(I72="low",IF(F72="",G72,F72),G72))) | O72: =IF(K72<>"",K72,G72) | P72: =IF(K72<>"",K72,IF(I72="high",IF(F72="",G72,F72),IF(I72="low",IF(H72="",G72,H72),G72))) | Q72: =IF(M72<>"",M72,J72) | R72: ONS Annual Business Survey, Sections A to S, 2024 results | S72: 26 May 2026 | T72: Division 47 and group 47.7, approximate GVA at basic prices / total turnover | V72: Applied to extra visitors' spend in the centre's shops: the share follows where the spend lands, not the unit's own use, because spend in the unit is already in its GVA (row D1). MHCLG used the same ratio for 2022 (23%). High = specialised stores (47.7). Our calculation | W72: Open source
A73: X3 | B73: Visitors | C73: GVA share of spend, cafes, restaurants and bars | D73: Visitor stream, Gateshead indicator only | E73: % of turnover | F73: 0.4616 | G73: 0.4754 | H73: 0.5075 | I73: low | J73: 4 | N73: =IF(K73<>"",K73,IF(I73="high",IF(H73="",G73,H73),IF(I73="low",IF(F73="",G73,F73),G73))) | O73: =IF(K73<>"",K73,G73) | P73: =IF(K73<>"",K73,IF(I73="high",IF(F73="",G73,F73),IF(I73="low",IF(H73="",G73,H73),G73))) | Q73: =IF(M73<>"",M73,J73) | R73: ONS Annual Business Survey, Sections A to S, 2024 results | S73: 26 May 2026 | T73: Section I, division 56, group 56.3 | V73: Applied to the share of extra visitors' spend going on food and drink (officer input, default 0% as in MHCLG's method). MHCLG used 52% for accommodation and food (2022). Our calculation | W73: Open source
A74: X4 | B74: Visitors | C74: Share of visits that are new trips to the centre | D74: Visitor stream, Gateshead indicator only | E74: % | F74: 10 | G74: 25 | H74: 50 | I74: low | J74: 6 | N74: =IF(K74<>"",K74,IF(I74="high",IF(H74="",G74,H74),IF(I74="low",IF(F74="",G74,F74),G74))) | O74: =IF(K74<>"",K74,G74) | P74: =IF(K74<>"",K74,IF(I74="high",IF(F74="",G74,F74),IF(I74="low",IF(H74="",G74,H74),G74))) | Q74: =IF(M74<>"",M74,J74) | R74: HCA Additionality Guide deadweight ready reckoner | S74: 2014 | T74: 3.3 (none 0, low 25, medium 50, high 75) | V74: Judgement anchored on the ready reckoner; no evidence for single units. Open Doors found 'only limited evidence of increasing footfall' | W74: Open source
A75: X5 | B75: Visitors | C75: Displacement of visitor spend within Gateshead | D75: Visitor stream, Gateshead indicator only | E75: % | F75: 25 | G75: 50 | H75: 75 | I75: high | J75: 6 | N75: =IF(K75<>"",K75,IF(I75="high",IF(H75="",G75,H75),IF(I75="low",IF(F75="",G75,F75),G75))) | O75: =IF(K75<>"",K75,G75) | P75: =IF(K75<>"",K75,IF(I75="high",IF(F75="",G75,F75),IF(I75="low",IF(H75="",G75,H75),G75))) | Q75: =IF(M75<>"",M75,J75) | R75: HCA Additionality Guide, 4th edition | S75: 2014 | T75: Table 4.8 ready reckoner | U75: About half of the activity would be displaced (medium) | V75: Towns Fund found no displacement to neighbouring towns, but only tested at town level | W75: Open source
A76: X6 | B76: Visitors | C76: Attendance per session, community and group uses | D76: Community hub, training, arts | E76: people per session | F76: 2 | G76: 11 | H76: 30 | I76: low | J76: 6 | N76: =IF(K76<>"",K76,IF(I76="high",IF(H76="",G76,H76),IF(I76="low",IF(F76="",G76,F76),G76))) | O76: =IF(K76<>"",K76,G76) | P76: =IF(K76<>"",K76,IF(I76="high",IF(F76="",G76,F76),IF(I76="low",IF(H76="",G76,H76),G76))) | Q76: =IF(M76<>"",M76,J76) | R76: Open Doors Pilot Programme evaluation | S76: November 2020 | T76: Chapter 3 MI data | U76: ranged from a minimum of two up to a maximum of 30, with the average number of attendees being 11 | V76: Groups per site 6 to 12, mostly weekly, 3 to 4 hour sessions. Indicative only (small bases) | W76: Open source
A77: X7 | B77: Visitors | C77: VAT removed from visitor spend before the GVA share | D77: Visitor stream, Gateshead indicator only | E77: divisor | G77: 1.2 | J77: Rule | N77: =IF(K77<>"",K77,IF(I77="high",IF(H77="",G77,H77),IF(I77="low",IF(F77="",G77,F77),G77))) | O77: =IF(K77<>"",K77,G77) | P77: =IF(K77<>"",K77,IF(I77="high",IF(F77="",G77,F77),IF(I77="low",IF(H77="",G77,H77),G77))) | Q77: =IF(M77<>"",M77,J77) | R77: GOV.UK, VAT rates | S77: Checked 23 October 2026 | T77: Standard rate | U77: Standard rate 20% ... Most goods and services | V77: ABS turnover excludes VAT while visitor spend includes it. Spend is divided by 1.2, treating it all as standard-rated, which slightly understates GVA where spend is zero-rated. MHCLG did not adjust; our correction | W77: Open source
A78: Z1 | B78: Businesses | C78: 1-year survival of new businesses | D78: Business counts | E78: % | F78: 92.7 | G78: 92.9 | H78: 93.4 | I78: low | J78: 3 | N78: =IF(K78<>"",K78,IF(I78="high",IF(H78="",G78,H78),IF(I78="low",IF(F78="",G78,F78),G78))) | O78: =IF(K78<>"",K78,G78) | P78: =IF(K78<>"",K78,IF(I78="high",IF(F78="",G78,F78),IF(I78="low",IF(H78="",G78,H78),G78))) | Q78: =IF(M78<>"",M78,J78) | R78: ONS Business demography, UK: 2024 | S78: 20 November 2025 (next edition 19 November 2026) | T78: Table 5.1e (2023 births) | V78: Gateshead central; North East low; UK high. Counts only (decision 16) | W78: Open source
A79: Z2 | B79: Businesses | C79: 3-year survival of new businesses | D79: Business counts | E79: % | F79: 51.9 | G79: 52.9 | H79: 53.5 | I79: low | J79: 3 | N79: =IF(K79<>"",K79,IF(I79="high",IF(H79="",G79,H79),IF(I79="low",IF(F79="",G79,F79),G79))) | O79: =IF(K79<>"",K79,G79) | P79: =IF(K79<>"",K79,IF(I79="high",IF(F79="",G79,F79),IF(I79="low",IF(H79="",G79,H79),G79))) | Q79: =IF(M79<>"",M79,J79) | R79: ONS Business demography, UK: 2024 | S79: 20 November 2025 (next edition 19 November 2026) | T79: Table 5.1c (2021 births) | V79: UK 3-year survival by industry (2021 births, Table 5.2c): retail 48.7%, food and beverage 48.7%, creative arts 67.1%, sport and recreation 60.9%, membership organisations 72.8%. Meanwhile start-ups are not typical births: flag | W79: Open source
A80: S1 | B80: Social value | C80: Volunteering wellbeing value | D80: Regular volunteers | E80: £ per volunteer a year | G80: 1204.4216 | J80: 6 | N80: =IF(K80<>"",K80,IF(I80="high",IF(H80="",G80,H80),IF(I80="low",IF(F80="",G80,F80),G80))) | O80: =IF(K80<>"",K80,G80) | P80: =IF(K80<>"",K80,IF(I80="high",IF(F80="",G80,F80),IF(I80="low",IF(H80="",G80,H80),G80))) | Q80: =IF(M80<>"",M80,J80) | R80: HM Treasury, Wellbeing Guidance for Appraisal (2021), from Lawton et al. (2021) Journal of Happiness Studies 22: 599-624 | S80: July 2021 | T80: Annex 2 table | U80: gives a value of £911 per volunteer per year on average | V80: Price year not stated in the guidance or found in the paper; treated as 2019 prices like the guidance's other values and uprated by A5. Pro-rate for months volunteering | W80: Open source
A81: S2 | B81: Social value | C81: Wellbeing value of moving from unemployment to work | D81: Jobs filled by previously unemployed residents | E81: £ per person a year | F81: 5023.9322 | G81: 7906.0828 | H81: 11211.301 | I81: low | J81: 6 | N81: =IF(K81<>"",K81,IF(I81="high",IF(H81="",G81,H81),IF(I81="low",IF(F81="",G81,F81),G81))) | O81: =IF(K81<>"",K81,G81) | P81: =IF(K81<>"",K81,IF(I81="high",IF(F81="",G81,F81),IF(I81="low",IF(H81="",G81,H81),G81))) | Q81: =IF(M81<>"",M81,J81) | R81: HM Treasury, Wellbeing Guidance for Appraisal (2021); MHCLG Appraisal Guide 6.19 | S81: July 2021 | T81: Annex 2 table | U81: central value of £5,980 per annum in 2019 prices (MHCLG 6.19) | V81: Over and above income. Gateshead lens allowed (MHCLG 6.23); UK lens only with evidence of new labour supply (Green Book 8.42 to 8.43) | W81: Open source
A82: S3 | B82: Social value | C82: Share of jobs filled by previously unemployed local residents | D82: S2 | E82: % | F82: 10 | G82: 20 | H82: 40 | I82: low | J82: 6 | N82: =IF(K82<>"",K82,IF(I82="high",IF(H82="",G82,H82),IF(I82="low",IF(F82="",G82,F82),G82))) | O82: =IF(K82<>"",K82,G82) | P82: =IF(K82<>"",K82,IF(I82="high",IF(F82="",G82,F82),IF(I82="low",IF(H82="",G82,H82),G82))) | Q82: =IF(M82<>"",M82,J82) | R82: HCA Additionality Guide, 4th edition (property-led regeneration research) | S82: 2014 (underlying research 1980s to 1990s) | T82: Chapter 4 leakage evidence | U82: companies in fairly deprived areas were filling about 40% of their vacancies from unemployed people in the local area | V82: High = the quoted figure; low and central our judgement. Officer override from recruitment records | W82: Open source
A83: S4 | B83: Social value | C83: Deadweight for jobseekers | D83: S2 | E83: % | G83: 26.3 | J83: 6 | N83: =IF(K83<>"",K83,IF(I83="high",IF(H83="",G83,H83),IF(I83="low",IF(F83="",G83,F83),G83))) | O83: =IF(K83<>"",K83,G83) | P83: =IF(K83<>"",K83,IF(I83="high",IF(F83="",G83,F83),IF(I83="low",IF(H83="",G83,H83),G83))) | Q83: =IF(M83<>"",M83,J83) | R83: HM Treasury, CBA guidance for local partnerships | S83: April 2014 | T83: Chapter 8 (employment) | U83: BIS analysis of 16 people and skills evaluations: 26.3% (paraphrase) | W83: Open source
A84: S5 | B84: Social value | C84: Regular cultural or creative participation | D84: Arts, culture, creative and community uses | E84: £ per regular participant a year | G84: 606.9342 | I84: low | J84: 4 | N84: =IF(K84<>"",K84,IF(I84="high",IF(H84="",G84,H84),IF(I84="low",IF(F84="",G84,F84),G84))) | O84: =IF(K84<>"",K84,G84) | P84: =IF(K84<>"",K84,IF(I84="high",IF(F84="",G84,F84),IF(I84="low",IF(H84="",G84,H84),G84))) | Q84: =IF(M84<>"",M84,J84) | R84: GMCA Unit Cost Database v3.0, from DCMS Culture and Heritage Capital (2024) | S84: November 2025 (2025/26 prices) | T84: C&S1.1 | U84: Estimated benefits from attending cultural activities once a week to the mental health of adults (aged 30-49) | V84: Default for adults 30 to 49. The officer picks the value matching the group instead: weekly organised arts, young adults 18 to 29, £720 (C&S4.0); arts participation more than once a week, adults 30 to 49, £419 (C&S1.2). These are subgroup values, not a range. WELLBY-derived, so discounted at 1.5% (A2). GMCA priced these at 2023/24 and inflated them to 2025/26; we apply the deflator step only, not the real GDP per head step. Regular participants only: Wellbeing Guidance Table 4 says evaluative measures do not suit a one-off cultural event. RAG green. DCMS 2024 source still to be read | W84: Open source
A85: S6 | B85: Social value | C85: Loneliness (moderate to mild) | D85: Sensitivity only | E85: £ per person a year | F85: 7800.3158 | G85: 12030.996 | H85: 17134.253 | I85: low | J85: 6 | N85: =IF(K85<>"",K85,IF(I85="high",IF(H85="",G85,H85),IF(I85="low",IF(F85="",G85,F85),G85))) | O85: =IF(K85<>"",K85,G85) | P85: =IF(K85<>"",K85,IF(I85="high",IF(F85="",G85,F85),IF(I85="low",IF(H85="",G85,H85),G85))) | Q85: =IF(M85<>"",M85,J85) | R85: HM Treasury, Wellbeing Guidance for Appraisal (2021) | S85: July 2021 | T85: Annex 2 table | U85: causality unclear | V85: Sensitivity sheet only; never in a ratio. Built on £13.5k per point (footnote 108), not £13,000, with an unclear price year; uprating it as 2019 prices is our assumption | W85: Open source
A86: S7 | B86: Social value | C86: Pride in place (switching test) | D86: Sensitivity only | E86: £ per person a year | G86: 4620 | J86: 6 | N86: =IF(K86<>"",K86,IF(I86="high",IF(H86="",G86,H86),IF(I86="low",IF(F86="",G86,F86),G86))) | O86: =IF(K86<>"",K86,G86) | P86: =IF(K86<>"",K86,IF(I86="high",IF(F86="",G86,F86),IF(I86="low",IF(H86="",G86,H86),G86))) | Q86: =IF(M86<>"",M86,J86) | R86: MHCLG Towns Fund evaluation VfM Annex (HACT value) | S86: 17 July 2026 | T86: Table A.4 | U86: Value pride in place £4,620 per person, per year | V86: Decision 6: switching test only. Price year not stated; held at the published figure | W86: Open source
A87: S8 | B87: Social value | C87: Fiscal saving, workless claimant into full-time work (memo line) | D87: Memo line, never in a ratio | E87: £ per person a year | G87: 18091.738 | J87: 4 | N87: =IF(K87<>"",K87,IF(I87="high",IF(H87="",G87,H87),IF(I87="low",IF(F87="",G87,F87),G87))) | O87: =IF(K87<>"",K87,G87) | P87: =IF(K87<>"",K87,IF(I87="high",IF(F87="",G87,F87),IF(I87="low",IF(H87="",G87,H87),G87))) | Q87: =IF(M87<>"",M87,J87) | R87: GMCA Unit Cost Database v3.0 | S87: November 2025 (2025/26 prices) | T87: E&E1.0 fiscal | U87: Fiscal, economic and social benefit from a single workless claimant with no children entering full-time (row description) | V87: Part-time work: £6,685 (E&E1.1). Cashable only with decommissioning (local partnerships guidance 7.26) | W87: Open source
A88: S9 | B88: Social value | C88: Training | D88: Training and skills, and any use running courses | E88: count | G88: Learners and qualifications counted | J88: 6 | N88: =IF(K88<>"",K88,IF(I88="high",IF(H88="",G88,H88),IF(I88="low",IF(F88="",G88,F88),G88))) | O88: =IF(K88<>"",K88,G88) | P88: =IF(K88<>"",K88,IF(I88="high",IF(F88="",G88,F88),IF(I88="low",IF(H88="",G88,H88),G88))) | Q88: =IF(M88<>"",M88,J88) | R88: GMCA Unit Cost Database v3.0 (for accredited courses only) | S88: November 2025 | T88: E&S5.0 (NVQ Level 2), E&S12.0 (NVQ Level 3) | U88: NVQ Level 2 qualification - annual fiscal and economic benefits | V88: Decision 9: a count unless accredited. Where a full Level 2 or 3 qualification is achieved, its annual value shows on the Sensitivity sheet only, because it is an earnings value that overlaps GVA | W88: Open source
A89: S10 | B89: Social value | C89: Accredited Level 2 qualification (sensitivity only) | D89: S9, Sensitivity sheet | E89: £ per learner a year | G89: 796.7413 | J89: 6 | N89: =IF(K89<>"",K89,IF(I89="high",IF(H89="",G89,H89),IF(I89="low",IF(F89="",G89,F89),G89))) | O89: =IF(K89<>"",K89,G89) | P89: =IF(K89<>"",K89,IF(I89="high",IF(F89="",G89,F89),IF(I89="low",IF(H89="",G89,H89),G89))) | Q89: =IF(M89<>"",M89,J89) | R89: GMCA Unit Cost Database v3.0 | S89: November 2025 (2025/26 prices; 2010/11 base) | T89: E&S5.0, fiscal plus economic updated values | U89: NVQ Level 2 qualification - annual fiscal and economic benefits | V89: RAG red. Fiscal £123 plus economic £658 (2025/26). Earnings value that overlaps GVA, so never in a ratio | W89: Open source
A90: S11 | B90: Social value | C90: Accredited Level 3 qualification (sensitivity only) | D90: S9, Sensitivity sheet | E90: £ per learner a year | G90: 2173.116 | J90: 6 | N90: =IF(K90<>"",K90,IF(I90="high",IF(H90="",G90,H90),IF(I90="low",IF(F90="",G90,F90),G90))) | O90: =IF(K90<>"",K90,G90) | P90: =IF(K90<>"",K90,IF(I90="high",IF(F90="",G90,F90),IF(I90="low",IF(H90="",G90,H90),G90))) | Q90: =IF(M90<>"",M90,J90) | R90: GMCA Unit Cost Database v3.0 | S90: November 2025 (2025/26 prices; 2010/11 base) | T90: E&S12.0, fiscal plus economic updated values | U90: NVQ Level 3 qualification - annual fiscal and economic benefits | V90: RAG red. Fiscal £762 plus economic £1,368 (2025/26). Never in a ratio | W90: Open source
A91: D1 | B91: Counting rules | C91: Spend inside the unit | D91: Visitor stream | E91: rule | G91: Excluded from visitor spend | J91: Rule | N91: =IF(K91<>"",K91,IF(I91="high",IF(H91="",G91,H91),IF(I91="low",IF(F91="",G91,F91),G91))) | O91: =IF(K91<>"",K91,G91) | P91: =IF(K91<>"",K91,IF(I91="high",IF(F91="",G91,F91),IF(I91="low",IF(H91="",G91,H91),G91))) | Q91: =IF(M91<>"",M91,J91) | R91: Agreed design (decision 15) | V91: Spend in the unit is already in the unit's GVA. Only extra visitors' spend elsewhere in the centre counts in the visitor stream
A92: D2 | B92: Counting rules | C92: One wellbeing value per person | D92: Social value streams | E92: rule | G92: Each person counted once | J92: Rule | N92: =IF(K92<>"",K92,IF(I92="high",IF(H92="",G92,H92),IF(I92="low",IF(F92="",G92,F92),G92))) | O92: =IF(K92<>"",K92,G92) | P92: =IF(K92<>"",K92,IF(I92="high",IF(F92="",G92,F92),IF(I92="low",IF(H92="",G92,H92),G92))) | Q92: =IF(M92<>"",M92,J92) | R92: HM Treasury, Wellbeing Guidance for Appraisal (2021) | S92: July 2021 | T92: 4.6, avoiding double counting | U92: it would be double counting to include any 'ongoing wellbeing impacts' from volunteering | V92: A person moving into a job takes S2 only; a volunteer takes S1 only; a participant takes S5 only. Workers in the unit (makers, staff) count as jobs, not as S5 participants | W92: Open source
A93: D3 | B93: Counting rules | C93: Transfers | D93: Cost and benefit lines | E93: rule | G93: Rates relief, grants and rent counted with offsetting entries | J93: Rule | N93: =IF(K93<>"",K93,IF(I93="high",IF(H93="",G93,H93),IF(I93="low",IF(F93="",G93,F93),G93))) | O93: =IF(K93<>"",K93,G93) | P93: =IF(K93<>"",K93,IF(I93="high",IF(F93="",G93,F93),IF(I93="low",IF(H93="",G93,H93),G93))) | Q93: =IF(M93<>"",M93,J93) | R93: MHCLG Appraisal Guide, 4th edition; Green Book 2026 | S93: February 2026 | T93: 3.34 and footnote 15; Green Book 6.33 to 6.38 | V93: Decision 12. Rows B3, B5, B6 and V4 | W93: Open source
A94: L1 | B94: Legacy (off by default) | C94: Persistence: image, events and tourism | D94: Legacy switch | E94: years | G94: 2 | J94: 6 | N94: =IF(K94<>"",K94,IF(I94="high",IF(H94="",G94,H94),IF(I94="low",IF(F94="",G94,F94),G94))) | O94: =IF(K94<>"",K94,G94) | P94: =IF(K94<>"",K94,IF(I94="high",IF(F94="",G94,F94),IF(I94="low",IF(H94="",G94,H94),G94))) | Q94: =IF(M94<>"",M94,J94) | R94: HCA Additionality Guide, 4th edition | S94: 2014 | T94: Table 5.19 (BIS IEF+) | U94: image, events and tourism 2 (table cell) | W94: Open source
A95: L2 | B95: Legacy (off by default) | C95: Persistence: bringing land or buildings back into use | D95: Legacy switch, permanent let only | E95: years | G95: 10 | J95: 6 | N95: =IF(K95<>"",K95,IF(I95="high",IF(H95="",G95,H95),IF(I95="low",IF(F95="",G95,F95),G95))) | O95: =IF(K95<>"",K95,G95) | P95: =IF(K95<>"",K95,IF(I95="high",IF(F95="",G95,F95),IF(I95="low",IF(H95="",G95,H95),G95))) | Q95: =IF(M95<>"",M95,J95) | R95: HCA Additionality Guide, 4th edition | S95: 2014 | T95: Table 5.19 | U95: bringing land back into use 10 (table cell) | W95: Open source
A96: L3 | B96: Legacy (off by default) | C96: Chance the meanwhile use converts to a permanent let | D96: Legacy switch | E96: % | G96: User input | J96: 6 | N96: =IF(K96<>"",K96,IF(I96="high",IF(H96="",G96,H96),IF(I96="low",IF(F96="",G96,F96),G96))) | O96: =IF(K96<>"",K96,G96) | P96: =IF(K96<>"",K96,IF(I96="high",IF(F96="",G96,F96),IF(I96="low",IF(H96="",G96,H96),G96))) | Q96: =IF(M96<>"",M96,J96) | R96: No robust evidence found | V96: Open Doors: 'little evidence to suggest that the groups would be able to take on the spaces independently'
A97: P1 | B97: Place and location | C97: Centre hierarchy | D97: Location input | E97: tier | G97: Gateshead Primary Shopping Area; District Centre (8); Local Centre (15); outside the hierarchy (parades and single shops) | J97: Rule | N97: =IF(K97<>"",K97,IF(I97="high",IF(H97="",G97,H97),IF(I97="low",IF(F97="",G97,F97),G97))) | O97: =IF(K97<>"",K97,G97) | P97: =IF(K97<>"",K97,IF(I97="high",IF(F97="",G97,F97),IF(I97="low",IF(H97="",G97,H97),G97))) | Q97: =IF(M97<>"",M97,J97) | R97: Core Strategy and Urban Core Plan for Gateshead and Newcastle 2010-2030, Policy CS7 | S97: Adopted March 2015 (in force; new joint plan to 2045 under preparation) | T97: Policy CS7 part 1 | U97: In Gateshead (Figure 9.1b): 1) Blaydon, 2) Birtley, 3) Coatsworth Road, 4) Felling, 5) Low Fell, 6) Ryton, 7) Whickham and 8) Wrekenton. | V97: Label and place scorecard input only (Phase 1b decision 4); the let-anyway chance (B1) uses the council's vacancy figures for the centre where held. Metrocentre is an 'existing out-of-centre regional shopping destination' (CS7 part 5), excluded. Refresh when the joint Retail and Town Centre Study reports | W97: Open source
A98: P2 | B98: Place and location | C98: Seven-point place scale | D98: Place scorecard | E98: scale | G98: Large Adverse to Large Beneficial | J98: Rule | N98: =IF(K98<>"",K98,IF(I98="high",IF(H98="",G98,H98),IF(I98="low",IF(F98="",G98,F98),G98))) | O98: =IF(K98<>"",K98,G98) | P98: =IF(K98<>"",K98,IF(I98="high",IF(F98="",G98,F98),IF(I98="low",IF(H98="",G98,H98),G98))) | Q98: =IF(M98<>"",M98,J98) | R98: MHCLG Appraisal Guide, 4th edition | S98: February 2026 | T98: 3.47 Table 2 | U98: Large Adverse, Moderate Adverse, Slight Adverse, Neutral, Slight Beneficial, Moderate Beneficial, Large Beneficial (scale points) | W98: Open source
A99: P3 | B99: Place and location | C99: Distance over which spillovers were found | D99: Scorecard wording | E99: metres | F99: 400 | H99: 800 | J99: 3 | N99: =IF(K99<>"",K99,IF(I99="high",IF(H99="",G99,H99),IF(I99="low",IF(F99="",G99,F99),G99))) | O99: =IF(K99<>"",K99,G99) | P99: =IF(K99<>"",K99,IF(I99="high",IF(F99="",G99,F99),IF(I99="low",IF(H99="",G99,H99),G99))) | Q99: =IF(M99<>"",M99,J99) | R99: Homes England, Measuring Social Value Paper 8 | S99: 24 October 2025 | T99: Foreword and findings | U99: for the majority of the schemes analysed, there was no consistent evidence of commercial-led regeneration leading to wider placemaking effects | W99: Open source

Sheet Calculations
A1: Calculations
A2: Every step for every proposal and scenario. Low takes the pessimistic end of every ranged assumption; high the optimistic end.
B4: Step | C4: Unit | D4: P1 low | E4: P1 central | F4: P1 high | G4: P2 low | H4: P2 central | I4: P2 high | J4: P3 low | K4: P3 central | L4: P3 high | M4: P4 low | N4: P4 central | O4: P4 high | P4: P5 low | Q4: P5 central | R4: P5 high
B5: Time and discounting
B6: Proposal entered: use, period and rateable value (1 = yes) | D6: =IF(AND(Inputs!$C$9<>"",N(Inputs!$C$21)>0,N(Inputs!$C$13)>0),1,0) | E6: =IF(AND(Inputs!$C$9<>"",N(Inputs!$C$21)>0,N(Inputs!$C$13)>0),1,0) | F6: =IF(AND(Inputs!$C$9<>"",N(Inputs!$C$21)>0,N(Inputs!$C$13)>0),1,0) | G6: =IF(AND(Inputs!$D$9<>"",N(Inputs!$D$21)>0,N(Inputs!$D$13)>0),1,0) | H6: =IF(AND(Inputs!$D$9<>"",N(Inputs!$D$21)>0,N(Inputs!$D$13)>0),1,0) | I6: =IF(AND(Inputs!$D$9<>"",N(Inputs!$D$21)>0,N(Inputs!$D$13)>0),1,0) | J6: =IF(AND(Inputs!$E$9<>"",N(Inputs!$E$21)>0,N(Inputs!$E$13)>0),1,0) | K6: =IF(AND(Inputs!$E$9<>"",N(Inputs!$E$21)>0,N(Inputs!$E$13)>0),1,0) | L6: =IF(AND(Inputs!$E$9<>"",N(Inputs!$E$21)>0,N(Inputs!$E$13)>0),1,0) | M6: =IF(AND(Inputs!$F$9<>"",N(Inputs!$F$21)>0,N(Inputs!$F$13)>0),1,0) | N6: =IF(AND(Inputs!$F$9<>"",N(Inputs!$F$21)>0,N(Inputs!$F$13)>0),1,0) | O6: =IF(AND(Inputs!$F$9<>"",N(Inputs!$F$21)>0,N(Inputs!$F$13)>0),1,0) | P6: =IF(AND(Inputs!$G$9<>"",N(Inputs!$G$21)>0,N(Inputs!$G$13)>0),1,0) | Q6: =IF(AND(Inputs!$G$9<>"",N(Inputs!$G$21)>0,N(Inputs!$G$13)>0),1,0) | R6: =IF(AND(Inputs!$G$9<>"",N(Inputs!$G$21)>0,N(Inputs!$G$13)>0),1,0)
B7: Occupation period used (capped at 60 months) | C7: months | D7: =IF(D6=0,"",MIN(60,Inputs!$C$21)) | E7: =IF(E6=0,"",MIN(60,Inputs!$C$21)) | F7: =IF(F6=0,"",MIN(60,Inputs!$C$21)) | G7: =IF(G6=0,"",MIN(60,Inputs!$D$21)) | H7: =IF(H6=0,"",MIN(60,Inputs!$D$21)) | I7: =IF(I6=0,"",MIN(60,Inputs!$D$21)) | J7: =IF(J6=0,"",MIN(60,Inputs!$E$21)) | K7: =IF(K6=0,"",MIN(60,Inputs!$E$21)) | L7: =IF(L6=0,"",MIN(60,Inputs!$E$21)) | M7: =IF(M6=0,"",MIN(60,Inputs!$F$21)) | N7: =IF(N6=0,"",MIN(60,Inputs!$F$21)) | O7: =IF(O6=0,"",MIN(60,Inputs!$F$21)) | P7: =IF(P6=0,"",MIN(60,Inputs!$G$21)) | Q7: =IF(Q6=0,"",MIN(60,Inputs!$G$21)) | R7: =IF(R6=0,"",MIN(60,Inputs!$G$21))
B8: Occupation period | C8: years | D8: =IF(D6=0,"",D7/12) | E8: =IF(E6=0,"",E7/12) | F8: =IF(F6=0,"",F7/12) | G8: =IF(G6=0,"",G7/12) | H8: =IF(H6=0,"",H7/12) | I8: =IF(I6=0,"",I7/12) | J8: =IF(J6=0,"",J7/12) | K8: =IF(K6=0,"",K7/12) | ... R8: =IF(R6=0,"",R7/12)
B9: Share of year 0 occupied | D9: =IF(D6=0,"",MIN(1,MAX(0,D8-0))) | E9: =IF(E6=0,"",MIN(1,MAX(0,E8-0))) | F9: =IF(F6=0,"",MIN(1,MAX(0,F8-0))) | G9: =IF(G6=0,"",MIN(1,MAX(0,G8-0))) | H9: =IF(H6=0,"",MIN(1,MAX(0,H8-0))) | I9: =IF(I6=0,"",MIN(1,MAX(0,I8-0))) | J9: =IF(J6=0,"",MIN(1,MAX(0,J8-0))) | K9: =IF(K6=0,"",MIN(1,MAX(0,K8-0))) | ... R9: =IF(R6=0,"",MIN(1,MAX(0,R8-0)))
B10: Share of year 1 occupied | D10: =IF(D6=0,"",MIN(1,MAX(0,D8-1))) | E10: =IF(E6=0,"",MIN(1,MAX(0,E8-1))) | F10: =IF(F6=0,"",MIN(1,MAX(0,F8-1))) | G10: =IF(G6=0,"",MIN(1,MAX(0,G8-1))) | H10: =IF(H6=0,"",MIN(1,MAX(0,H8-1))) | I10: =IF(I6=0,"",MIN(1,MAX(0,I8-1))) | J10: =IF(J6=0,"",MIN(1,MAX(0,J8-1))) | K10: =IF(K6=0,"",MIN(1,MAX(0,K8-1))) | ... R10: =IF(R6=0,"",MIN(1,MAX(0,R8-1)))
B11: Share of year 2 occupied | D11: =IF(D6=0,"",MIN(1,MAX(0,D8-2))) | E11: =IF(E6=0,"",MIN(1,MAX(0,E8-2))) | F11: =IF(F6=0,"",MIN(1,MAX(0,F8-2))) | G11: =IF(G6=0,"",MIN(1,MAX(0,G8-2))) | H11: =IF(H6=0,"",MIN(1,MAX(0,H8-2))) | I11: =IF(I6=0,"",MIN(1,MAX(0,I8-2))) | J11: =IF(J6=0,"",MIN(1,MAX(0,J8-2))) | K11: =IF(K6=0,"",MIN(1,MAX(0,K8-2))) | ... R11: =IF(R6=0,"",MIN(1,MAX(0,R8-2)))
B12: Share of year 3 occupied | D12: =IF(D6=0,"",MIN(1,MAX(0,D8-3))) | E12: =IF(E6=0,"",MIN(1,MAX(0,E8-3))) | F12: =IF(F6=0,"",MIN(1,MAX(0,F8-3))) | G12: =IF(G6=0,"",MIN(1,MAX(0,G8-3))) | H12: =IF(H6=0,"",MIN(1,MAX(0,H8-3))) | I12: =IF(I6=0,"",MIN(1,MAX(0,I8-3))) | J12: =IF(J6=0,"",MIN(1,MAX(0,J8-3))) | K12: =IF(K6=0,"",MIN(1,MAX(0,K8-3))) | ... R12: =IF(R6=0,"",MIN(1,MAX(0,R8-3)))
B13: Share of year 4 occupied | D13: =IF(D6=0,"",MIN(1,MAX(0,D8-4))) | E13: =IF(E6=0,"",MIN(1,MAX(0,E8-4))) | F13: =IF(F6=0,"",MIN(1,MAX(0,F8-4))) | G13: =IF(G6=0,"",MIN(1,MAX(0,G8-4))) | H13: =IF(H6=0,"",MIN(1,MAX(0,H8-4))) | I13: =IF(I6=0,"",MIN(1,MAX(0,I8-4))) | J13: =IF(J6=0,"",MIN(1,MAX(0,J8-4))) | K13: =IF(K6=0,"",MIN(1,MAX(0,K8-4))) | ... R13: =IF(R6=0,"",MIN(1,MAX(0,R8-4)))
B14: Discounted years at the discount rate | D14: =IF(D6=0,"",D9/(1+Settings!$B$6)^0+D10/(1+Settings!$B$6)^1+D11/(1+Settings!$B$6)^2+D12/(1+Settings!$B$6)^3+D13/(1+Settings!$B$6)^4) | E14: =IF(E6=0,"",E9/(1+Settings!$B$6)^0+E10/(1+Settings!$B$6)^1+E11/(1+Settings!$B$6)^2+E12/(1+Settings!$B$6)^3+E13/(1+Settings!$B$6)^4) | F14: =IF(F6=0,"",F9/(1+Settings!$B$6)^0+F10/(1+Settings!$B$6)^1+F11/(1+Settings!$B$6)^2+F12/(1+Settings!$B$6)^3+F13/(1+Settings!$B$6)^4) | G14: =IF(G6=0,"",G9/(1+Settings!$B$6)^0+G10/(1+Settings!$B$6)^1+G11/(1+Settings!$B$6)^2+G12/(1+Settings!$B$6)^3+G13/(1+Settings!$B$6)^4) | H14: =IF(H6=0,"",H9/(1+Settings!$B$6)^0+H10/(1+Settings!$B$6)^1+H11/(1+Settings!$B$6)^2+H12/(1+Settings!$B$6)^3+H13/(1+Settings!$B$6)^4) | I14: =IF(I6=0,"",I9/(1+Settings!$B$6)^0+I10/(1+Settings!$B$6)^1+I11/(1+Settings!$B$6)^2+I12/(1+Settings!$B$6)^3+I13/(1+Settings!$B$6)^4) | J14: =IF(J6=0,"",J9/(1+Settings!$B$6)^0+J10/(1+Settings!$B$6)^1+J11/(1+Settings!$B$6)^2+J12/(1+Settings!$B$6)^3+J13/(1+Settings!$B$6)^4) | K14: =IF(K6=0,"",K9/(1+Settings!$B$6)^0+K10/(1+Settings!$B$6)^1+K11/(1+Settings!$B$6)^2+K12/(1+Settings!$B$6)^3+K13/(1+Settings!$B$6)^4) | ... R14: =IF(R6=0,"",R9/(1+Settings!$B$6)^0+R10/(1+Settings!$B$6)^1+R11/(1+Settings!$B$6)^2+R12/(1+Settings!$B$6)^3+R13/(1+Settings!$B$6)^4)
B15: Discounted years at the wellbeing rate | D15: =IF(D6=0,"",D9/(1+Settings!$B$7)^0+D10/(1+Settings!$B$7)^1+D11/(1+Settings!$B$7)^2+D12/(1+Settings!$B$7)^3+D13/(1+Settings!$B$7)^4) | E15: =IF(E6=0,"",E9/(1+Settings!$B$7)^0+E10/(1+Settings!$B$7)^1+E11/(1+Settings!$B$7)^2+E12/(1+Settings!$B$7)^3+E13/(1+Settings!$B$7)^4) | F15: =IF(F6=0,"",F9/(1+Settings!$B$7)^0+F10/(1+Settings!$B$7)^1+F11/(1+Settings!$B$7)^2+F12/(1+Settings!$B$7)^3+F13/(1+Settings!$B$7)^4) | G15: =IF(G6=0,"",G9/(1+Settings!$B$7)^0+G10/(1+Settings!$B$7)^1+G11/(1+Settings!$B$7)^2+G12/(1+Settings!$B$7)^3+G13/(1+Settings!$B$7)^4) | H15: =IF(H6=0,"",H9/(1+Settings!$B$7)^0+H10/(1+Settings!$B$7)^1+H11/(1+Settings!$B$7)^2+H12/(1+Settings!$B$7)^3+H13/(1+Settings!$B$7)^4) | I15: =IF(I6=0,"",I9/(1+Settings!$B$7)^0+I10/(1+Settings!$B$7)^1+I11/(1+Settings!$B$7)^2+I12/(1+Settings!$B$7)^3+I13/(1+Settings!$B$7)^4) | J15: =IF(J6=0,"",J9/(1+Settings!$B$7)^0+J10/(1+Settings!$B$7)^1+J11/(1+Settings!$B$7)^2+J12/(1+Settings!$B$7)^3+J13/(1+Settings!$B$7)^4) | K15: =IF(K6=0,"",K9/(1+Settings!$B$7)^0+K10/(1+Settings!$B$7)^1+K11/(1+Settings!$B$7)^2+K12/(1+Settings!$B$7)^3+K13/(1+Settings!$B$7)^4) | ... R15: =IF(R6=0,"",R9/(1+Settings!$B$7)^0+R10/(1+Settings!$B$7)^1+R11/(1+Settings!$B$7)^2+R12/(1+Settings!$B$7)^3+R13/(1+Settings!$B$7)^4)
B16: Discount factor for the year after occupation | D16: =IF(D6=0,"",1/(1+Settings!$B$6)^ROUNDUP(D8,0)) | E16: =IF(E6=0,"",1/(1+Settings!$B$6)^ROUNDUP(E8,0)) | F16: =IF(F6=0,"",1/(1+Settings!$B$6)^ROUNDUP(F8,0)) | G16: =IF(G6=0,"",1/(1+Settings!$B$6)^ROUNDUP(G8,0)) | H16: =IF(H6=0,"",1/(1+Settings!$B$6)^ROUNDUP(H8,0)) | I16: =IF(I6=0,"",1/(1+Settings!$B$6)^ROUNDUP(I8,0)) | J16: =IF(J6=0,"",1/(1+Settings!$B$6)^ROUNDUP(J8,0)) | K16: =IF(K6=0,"",1/(1+Settings!$B$6)^ROUNDUP(K8,0)) | ... R16: =IF(R6=0,"",1/(1+Settings!$B$6)^ROUNDUP(R8,0))
B17: Business as Usual: chance of a let anyway
B18: Council survey: vacant units | D18: =IF(D6=0,"",IFERROR(IF(INDEX('Static Data'!$C$35:$C$59,MATCH(Inputs!$C$7,'Static Data'!$A$35:$A$59,0))="","",INDEX('Static Data'!$C$35:$C$59,MATCH(Inputs!$C$7,'Static Data'!$A$35:$A$59,0))),"")) | E18: =IF(E6=0,"",IFERROR(IF(INDEX('Static Data'!$C$35:$C$59,MATCH(Inputs!$C$7,'Static Data'!$A$35:$A$59,0))="","",INDEX('Static Data'!$C$35:$C$59,MATCH(Inputs!$C$7,'Static Data'!$A$35:$A$59,0))),"")) | F18: =IF(F6=0,"",IFERROR(IF(INDEX('Static Data'!$C$35:$C$59,MATCH(Inputs!$C$7,'Static Data'!$A$35:$A$59,0))="","",INDEX('Static Data'!$C$35:$C$59,MATCH(Inputs!$C$7,'Static Data'!$A$35:$A$59,0))),"")) | G18: =IF(G6=0,"",IFERROR(IF(INDEX('Static Data'!$C$35:$C$59,MATCH(Inputs!$D$7,'Static Data'!$A$35:$A$59,0))="","",INDEX('Static Data'!$C$35:$C$59,MATCH(Inputs!$D$7,'Static Data'!$A$35:$A$59,0))),"")) | H18: =IF(H6=0,"",IFERROR(IF(INDEX('Static Data'!$C$35:$C$59,MATCH(Inputs!$D$7,'Static Data'!$A$35:$A$59,0))="","",INDEX('Static Data'!$C$35:$C$59,MATCH(Inputs!$D$7,'Static Data'!$A$35:$A$59,0))),"")) | I18: =IF(I6=0,"",IFERROR(IF(INDEX('Static Data'!$C$35:$C$59,MATCH(Inputs!$D$7,'Static Data'!$A$35:$A$59,0))="","",INDEX('Static Data'!$C$35:$C$59,MATCH(Inputs!$D$7,'Static Data'!$A$35:$A$59,0))),"")) | J18: =IF(J6=0,"",IFERROR(IF(INDEX('Static Data'!$C$35:$C$59,MATCH(Inputs!$E$7,'Static Data'!$A$35:$A$59,0))="","",INDEX('Static Data'!$C$35:$C$59,MATCH(Inputs!$E$7,'Static Data'!$A$35:$A$59,0))),"")) | K18: =IF(K6=0,"",IFERROR(IF(INDEX('Static Data'!$C$35:$C$59,MATCH(Inputs!$E$7,'Static Data'!$A$35:$A$59,0))="","",INDEX('Static Data'!$C$35:$C$59,MATCH(Inputs!$E$7,'Static Data'!$A$35:$A$59,0))),"")) | L18: =IF(L6=0,"",IFERROR(IF(INDEX('Static Data'!$C$35:$C$59,MATCH(Inputs!$E$7,'Static Data'!$A$35:$A$59,0))="","",INDEX('Static Data'!$C$35:$C$59,MATCH(Inputs!$E$7,'Static Data'!$A$35:$A$59,0))),"")) | M18: =IF(M6=0,"",IFERROR(IF(INDEX('Static Data'!$C$35:$C$59,MATCH(Inputs!$F$7,'Static Data'!$A$35:$A$59,0))="","",INDEX('Static Data'!$C$35:$C$59,MATCH(Inputs!$F$7,'Static Data'!$A$35:$A$59,0))),"")) | N18: =IF(N6=0,"",IFERROR(IF(INDEX('Static Data'!$C$35:$C$59,MATCH(Inputs!$F$7,'Static Data'!$A$35:$A$59,0))="","",INDEX('Static Data'!$C$35:$C$59,MATCH(Inputs!$F$7,'Static Data'!$A$35:$A$59,0))),"")) | O18: =IF(O6=0,"",IFERROR(IF(INDEX('Static Data'!$C$35:$C$59,MATCH(Inputs!$F$7,'Static Data'!$A$35:$A$59,0))="","",INDEX('Static Data'!$C$35:$C$59,MATCH(Inputs!$F$7,'Static Data'!$A$35:$A$59,0))),"")) | P18: =IF(P6=0,"",IFERROR(IF(INDEX('Static Data'!$C$35:$C$59,MATCH(Inputs!$G$7,'Static Data'!$A$35:$A$59,0))="","",INDEX('Static Data'!$C$35:$C$59,MATCH(Inputs!$G$7,'Static Data'!$A$35:$A$59,0))),"")) | Q18: =IF(Q6=0,"",IFERROR(IF(INDEX('Static Data'!$C$35:$C$59,MATCH(Inputs!$G$7,'Static Data'!$A$35:$A$59,0))="","",INDEX('Static Data'!$C$35:$C$59,MATCH(Inputs!$G$7,'Static Data'!$A$35:$A$59,0))),"")) | R18: =IF(R6=0,"",IFERROR(IF(INDEX('Static Data'!$C$35:$C$59,MATCH(Inputs!$G$7,'Static Data'!$A$35:$A$59,0))="","",INDEX('Static Data'!$C$35:$C$59,MATCH(Inputs!$G$7,'Static Data'!$A$35:$A$59,0))),""))
B19: Council survey: still vacant | D19: =IF(D6=0,"",IFERROR(IF(INDEX('Static Data'!$D$35:$D$59,MATCH(Inputs!$C$7,'Static Data'!$A$35:$A$59,0))="","",INDEX('Static Data'!$D$35:$D$59,MATCH(Inputs!$C$7,'Static Data'!$A$35:$A$59,0))),"")) | E19: =IF(E6=0,"",IFERROR(IF(INDEX('Static Data'!$D$35:$D$59,MATCH(Inputs!$C$7,'Static Data'!$A$35:$A$59,0))="","",INDEX('Static Data'!$D$35:$D$59,MATCH(Inputs!$C$7,'Static Data'!$A$35:$A$59,0))),"")) | F19: =IF(F6=0,"",IFERROR(IF(INDEX('Static Data'!$D$35:$D$59,MATCH(Inputs!$C$7,'Static Data'!$A$35:$A$59,0))="","",INDEX('Static Data'!$D$35:$D$59,MATCH(Inputs!$C$7,'Static Data'!$A$35:$A$59,0))),"")) | G19: =IF(G6=0,"",IFERROR(IF(INDEX('Static Data'!$D$35:$D$59,MATCH(Inputs!$D$7,'Static Data'!$A$35:$A$59,0))="","",INDEX('Static Data'!$D$35:$D$59,MATCH(Inputs!$D$7,'Static Data'!$A$35:$A$59,0))),"")) | H19: =IF(H6=0,"",IFERROR(IF(INDEX('Static Data'!$D$35:$D$59,MATCH(Inputs!$D$7,'Static Data'!$A$35:$A$59,0))="","",INDEX('Static Data'!$D$35:$D$59,MATCH(Inputs!$D$7,'Static Data'!$A$35:$A$59,0))),"")) | I19: =IF(I6=0,"",IFERROR(IF(INDEX('Static Data'!$D$35:$D$59,MATCH(Inputs!$D$7,'Static Data'!$A$35:$A$59,0))="","",INDEX('Static Data'!$D$35:$D$59,MATCH(Inputs!$D$7,'Static Data'!$A$35:$A$59,0))),"")) | J19: =IF(J6=0,"",IFERROR(IF(INDEX('Static Data'!$D$35:$D$59,MATCH(Inputs!$E$7,'Static Data'!$A$35:$A$59,0))="","",INDEX('Static Data'!$D$35:$D$59,MATCH(Inputs!$E$7,'Static Data'!$A$35:$A$59,0))),"")) | K19: =IF(K6=0,"",IFERROR(IF(INDEX('Static Data'!$D$35:$D$59,MATCH(Inputs!$E$7,'Static Data'!$A$35:$A$59,0))="","",INDEX('Static Data'!$D$35:$D$59,MATCH(Inputs!$E$7,'Static Data'!$A$35:$A$59,0))),"")) | L19: =IF(L6=0,"",IFERROR(IF(INDEX('Static Data'!$D$35:$D$59,MATCH(Inputs!$E$7,'Static Data'!$A$35:$A$59,0))="","",INDEX('Static Data'!$D$35:$D$59,MATCH(Inputs!$E$7,'Static Data'!$A$35:$A$59,0))),"")) | M19: =IF(M6=0,"",IFERROR(IF(INDEX('Static Data'!$D$35:$D$59,MATCH(Inputs!$F$7,'Static Data'!$A$35:$A$59,0))="","",INDEX('Static Data'!$D$35:$D$59,MATCH(Inputs!$F$7,'Static Data'!$A$35:$A$59,0))),"")) | N19: =IF(N6=0,"",IFERROR(IF(INDEX('Static Data'!$D$35:$D$59,MATCH(Inputs!$F$7,'Static Data'!$A$35:$A$59,0))="","",INDEX('Static Data'!$D$35:$D$59,MATCH(Inputs!$F$7,'Static Data'!$A$35:$A$59,0))),"")) | O19: =IF(O6=0,"",IFERROR(IF(INDEX('Static Data'!$D$35:$D$59,MATCH(Inputs!$F$7,'Static Data'!$A$35:$A$59,0))="","",INDEX('Static Data'!$D$35:$D$59,MATCH(Inputs!$F$7,'Static Data'!$A$35:$A$59,0))),"")) | P19: =IF(P6=0,"",IFERROR(IF(INDEX('Static Data'!$D$35:$D$59,MATCH(Inputs!$G$7,'Static Data'!$A$35:$A$59,0))="","",INDEX('Static Data'!$D$35:$D$59,MATCH(Inputs!$G$7,'Static Data'!$A$35:$A$59,0))),"")) | Q19: =IF(Q6=0,"",IFERROR(IF(INDEX('Static Data'!$D$35:$D$59,MATCH(Inputs!$G$7,'Static Data'!$A$35:$A$59,0))="","",INDEX('Static Data'!$D$35:$D$59,MATCH(Inputs!$G$7,'Static Data'!$A$35:$A$59,0))),"")) | R19: =IF(R6=0,"",IFERROR(IF(INDEX('Static Data'!$D$35:$D$59,MATCH(Inputs!$G$7,'Static Data'!$A$35:$A$59,0))="","",INDEX('Static Data'!$D$35:$D$59,MATCH(Inputs!$G$7,'Static Data'!$A$35:$A$59,0))),""))
B20: Council survey: months between surveys | D20: =IF(D6=0,"",IFERROR(IF(INDEX('Static Data'!$E$35:$E$59,MATCH(Inputs!$C$7,'Static Data'!$A$35:$A$59,0))="","",INDEX('Static Data'!$E$35:$E$59,MATCH(Inputs!$C$7,'Static Data'!$A$35:$A$59,0))),"")) | E20: =IF(E6=0,"",IFERROR(IF(INDEX('Static Data'!$E$35:$E$59,MATCH(Inputs!$C$7,'Static Data'!$A$35:$A$59,0))="","",INDEX('Static Data'!$E$35:$E$59,MATCH(Inputs!$C$7,'Static Data'!$A$35:$A$59,0))),"")) | F20: =IF(F6=0,"",IFERROR(IF(INDEX('Static Data'!$E$35:$E$59,MATCH(Inputs!$C$7,'Static Data'!$A$35:$A$59,0))="","",INDEX('Static Data'!$E$35:$E$59,MATCH(Inputs!$C$7,'Static Data'!$A$35:$A$59,0))),"")) | G20: =IF(G6=0,"",IFERROR(IF(INDEX('Static Data'!$E$35:$E$59,MATCH(Inputs!$D$7,'Static Data'!$A$35:$A$59,0))="","",INDEX('Static Data'!$E$35:$E$59,MATCH(Inputs!$D$7,'Static Data'!$A$35:$A$59,0))),"")) | H20: =IF(H6=0,"",IFERROR(IF(INDEX('Static Data'!$E$35:$E$59,MATCH(Inputs!$D$7,'Static Data'!$A$35:$A$59,0))="","",INDEX('Static Data'!$E$35:$E$59,MATCH(Inputs!$D$7,'Static Data'!$A$35:$A$59,0))),"")) | I20: =IF(I6=0,"",IFERROR(IF(INDEX('Static Data'!$E$35:$E$59,MATCH(Inputs!$D$7,'Static Data'!$A$35:$A$59,0))="","",INDEX('Static Data'!$E$35:$E$59,MATCH(Inputs!$D$7,'Static Data'!$A$35:$A$59,0))),"")) | J20: =IF(J6=0,"",IFERROR(IF(INDEX('Static Data'!$E$35:$E$59,MATCH(Inputs!$E$7,'Static Data'!$A$35:$A$59,0))="","",INDEX('Static Data'!$E$35:$E$59,MATCH(Inputs!$E$7,'Static Data'!$A$35:$A$59,0))),"")) | K20: =IF(K6=0,"",IFERROR(IF(INDEX('Static Data'!$E$35:$E$59,MATCH(Inputs!$E$7,'Static Data'!$A$35:$A$59,0))="","",INDEX('Static Data'!$E$35:$E$59,MATCH(Inputs!$E$7,'Static Data'!$A$35:$A$59,0))),"")) | L20: =IF(L6=0,"",IFERROR(IF(INDEX('Static Data'!$E$35:$E$59,MATCH(Inputs!$E$7,'Static Data'!$A$35:$A$59,0))="","",INDEX('Static Data'!$E$35:$E$59,MATCH(Inputs!$E$7,'Static Data'!$A$35:$A$59,0))),"")) | M20: =IF(M6=0,"",IFERROR(IF(INDEX('Static Data'!$E$35:$E$59,MATCH(Inputs!$F$7,'Static Data'!$A$35:$A$59,0))="","",INDEX('Static Data'!$E$35:$E$59,MATCH(Inputs!$F$7,'Static Data'!$A$35:$A$59,0))),"")) | N20: =IF(N6=0,"",IFERROR(IF(INDEX('Static Data'!$E$35:$E$59,MATCH(Inputs!$F$7,'Static Data'!$A$35:$A$59,0))="","",INDEX('Static Data'!$E$35:$E$59,MATCH(Inputs!$F$7,'Static Data'!$A$35:$A$59,0))),"")) | O20: =IF(O6=0,"",IFERROR(IF(INDEX('Static Data'!$E$35:$E$59,MATCH(Inputs!$F$7,'Static Data'!$A$35:$A$59,0))="","",INDEX('Static Data'!$E$35:$E$59,MATCH(Inputs!$F$7,'Static Data'!$A$35:$A$59,0))),"")) | P20: =IF(P6=0,"",IFERROR(IF(INDEX('Static Data'!$E$35:$E$59,MATCH(Inputs!$G$7,'Static Data'!$A$35:$A$59,0))="","",INDEX('Static Data'!$E$35:$E$59,MATCH(Inputs!$G$7,'Static Data'!$A$35:$A$59,0))),"")) | Q20: =IF(Q6=0,"",IFERROR(IF(INDEX('Static Data'!$E$35:$E$59,MATCH(Inputs!$G$7,'Static Data'!$A$35:$A$59,0))="","",INDEX('Static Data'!$E$35:$E$59,MATCH(Inputs!$G$7,'Static Data'!$A$35:$A$59,0))),"")) | R20: =IF(R6=0,"",IFERROR(IF(INDEX('Static Data'!$E$35:$E$59,MATCH(Inputs!$G$7,'Static Data'!$A$35:$A$59,0))="","",INDEX('Static Data'!$E$35:$E$59,MATCH(Inputs!$G$7,'Static Data'!$A$35:$A$59,0))),""))
B21: Council survey complete (1 = yes) | D21: =IF(D6=0,"",IF(AND(N(D18)>0,D19<>"",N(D20)>0),1,0)) | E21: =IF(E6=0,"",IF(AND(N(E18)>0,E19<>"",N(E20)>0),1,0)) | F21: =IF(F6=0,"",IF(AND(N(F18)>0,F19<>"",N(F20)>0),1,0)) | G21: =IF(G6=0,"",IF(AND(N(G18)>0,G19<>"",N(G20)>0),1,0)) | H21: =IF(H6=0,"",IF(AND(N(H18)>0,H19<>"",N(H20)>0),1,0)) | I21: =IF(I6=0,"",IF(AND(N(I18)>0,I19<>"",N(I20)>0),1,0)) | J21: =IF(J6=0,"",IF(AND(N(J18)>0,J19<>"",N(J20)>0),1,0)) | K21: =IF(K6=0,"",IF(AND(N(K18)>0,K19<>"",N(K20)>0),1,0)) | ... R21: =IF(R6=0,"",IF(AND(N(R18)>0,R19<>"",N(R20)>0),1,0))
B22: Chance of a let anyway over the period | C22: share | D22: =IF(D6=0,"",IF(Inputs!$C$18<>"",Inputs!$C$18,IF(D21=1,1-(D19/D18)^(D7/D20),Assumptions!$N$22/100))) | E22: =IF(E6=0,"",IF(Inputs!$C$18<>"",Inputs!$C$18,IF(E21=1,1-(E19/E18)^(E7/E20),Assumptions!$O$22/100))) | F22: =IF(F6=0,"",IF(Inputs!$C$18<>"",Inputs!$C$18,IF(F21=1,1-(F19/F18)^(F7/F20),Assumptions!$P$22/100))) | G22: =IF(G6=0,"",IF(Inputs!$D$18<>"",Inputs!$D$18,IF(G21=1,1-(G19/G18)^(G7/G20),Assumptions!$N$22/100))) | H22: =IF(H6=0,"",IF(Inputs!$D$18<>"",Inputs!$D$18,IF(H21=1,1-(H19/H18)^(H7/H20),Assumptions!$O$22/100))) | I22: =IF(I6=0,"",IF(Inputs!$D$18<>"",Inputs!$D$18,IF(I21=1,1-(I19/I18)^(I7/I20),Assumptions!$P$22/100))) | J22: =IF(J6=0,"",IF(Inputs!$E$18<>"",Inputs!$E$18,IF(J21=1,1-(J19/J18)^(J7/J20),Assumptions!$N$22/100))) | K22: =IF(K6=0,"",IF(Inputs!$E$18<>"",Inputs!$E$18,IF(K21=1,1-(K19/K18)^(K7/K20),Assumptions!$O$22/100))) | L22: =IF(L6=0,"",IF(Inputs!$E$18<>"",Inputs!$E$18,IF(L21=1,1-(L19/L18)^(L7/L20),Assumptions!$P$22/100))) | M22: =IF(M6=0,"",IF(Inputs!$F$18<>"",Inputs!$F$18,IF(M21=1,1-(M19/M18)^(M7/M20),Assumptions!$N$22/100))) | N22: =IF(N6=0,"",IF(Inputs!$F$18<>"",Inputs!$F$18,IF(N21=1,1-(N19/N18)^(N7/N20),Assumptions!$O$22/100))) | O22: =IF(O6=0,"",IF(Inputs!$F$18<>"",Inputs!$F$18,IF(O21=1,1-(O19/O18)^(O7/O20),Assumptions!$P$22/100))) | P22: =IF(P6=0,"",IF(Inputs!$G$18<>"",Inputs!$G$18,IF(P21=1,1-(P19/P18)^(P7/P20),Assumptions!$N$22/100))) | Q22: =IF(Q6=0,"",IF(Inputs!$G$18<>"",Inputs!$G$18,IF(Q21=1,1-(Q19/Q18)^(Q7/Q20),Assumptions!$O$22/100))) | R22: =IF(R6=0,"",IF(Inputs!$G$18<>"",Inputs!$G$18,IF(R21=1,1-(R19/R18)^(R7/R20),Assumptions!$P$22/100)))
B23: Grade of the let-anyway figure | D23: =IF(D6=0,"",IF(Inputs!$C$18<>"",4,IF(D21=1,2,Assumptions!$Q$22))) | E23: =IF(E6=0,"",IF(Inputs!$C$18<>"",4,IF(E21=1,2,Assumptions!$Q$22))) | F23: =IF(F6=0,"",IF(Inputs!$C$18<>"",4,IF(F21=1,2,Assumptions!$Q$22))) | G23: =IF(G6=0,"",IF(Inputs!$D$18<>"",4,IF(G21=1,2,Assumptions!$Q$22))) | H23: =IF(H6=0,"",IF(Inputs!$D$18<>"",4,IF(H21=1,2,Assumptions!$Q$22))) | I23: =IF(I6=0,"",IF(Inputs!$D$18<>"",4,IF(I21=1,2,Assumptions!$Q$22))) | J23: =IF(J6=0,"",IF(Inputs!$E$18<>"",4,IF(J21=1,2,Assumptions!$Q$22))) | K23: =IF(K6=0,"",IF(Inputs!$E$18<>"",4,IF(K21=1,2,Assumptions!$Q$22))) | L23: =IF(L6=0,"",IF(Inputs!$E$18<>"",4,IF(L21=1,2,Assumptions!$Q$22))) | M23: =IF(M6=0,"",IF(Inputs!$F$18<>"",4,IF(M21=1,2,Assumptions!$Q$22))) | N23: =IF(N6=0,"",IF(Inputs!$F$18<>"",4,IF(N21=1,2,Assumptions!$Q$22))) | O23: =IF(O6=0,"",IF(Inputs!$F$18<>"",4,IF(O21=1,2,Assumptions!$Q$22))) | P23: =IF(P6=0,"",IF(Inputs!$G$18<>"",4,IF(P21=1,2,Assumptions!$Q$22))) | Q23: =IF(Q6=0,"",IF(Inputs!$G$18<>"",4,IF(Q21=1,2,Assumptions!$Q$22))) | R23: =IF(R6=0,"",IF(Inputs!$G$18<>"",4,IF(R21=1,2,Assumptions!$Q$22)))
B24: Break clause (1 = the landlord can end the lease for a let) | D24: =IF(D6=0,"",IF(Inputs!$C$19="No",0,1)) | E24: =IF(E6=0,"",IF(Inputs!$C$19="No",0,1)) | F24: =IF(F6=0,"",IF(Inputs!$C$19="No",0,1)) | G24: =IF(G6=0,"",IF(Inputs!$D$19="No",0,1)) | H24: =IF(H6=0,"",IF(Inputs!$D$19="No",0,1)) | I24: =IF(I6=0,"",IF(Inputs!$D$19="No",0,1)) | J24: =IF(J6=0,"",IF(Inputs!$E$19="No",0,1)) | K24: =IF(K6=0,"",IF(Inputs!$E$19="No",0,1)) | L24: =IF(L6=0,"",IF(Inputs!$E$19="No",0,1)) | M24: =IF(M6=0,"",IF(Inputs!$F$19="No",0,1)) | N24: =IF(N6=0,"",IF(Inputs!$F$19="No",0,1)) | O24: =IF(O6=0,"",IF(Inputs!$F$19="No",0,1)) | P24: =IF(P6=0,"",IF(Inputs!$G$19="No",0,1)) | Q24: =IF(Q6=0,"",IF(Inputs!$G$19="No",0,1)) | R24: =IF(R6=0,"",IF(Inputs!$G$19="No",0,1))
B25: Share kept after a let anyway (jobs, visitors, avoided costs) | C25: share | D25: =IF(D6=0,"",1-D22) | E25: =IF(E6=0,"",1-E22) | F25: =IF(F6=0,"",1-F22) | G25: =IF(G6=0,"",1-G22) | H25: =IF(H6=0,"",1-H22) | I25: =IF(I6=0,"",1-I22) | J25: =IF(J6=0,"",1-J22) | K25: =IF(K6=0,"",1-K22) | ... R25: =IF(R6=0,"",1-R22)
B26: Share kept for volunteering and participation | C26: share | D26: =IF(D6=0,"",IF(D24=1,1-D22,1)) | E26: =IF(E6=0,"",IF(E24=1,1-E22,1)) | F26: =IF(F6=0,"",IF(F24=1,1-F22,1)) | G26: =IF(G6=0,"",IF(G24=1,1-G22,1)) | H26: =IF(H6=0,"",IF(H24=1,1-H22,1)) | I26: =IF(I6=0,"",IF(I24=1,1-I22,1)) | J26: =IF(J6=0,"",IF(J24=1,1-J22,1)) | K26: =IF(K6=0,"",IF(K24=1,1-K22,1)) | ... R26: =IF(R6=0,"",IF(R24=1,1-R22,1))
B27: Jobs (FTE)
B28: Floor area | C28: m2 | D28: =IF(D6=0,"",N(Inputs!$C$11)*IF(Inputs!$C$12="m2",1,0.09290304)) | E28: =IF(E6=0,"",N(Inputs!$C$11)*IF(Inputs!$C$12="m2",1,0.09290304)) | F28: =IF(F6=0,"",N(Inputs!$C$11)*IF(Inputs!$C$12="m2",1,0.09290304)) | G28: =IF(G6=0,"",N(Inputs!$D$11)*IF(Inputs!$D$12="m2",1,0.09290304)) | H28: =IF(H6=0,"",N(Inputs!$D$11)*IF(Inputs!$D$12="m2",1,0.09290304)) | I28: =IF(I6=0,"",N(Inputs!$D$11)*IF(Inputs!$D$12="m2",1,0.09290304)) | J28: =IF(J6=0,"",N(Inputs!$E$11)*IF(Inputs!$E$12="m2",1,0.09290304)) | K28: =IF(K6=0,"",N(Inputs!$E$11)*IF(Inputs!$E$12="m2",1,0.09290304)) | L28: =IF(L6=0,"",N(Inputs!$E$11)*IF(Inputs!$E$12="m2",1,0.09290304)) | M28: =IF(M6=0,"",N(Inputs!$F$11)*IF(Inputs!$F$12="m2",1,0.09290304)) | N28: =IF(N6=0,"",N(Inputs!$F$11)*IF(Inputs!$F$12="m2",1,0.09290304)) | O28: =IF(O6=0,"",N(Inputs!$F$11)*IF(Inputs!$F$12="m2",1,0.09290304)) | P28: =IF(P6=0,"",N(Inputs!$G$11)*IF(Inputs!$G$12="m2",1,0.09290304)) | Q28: =IF(Q6=0,"",N(Inputs!$G$11)*IF(Inputs!$G$12="m2",1,0.09290304)) | R28: =IF(R6=0,"",N(Inputs!$G$11)*IF(Inputs!$G$12="m2",1,0.09290304))
B29: Share of the space in use | C29: share | D29: =IF(D6=0,"",IF(Inputs!$C$40<>"",Inputs!$C$40,Assumptions!$N$43/100)) | E29: =IF(E6=0,"",IF(Inputs!$C$40<>"",Inputs!$C$40,Assumptions!$O$43/100)) | F29: =IF(F6=0,"",IF(Inputs!$C$40<>"",Inputs!$C$40,Assumptions!$P$43/100)) | G29: =IF(G6=0,"",IF(Inputs!$D$40<>"",Inputs!$D$40,Assumptions!$N$43/100)) | H29: =IF(H6=0,"",IF(Inputs!$D$40<>"",Inputs!$D$40,Assumptions!$O$43/100)) | I29: =IF(I6=0,"",IF(Inputs!$D$40<>"",Inputs!$D$40,Assumptions!$P$43/100)) | J29: =IF(J6=0,"",IF(Inputs!$E$40<>"",Inputs!$E$40,Assumptions!$N$43/100)) | K29: =IF(K6=0,"",IF(Inputs!$E$40<>"",Inputs!$E$40,Assumptions!$O$43/100)) | L29: =IF(L6=0,"",IF(Inputs!$E$40<>"",Inputs!$E$40,Assumptions!$P$43/100)) | M29: =IF(M6=0,"",IF(Inputs!$F$40<>"",Inputs!$F$40,Assumptions!$N$43/100)) | N29: =IF(N6=0,"",IF(Inputs!$F$40<>"",Inputs!$F$40,Assumptions!$O$43/100)) | O29: =IF(O6=0,"",IF(Inputs!$F$40<>"",Inputs!$F$40,Assumptions!$P$43/100)) | P29: =IF(P6=0,"",IF(Inputs!$G$40<>"",Inputs!$G$40,Assumptions!$N$43/100)) | Q29: =IF(Q6=0,"",IF(Inputs!$G$40<>"",Inputs!$G$40,Assumptions!$O$43/100)) | R29: =IF(R6=0,"",IF(Inputs!$G$40<>"",Inputs!$G$40,Assumptions!$P$43/100))
B30: Officer staffing | C30: FTE | D30: =IF(D6=0,"",IF(Inputs!$C$37<>"",Inputs!$C$37,IF(OR(Inputs!$C$38<>"",Inputs!$C$39<>""),N(Inputs!$C$38)+N(Inputs!$C$39)/Assumptions!$O$44,""))) | E30: =IF(E6=0,"",IF(Inputs!$C$37<>"",Inputs!$C$37,IF(OR(Inputs!$C$38<>"",Inputs!$C$39<>""),N(Inputs!$C$38)+N(Inputs!$C$39)/Assumptions!$O$44,""))) | F30: =IF(F6=0,"",IF(Inputs!$C$37<>"",Inputs!$C$37,IF(OR(Inputs!$C$38<>"",Inputs!$C$39<>""),N(Inputs!$C$38)+N(Inputs!$C$39)/Assumptions!$O$44,""))) | G30: =IF(G6=0,"",IF(Inputs!$D$37<>"",Inputs!$D$37,IF(OR(Inputs!$D$38<>"",Inputs!$D$39<>""),N(Inputs!$D$38)+N(Inputs!$D$39)/Assumptions!$O$44,""))) | H30: =IF(H6=0,"",IF(Inputs!$D$37<>"",Inputs!$D$37,IF(OR(Inputs!$D$38<>"",Inputs!$D$39<>""),N(Inputs!$D$38)+N(Inputs!$D$39)/Assumptions!$O$44,""))) | I30: =IF(I6=0,"",IF(Inputs!$D$37<>"",Inputs!$D$37,IF(OR(Inputs!$D$38<>"",Inputs!$D$39<>""),N(Inputs!$D$38)+N(Inputs!$D$39)/Assumptions!$O$44,""))) | J30: =IF(J6=0,"",IF(Inputs!$E$37<>"",Inputs!$E$37,IF(OR(Inputs!$E$38<>"",Inputs!$E$39<>""),N(Inputs!$E$38)+N(Inputs!$E$39)/Assumptions!$O$44,""))) | K30: =IF(K6=0,"",IF(Inputs!$E$37<>"",Inputs!$E$37,IF(OR(Inputs!$E$38<>"",Inputs!$E$39<>""),N(Inputs!$E$38)+N(Inputs!$E$39)/Assumptions!$O$44,""))) | L30: =IF(L6=0,"",IF(Inputs!$E$37<>"",Inputs!$E$37,IF(OR(Inputs!$E$38<>"",Inputs!$E$39<>""),N(Inputs!$E$38)+N(Inputs!$E$39)/Assumptions!$O$44,""))) | M30: =IF(M6=0,"",IF(Inputs!$F$37<>"",Inputs!$F$37,IF(OR(Inputs!$F$38<>"",Inputs!$F$39<>""),N(Inputs!$F$38)+N(Inputs!$F$39)/Assumptions!$O$44,""))) | N30: =IF(N6=0,"",IF(Inputs!$F$37<>"",Inputs!$F$37,IF(OR(Inputs!$F$38<>"",Inputs!$F$39<>""),N(Inputs!$F$38)+N(Inputs!$F$39)/Assumptions!$O$44,""))) | O30: =IF(O6=0,"",IF(Inputs!$F$37<>"",Inputs!$F$37,IF(OR(Inputs!$F$38<>"",Inputs!$F$39<>""),N(Inputs!$F$38)+N(Inputs!$F$39)/Assumptions!$O$44,""))) | P30: =IF(P6=0,"",IF(Inputs!$G$37<>"",Inputs!$G$37,IF(OR(Inputs!$G$38<>"",Inputs!$G$39<>""),N(Inputs!$G$38)+N(Inputs!$G$39)/Assumptions!$O$44,""))) | Q30: =IF(Q6=0,"",IF(Inputs!$G$37<>"",Inputs!$G$37,IF(OR(Inputs!$G$38<>"",Inputs!$G$39<>""),N(Inputs!$G$38)+N(Inputs!$G$39)/Assumptions!$O$44,""))) | R30: =IF(R6=0,"",IF(Inputs!$G$37<>"",Inputs!$G$37,IF(OR(Inputs!$G$38<>"",Inputs!$G$39<>""),N(Inputs!$G$38)+N(Inputs!$G$39)/Assumptions!$O$44,"")))
B31: Employment density for the use | C31: m2 per FTE | D31: =IF(D6=0,"",IFERROR(INDEX(Lookups!$O$5:$O$12,MATCH(Inputs!$C$9,Lookups!$N$5:$N$12,0)),"")) | E31: =IF(E6=0,"",IFERROR(INDEX(Lookups!$P$5:$P$12,MATCH(Inputs!$C$9,Lookups!$N$5:$N$12,0)),"")) | F31: =IF(F6=0,"",IFERROR(INDEX(Lookups!$Q$5:$Q$12,MATCH(Inputs!$C$9,Lookups!$N$5:$N$12,0)),"")) | G31: =IF(G6=0,"",IFERROR(INDEX(Lookups!$O$5:$O$12,MATCH(Inputs!$D$9,Lookups!$N$5:$N$12,0)),"")) | H31: =IF(H6=0,"",IFERROR(INDEX(Lookups!$P$5:$P$12,MATCH(Inputs!$D$9,Lookups!$N$5:$N$12,0)),"")) | I31: =IF(I6=0,"",IFERROR(INDEX(Lookups!$Q$5:$Q$12,MATCH(Inputs!$D$9,Lookups!$N$5:$N$12,0)),"")) | J31: =IF(J6=0,"",IFERROR(INDEX(Lookups!$O$5:$O$12,MATCH(Inputs!$E$9,Lookups!$N$5:$N$12,0)),"")) | K31: =IF(K6=0,"",IFERROR(INDEX(Lookups!$P$5:$P$12,MATCH(Inputs!$E$9,Lookups!$N$5:$N$12,0)),"")) | L31: =IF(L6=0,"",IFERROR(INDEX(Lookups!$Q$5:$Q$12,MATCH(Inputs!$E$9,Lookups!$N$5:$N$12,0)),"")) | M31: =IF(M6=0,"",IFERROR(INDEX(Lookups!$O$5:$O$12,MATCH(Inputs!$F$9,Lookups!$N$5:$N$12,0)),"")) | N31: =IF(N6=0,"",IFERROR(INDEX(Lookups!$P$5:$P$12,MATCH(Inputs!$F$9,Lookups!$N$5:$N$12,0)),"")) | O31: =IF(O6=0,"",IFERROR(INDEX(Lookups!$Q$5:$Q$12,MATCH(Inputs!$F$9,Lookups!$N$5:$N$12,0)),"")) | P31: =IF(P6=0,"",IFERROR(INDEX(Lookups!$O$5:$O$12,MATCH(Inputs!$G$9,Lookups!$N$5:$N$12,0)),"")) | Q31: =IF(Q6=0,"",IFERROR(INDEX(Lookups!$P$5:$P$12,MATCH(Inputs!$G$9,Lookups!$N$5:$N$12,0)),"")) | R31: =IF(R6=0,"",IFERROR(INDEX(Lookups!$Q$5:$Q$12,MATCH(Inputs!$G$9,Lookups!$N$5:$N$12,0)),""))
B32: Density in use (blank where the Guide has none) | C32: m2 per FTE | D32: =IF(D6=0,"",IF(AND(ISNUMBER(D31),N(D31)>0),D31,"")) | E32: =IF(E6=0,"",IF(AND(ISNUMBER(E31),N(E31)>0),E31,"")) | F32: =IF(F6=0,"",IF(AND(ISNUMBER(F31),N(F31)>0),F31,"")) | G32: =IF(G6=0,"",IF(AND(ISNUMBER(G31),N(G31)>0),G31,"")) | H32: =IF(H6=0,"",IF(AND(ISNUMBER(H31),N(H31)>0),H31,"")) | I32: =IF(I6=0,"",IF(AND(ISNUMBER(I31),N(I31)>0),I31,"")) | J32: =IF(J6=0,"",IF(AND(ISNUMBER(J31),N(J31)>0),J31,"")) | K32: =IF(K6=0,"",IF(AND(ISNUMBER(K31),N(K31)>0),K31,"")) | ... R32: =IF(R6=0,"",IF(AND(ISNUMBER(R31),N(R31)>0),R31,""))
B33: Density on net internal area (1 = yes) | D33: =IF(D6=0,"",INDEX(Lookups!$S$5:$S$12,MATCH(Inputs!$C$9,Lookups!$N$5:$N$12,0))) | E33: =IF(E6=0,"",INDEX(Lookups!$S$5:$S$12,MATCH(Inputs!$C$9,Lookups!$N$5:$N$12,0))) | F33: =IF(F6=0,"",INDEX(Lookups!$S$5:$S$12,MATCH(Inputs!$C$9,Lookups!$N$5:$N$12,0))) | G33: =IF(G6=0,"",INDEX(Lookups!$S$5:$S$12,MATCH(Inputs!$D$9,Lookups!$N$5:$N$12,0))) | H33: =IF(H6=0,"",INDEX(Lookups!$S$5:$S$12,MATCH(Inputs!$D$9,Lookups!$N$5:$N$12,0))) | I33: =IF(I6=0,"",INDEX(Lookups!$S$5:$S$12,MATCH(Inputs!$D$9,Lookups!$N$5:$N$12,0))) | J33: =IF(J6=0,"",INDEX(Lookups!$S$5:$S$12,MATCH(Inputs!$E$9,Lookups!$N$5:$N$12,0))) | K33: =IF(K6=0,"",INDEX(Lookups!$S$5:$S$12,MATCH(Inputs!$E$9,Lookups!$N$5:$N$12,0))) | L33: =IF(L6=0,"",INDEX(Lookups!$S$5:$S$12,MATCH(Inputs!$E$9,Lookups!$N$5:$N$12,0))) | M33: =IF(M6=0,"",INDEX(Lookups!$S$5:$S$12,MATCH(Inputs!$F$9,Lookups!$N$5:$N$12,0))) | N33: =IF(N6=0,"",INDEX(Lookups!$S$5:$S$12,MATCH(Inputs!$F$9,Lookups!$N$5:$N$12,0))) | O33: =IF(O6=0,"",INDEX(Lookups!$S$5:$S$12,MATCH(Inputs!$F$9,Lookups!$N$5:$N$12,0))) | P33: =IF(P6=0,"",INDEX(Lookups!$S$5:$S$12,MATCH(Inputs!$G$9,Lookups!$N$5:$N$12,0))) | Q33: =IF(Q6=0,"",INDEX(Lookups!$S$5:$S$12,MATCH(Inputs!$G$9,Lookups!$N$5:$N$12,0))) | R33: =IF(R6=0,"",INDEX(Lookups!$S$5:$S$12,MATCH(Inputs!$G$9,Lookups!$N$5:$N$12,0)))
B34: ONS FTE per local unit, matching industry | C34: FTE | D34: =IF(D6=0,"",INDEX(Lookups!$T$5:$T$12,MATCH(Inputs!$C$9,Lookups!$N$5:$N$12,0))) | E34: =IF(E6=0,"",INDEX(Lookups!$T$5:$T$12,MATCH(Inputs!$C$9,Lookups!$N$5:$N$12,0))) | F34: =IF(F6=0,"",INDEX(Lookups!$T$5:$T$12,MATCH(Inputs!$C$9,Lookups!$N$5:$N$12,0))) | G34: =IF(G6=0,"",INDEX(Lookups!$T$5:$T$12,MATCH(Inputs!$D$9,Lookups!$N$5:$N$12,0))) | H34: =IF(H6=0,"",INDEX(Lookups!$T$5:$T$12,MATCH(Inputs!$D$9,Lookups!$N$5:$N$12,0))) | I34: =IF(I6=0,"",INDEX(Lookups!$T$5:$T$12,MATCH(Inputs!$D$9,Lookups!$N$5:$N$12,0))) | J34: =IF(J6=0,"",INDEX(Lookups!$T$5:$T$12,MATCH(Inputs!$E$9,Lookups!$N$5:$N$12,0))) | K34: =IF(K6=0,"",INDEX(Lookups!$T$5:$T$12,MATCH(Inputs!$E$9,Lookups!$N$5:$N$12,0))) | L34: =IF(L6=0,"",INDEX(Lookups!$T$5:$T$12,MATCH(Inputs!$E$9,Lookups!$N$5:$N$12,0))) | M34: =IF(M6=0,"",INDEX(Lookups!$T$5:$T$12,MATCH(Inputs!$F$9,Lookups!$N$5:$N$12,0))) | N34: =IF(N6=0,"",INDEX(Lookups!$T$5:$T$12,MATCH(Inputs!$F$9,Lookups!$N$5:$N$12,0))) | O34: =IF(O6=0,"",INDEX(Lookups!$T$5:$T$12,MATCH(Inputs!$F$9,Lookups!$N$5:$N$12,0))) | P34: =IF(P6=0,"",INDEX(Lookups!$T$5:$T$12,MATCH(Inputs!$G$9,Lookups!$N$5:$N$12,0))) | Q34: =IF(Q6=0,"",INDEX(Lookups!$T$5:$T$12,MATCH(Inputs!$G$9,Lookups!$N$5:$N$12,0))) | R34: =IF(R6=0,"",INDEX(Lookups!$T$5:$T$12,MATCH(Inputs!$G$9,Lookups!$N$5:$N$12,0)))
B35: Gross FTE while open | C35: FTE | D35: =IF(D6=0,"",IF(D30<>"",D30,IF(D32<>"",D28*IF(D33=1,Assumptions!$O$45/100,1)/D32*D29,D34*D29))) | E35: =IF(E6=0,"",IF(E30<>"",E30,IF(E32<>"",E28*IF(E33=1,Assumptions!$O$45/100,1)/E32*E29,E34*E29))) | F35: =IF(F6=0,"",IF(F30<>"",F30,IF(F32<>"",F28*IF(F33=1,Assumptions!$O$45/100,1)/F32*F29,F34*F29))) | G35: =IF(G6=0,"",IF(G30<>"",G30,IF(G32<>"",G28*IF(G33=1,Assumptions!$O$45/100,1)/G32*G29,G34*G29))) | H35: =IF(H6=0,"",IF(H30<>"",H30,IF(H32<>"",H28*IF(H33=1,Assumptions!$O$45/100,1)/H32*H29,H34*H29))) | I35: =IF(I6=0,"",IF(I30<>"",I30,IF(I32<>"",I28*IF(I33=1,Assumptions!$O$45/100,1)/I32*I29,I34*I29))) | J35: =IF(J6=0,"",IF(J30<>"",J30,IF(J32<>"",J28*IF(J33=1,Assumptions!$O$45/100,1)/J32*J29,J34*J29))) | K35: =IF(K6=0,"",IF(K30<>"",K30,IF(K32<>"",K28*IF(K33=1,Assumptions!$O$45/100,1)/K32*K29,K34*K29))) | ... R35: =IF(R6=0,"",IF(R30<>"",R30,IF(R32<>"",R28*IF(R33=1,Assumptions!$O$45/100,1)/R32*R29,R34*R29)))
B36: Grade of the job estimate | D36: =IF(D6=0,"",IF(D30<>"",2,MAX(IF(D32<>"",INDEX(Lookups!$R$5:$R$12,MATCH(Inputs!$C$9,Lookups!$N$5:$N$12,0)),INDEX(Lookups!$U$5:$U$12,MATCH(Inputs!$C$9,Lookups!$N$5:$N$12,0))),IF(Inputs!$C$40<>"",2,Assumptions!$Q$43)))) | E36: =IF(E6=0,"",IF(E30<>"",2,MAX(IF(E32<>"",INDEX(Lookups!$R$5:$R$12,MATCH(Inputs!$C$9,Lookups!$N$5:$N$12,0)),INDEX(Lookups!$U$5:$U$12,MATCH(Inputs!$C$9,Lookups!$N$5:$N$12,0))),IF(Inputs!$C$40<>"",2,Assumptions!$Q$43)))) | F36: =IF(F6=0,"",IF(F30<>"",2,MAX(IF(F32<>"",INDEX(Lookups!$R$5:$R$12,MATCH(Inputs!$C$9,Lookups!$N$5:$N$12,0)),INDEX(Lookups!$U$5:$U$12,MATCH(Inputs!$C$9,Lookups!$N$5:$N$12,0))),IF(Inputs!$C$40<>"",2,Assumptions!$Q$43)))) | G36: =IF(G6=0,"",IF(G30<>"",2,MAX(IF(G32<>"",INDEX(Lookups!$R$5:$R$12,MATCH(Inputs!$D$9,Lookups!$N$5:$N$12,0)),INDEX(Lookups!$U$5:$U$12,MATCH(Inputs!$D$9,Lookups!$N$5:$N$12,0))),IF(Inputs!$D$40<>"",2,Assumptions!$Q$43)))) | H36: =IF(H6=0,"",IF(H30<>"",2,MAX(IF(H32<>"",INDEX(Lookups!$R$5:$R$12,MATCH(Inputs!$D$9,Lookups!$N$5:$N$12,0)),INDEX(Lookups!$U$5:$U$12,MATCH(Inputs!$D$9,Lookups!$N$5:$N$12,0))),IF(Inputs!$D$40<>"",2,Assumptions!$Q$43)))) | I36: =IF(I6=0,"",IF(I30<>"",2,MAX(IF(I32<>"",INDEX(Lookups!$R$5:$R$12,MATCH(Inputs!$D$9,Lookups!$N$5:$N$12,0)),INDEX(Lookups!$U$5:$U$12,MATCH(Inputs!$D$9,Lookups!$N$5:$N$12,0))),IF(Inputs!$D$40<>"",2,Assumptions!$Q$43)))) | J36: =IF(J6=0,"",IF(J30<>"",2,MAX(IF(J32<>"",INDEX(Lookups!$R$5:$R$12,MATCH(Inputs!$E$9,Lookups!$N$5:$N$12,0)),INDEX(Lookups!$U$5:$U$12,MATCH(Inputs!$E$9,Lookups!$N$5:$N$12,0))),IF(Inputs!$E$40<>"",2,Assumptions!$Q$43)))) | K36: =IF(K6=0,"",IF(K30<>"",2,MAX(IF(K32<>"",INDEX(Lookups!$R$5:$R$12,MATCH(Inputs!$E$9,Lookups!$N$5:$N$12,0)),INDEX(Lookups!$U$5:$U$12,MATCH(Inputs!$E$9,Lookups!$N$5:$N$12,0))),IF(Inputs!$E$40<>"",2,Assumptions!$Q$43)))) | L36: =IF(L6=0,"",IF(L30<>"",2,MAX(IF(L32<>"",INDEX(Lookups!$R$5:$R$12,MATCH(Inputs!$E$9,Lookups!$N$5:$N$12,0)),INDEX(Lookups!$U$5:$U$12,MATCH(Inputs!$E$9,Lookups!$N$5:$N$12,0))),IF(Inputs!$E$40<>"",2,Assumptions!$Q$43)))) | M36: =IF(M6=0,"",IF(M30<>"",2,MAX(IF(M32<>"",INDEX(Lookups!$R$5:$R$12,MATCH(Inputs!$F$9,Lookups!$N$5:$N$12,0)),INDEX(Lookups!$U$5:$U$12,MATCH(Inputs!$F$9,Lookups!$N$5:$N$12,0))),IF(Inputs!$F$40<>"",2,Assumptions!$Q$43)))) | N36: =IF(N6=0,"",IF(N30<>"",2,MAX(IF(N32<>"",INDEX(Lookups!$R$5:$R$12,MATCH(Inputs!$F$9,Lookups!$N$5:$N$12,0)),INDEX(Lookups!$U$5:$U$12,MATCH(Inputs!$F$9,Lookups!$N$5:$N$12,0))),IF(Inputs!$F$40<>"",2,Assumptions!$Q$43)))) | O36: =IF(O6=0,"",IF(O30<>"",2,MAX(IF(O32<>"",INDEX(Lookups!$R$5:$R$12,MATCH(Inputs!$F$9,Lookups!$N$5:$N$12,0)),INDEX(Lookups!$U$5:$U$12,MATCH(Inputs!$F$9,Lookups!$N$5:$N$12,0))),IF(Inputs!$F$40<>"",2,Assumptions!$Q$43)))) | P36: =IF(P6=0,"",IF(P30<>"",2,MAX(IF(P32<>"",INDEX(Lookups!$R$5:$R$12,MATCH(Inputs!$G$9,Lookups!$N$5:$N$12,0)),INDEX(Lookups!$U$5:$U$12,MATCH(Inputs!$G$9,Lookups!$N$5:$N$12,0))),IF(Inputs!$G$40<>"",2,Assumptions!$Q$43)))) | Q36: =IF(Q6=0,"",IF(Q30<>"",2,MAX(IF(Q32<>"",INDEX(Lookups!$R$5:$R$12,MATCH(Inputs!$G$9,Lookups!$N$5:$N$12,0)),INDEX(Lookups!$U$5:$U$12,MATCH(Inputs!$G$9,Lookups!$N$5:$N$12,0))),IF(Inputs!$G$40<>"",2,Assumptions!$Q$43)))) | R36: =IF(R6=0,"",IF(R30<>"",2,MAX(IF(R32<>"",INDEX(Lookups!$R$5:$R$12,MATCH(Inputs!$G$9,Lookups!$N$5:$N$12,0)),INDEX(Lookups!$U$5:$U$12,MATCH(Inputs!$G$9,Lookups!$N$5:$N$12,0))),IF(Inputs!$G$40<>"",2,Assumptions!$Q$43))))
B37: Displacement, Gateshead | C37: % | D37: =IF(D6=0,"",INDEX(Lookups!$Z$5:$Z$12,MATCH(Inputs!$C$9,Lookups!$N$5:$N$12,0))) | E37: =IF(E6=0,"",INDEX(Lookups!$AA$5:$AA$12,MATCH(Inputs!$C$9,Lookups!$N$5:$N$12,0))) | F37: =IF(F6=0,"",INDEX(Lookups!$AB$5:$AB$12,MATCH(Inputs!$C$9,Lookups!$N$5:$N$12,0))) | G37: =IF(G6=0,"",INDEX(Lookups!$Z$5:$Z$12,MATCH(Inputs!$D$9,Lookups!$N$5:$N$12,0))) | H37: =IF(H6=0,"",INDEX(Lookups!$AA$5:$AA$12,MATCH(Inputs!$D$9,Lookups!$N$5:$N$12,0))) | I37: =IF(I6=0,"",INDEX(Lookups!$AB$5:$AB$12,MATCH(Inputs!$D$9,Lookups!$N$5:$N$12,0))) | J37: =IF(J6=0,"",INDEX(Lookups!$Z$5:$Z$12,MATCH(Inputs!$E$9,Lookups!$N$5:$N$12,0))) | K37: =IF(K6=0,"",INDEX(Lookups!$AA$5:$AA$12,MATCH(Inputs!$E$9,Lookups!$N$5:$N$12,0))) | L37: =IF(L6=0,"",INDEX(Lookups!$AB$5:$AB$12,MATCH(Inputs!$E$9,Lookups!$N$5:$N$12,0))) | M37: =IF(M6=0,"",INDEX(Lookups!$Z$5:$Z$12,MATCH(Inputs!$F$9,Lookups!$N$5:$N$12,0))) | N37: =IF(N6=0,"",INDEX(Lookups!$AA$5:$AA$12,MATCH(Inputs!$F$9,Lookups!$N$5:$N$12,0))) | O37: =IF(O6=0,"",INDEX(Lookups!$AB$5:$AB$12,MATCH(Inputs!$F$9,Lookups!$N$5:$N$12,0))) | P37: =IF(P6=0,"",INDEX(Lookups!$Z$5:$Z$12,MATCH(Inputs!$G$9,Lookups!$N$5:$N$12,0))) | Q37: =IF(Q6=0,"",INDEX(Lookups!$AA$5:$AA$12,MATCH(Inputs!$G$9,Lookups!$N$5:$N$12,0))) | R37: =IF(R6=0,"",INDEX(Lookups!$AB$5:$AB$12,MATCH(Inputs!$G$9,Lookups!$N$5:$N$12,0)))
B38: Net FTE, Gateshead | C38: FTE | D38: =IF(D6=0,"",D35*D25*(1-D37/100)*Assumptions!$N$58) | E38: =IF(E6=0,"",E35*E25*(1-E37/100)*Assumptions!$O$58) | F38: =IF(F6=0,"",F35*F25*(1-F37/100)*Assumptions!$P$58) | G38: =IF(G6=0,"",G35*G25*(1-G37/100)*Assumptions!$N$58) | H38: =IF(H6=0,"",H35*H25*(1-H37/100)*Assumptions!$O$58) | I38: =IF(I6=0,"",I35*I25*(1-I37/100)*Assumptions!$P$58) | J38: =IF(J6=0,"",J35*J25*(1-J37/100)*Assumptions!$N$58) | K38: =IF(K6=0,"",K35*K25*(1-K37/100)*Assumptions!$O$58) | L38: =IF(L6=0,"",L35*L25*(1-L37/100)*Assumptions!$P$58) | M38: =IF(M6=0,"",M35*M25*(1-M37/100)*Assumptions!$N$58) | N38: =IF(N6=0,"",N35*N25*(1-N37/100)*Assumptions!$O$58) | O38: =IF(O6=0,"",O35*O25*(1-O37/100)*Assumptions!$P$58) | P38: =IF(P6=0,"",P35*P25*(1-P37/100)*Assumptions!$N$58) | Q38: =IF(Q6=0,"",Q35*Q25*(1-Q37/100)*Assumptions!$O$58) | R38: =IF(R6=0,"",R35*R25*(1-R37/100)*Assumptions!$P$58)
B39: Displacement, NEMSA | C39: % | D39: =IF(D6=0,"",INDEX(Lookups!$AC$5:$AC$12,MATCH(Inputs!$C$9,Lookups!$N$5:$N$12,0))) | E39: =IF(E6=0,"",INDEX(Lookups!$AD$5:$AD$12,MATCH(Inputs!$C$9,Lookups!$N$5:$N$12,0))) | F39: =IF(F6=0,"",INDEX(Lookups!$AE$5:$AE$12,MATCH(Inputs!$C$9,Lookups!$N$5:$N$12,0))) | G39: =IF(G6=0,"",INDEX(Lookups!$AC$5:$AC$12,MATCH(Inputs!$D$9,Lookups!$N$5:$N$12,0))) | H39: =IF(H6=0,"",INDEX(Lookups!$AD$5:$AD$12,MATCH(Inputs!$D$9,Lookups!$N$5:$N$12,0))) | I39: =IF(I6=0,"",INDEX(Lookups!$AE$5:$AE$12,MATCH(Inputs!$D$9,Lookups!$N$5:$N$12,0))) | J39: =IF(J6=0,"",INDEX(Lookups!$AC$5:$AC$12,MATCH(Inputs!$E$9,Lookups!$N$5:$N$12,0))) | K39: =IF(K6=0,"",INDEX(Lookups!$AD$5:$AD$12,MATCH(Inputs!$E$9,Lookups!$N$5:$N$12,0))) | L39: =IF(L6=0,"",INDEX(Lookups!$AE$5:$AE$12,MATCH(Inputs!$E$9,Lookups!$N$5:$N$12,0))) | M39: =IF(M6=0,"",INDEX(Lookups!$AC$5:$AC$12,MATCH(Inputs!$F$9,Lookups!$N$5:$N$12,0))) | N39: =IF(N6=0,"",INDEX(Lookups!$AD$5:$AD$12,MATCH(Inputs!$F$9,Lookups!$N$5:$N$12,0))) | O39: =IF(O6=0,"",INDEX(Lookups!$AE$5:$AE$12,MATCH(Inputs!$F$9,Lookups!$N$5:$N$12,0))) | P39: =IF(P6=0,"",INDEX(Lookups!$AC$5:$AC$12,MATCH(Inputs!$G$9,Lookups!$N$5:$N$12,0))) | Q39: =IF(Q6=0,"",INDEX(Lookups!$AD$5:$AD$12,MATCH(Inputs!$G$9,Lookups!$N$5:$N$12,0))) | R39: =IF(R6=0,"",INDEX(Lookups!$AE$5:$AE$12,MATCH(Inputs!$G$9,Lookups!$N$5:$N$12,0)))
B40: Net FTE, NEMSA | C40: FTE | D40: =IF(D6=0,"",D35*D25*(1-D39/100)*Assumptions!$N$70) | E40: =IF(E6=0,"",E35*E25*(1-E39/100)*Assumptions!$O$70) | F40: =IF(F6=0,"",F35*F25*(1-F39/100)*Assumptions!$P$70) | G40: =IF(G6=0,"",G35*G25*(1-G39/100)*Assumptions!$N$70) | H40: =IF(H6=0,"",H35*H25*(1-H39/100)*Assumptions!$O$70) | I40: =IF(I6=0,"",I35*I25*(1-I39/100)*Assumptions!$P$70) | J40: =IF(J6=0,"",J35*J25*(1-J39/100)*Assumptions!$N$70) | K40: =IF(K6=0,"",K35*K25*(1-K39/100)*Assumptions!$O$70) | L40: =IF(L6=0,"",L35*L25*(1-L39/100)*Assumptions!$P$70) | M40: =IF(M6=0,"",M35*M25*(1-M39/100)*Assumptions!$N$70) | N40: =IF(N6=0,"",N35*N25*(1-N39/100)*Assumptions!$O$70) | O40: =IF(O6=0,"",O35*O25*(1-O39/100)*Assumptions!$P$70) | P40: =IF(P6=0,"",P35*P25*(1-P39/100)*Assumptions!$N$70) | Q40: =IF(Q6=0,"",Q35*Q25*(1-Q39/100)*Assumptions!$O$70) | R40: =IF(R6=0,"",R35*R25*(1-R39/100)*Assumptions!$P$70)
B41: Net FTE, UK (full displacement, Green Book 8.41) | C41: FTE | D41: =IF(D6=0,"",0) | E41: =IF(E6=0,"",0) | F41: =IF(F6=0,"",0) | G41: =IF(G6=0,"",0) | H41: =IF(H6=0,"",0) | I41: =IF(I6=0,"",0) | J41: =IF(J6=0,"",0) | K41: =IF(K6=0,"",0) | ... R41: =IF(R6=0,"",0)
B42: GVA per FTE | C42: £ | D42: =IF(D6=0,"",INDEX(Lookups!$V$5:$V$12,MATCH(Inputs!$C$9,Lookups!$N$5:$N$12,0))) | E42: =IF(E6=0,"",INDEX(Lookups!$W$5:$W$12,MATCH(Inputs!$C$9,Lookups!$N$5:$N$12,0))) | F42: =IF(F6=0,"",INDEX(Lookups!$X$5:$X$12,MATCH(Inputs!$C$9,Lookups!$N$5:$N$12,0))) | G42: =IF(G6=0,"",INDEX(Lookups!$V$5:$V$12,MATCH(Inputs!$D$9,Lookups!$N$5:$N$12,0))) | H42: =IF(H6=0,"",INDEX(Lookups!$W$5:$W$12,MATCH(Inputs!$D$9,Lookups!$N$5:$N$12,0))) | I42: =IF(I6=0,"",INDEX(Lookups!$X$5:$X$12,MATCH(Inputs!$D$9,Lookups!$N$5:$N$12,0))) | J42: =IF(J6=0,"",INDEX(Lookups!$V$5:$V$12,MATCH(Inputs!$E$9,Lookups!$N$5:$N$12,0))) | K42: =IF(K6=0,"",INDEX(Lookups!$W$5:$W$12,MATCH(Inputs!$E$9,Lookups!$N$5:$N$12,0))) | L42: =IF(L6=0,"",INDEX(Lookups!$X$5:$X$12,MATCH(Inputs!$E$9,Lookups!$N$5:$N$12,0))) | M42: =IF(M6=0,"",INDEX(Lookups!$V$5:$V$12,MATCH(Inputs!$F$9,Lookups!$N$5:$N$12,0))) | N42: =IF(N6=0,"",INDEX(Lookups!$W$5:$W$12,MATCH(Inputs!$F$9,Lookups!$N$5:$N$12,0))) | O42: =IF(O6=0,"",INDEX(Lookups!$X$5:$X$12,MATCH(Inputs!$F$9,Lookups!$N$5:$N$12,0))) | P42: =IF(P6=0,"",INDEX(Lookups!$V$5:$V$12,MATCH(Inputs!$G$9,Lookups!$N$5:$N$12,0))) | Q42: =IF(Q6=0,"",INDEX(Lookups!$W$5:$W$12,MATCH(Inputs!$G$9,Lookups!$N$5:$N$12,0))) | R42: =IF(R6=0,"",INDEX(Lookups!$X$5:$X$12,MATCH(Inputs!$G$9,Lookups!$N$5:$N$12,0)))
B43: Grade of the GVA estimate | D43: =IF(D6=0,"",MAX(D36,INDEX(Lookups!$Y$5:$Y$12,MATCH(Inputs!$C$9,Lookups!$N$5:$N$12,0)))) | E43: =IF(E6=0,"",MAX(E36,INDEX(Lookups!$Y$5:$Y$12,MATCH(Inputs!$C$9,Lookups!$N$5:$N$12,0)))) | F43: =IF(F6=0,"",MAX(F36,INDEX(Lookups!$Y$5:$Y$12,MATCH(Inputs!$C$9,Lookups!$N$5:$N$12,0)))) | G43: =IF(G6=0,"",MAX(G36,INDEX(Lookups!$Y$5:$Y$12,MATCH(Inputs!$D$9,Lookups!$N$5:$N$12,0)))) | H43: =IF(H6=0,"",MAX(H36,INDEX(Lookups!$Y$5:$Y$12,MATCH(Inputs!$D$9,Lookups!$N$5:$N$12,0)))) | I43: =IF(I6=0,"",MAX(I36,INDEX(Lookups!$Y$5:$Y$12,MATCH(Inputs!$D$9,Lookups!$N$5:$N$12,0)))) | J43: =IF(J6=0,"",MAX(J36,INDEX(Lookups!$Y$5:$Y$12,MATCH(Inputs!$E$9,Lookups!$N$5:$N$12,0)))) | K43: =IF(K6=0,"",MAX(K36,INDEX(Lookups!$Y$5:$Y$12,MATCH(Inputs!$E$9,Lookups!$N$5:$N$12,0)))) | L43: =IF(L6=0,"",MAX(L36,INDEX(Lookups!$Y$5:$Y$12,MATCH(Inputs!$E$9,Lookups!$N$5:$N$12,0)))) | M43: =IF(M6=0,"",MAX(M36,INDEX(Lookups!$Y$5:$Y$12,MATCH(Inputs!$F$9,Lookups!$N$5:$N$12,0)))) | N43: =IF(N6=0,"",MAX(N36,INDEX(Lookups!$Y$5:$Y$12,MATCH(Inputs!$F$9,Lookups!$N$5:$N$12,0)))) | O43: =IF(O6=0,"",MAX(O36,INDEX(Lookups!$Y$5:$Y$12,MATCH(Inputs!$F$9,Lookups!$N$5:$N$12,0)))) | P43: =IF(P6=0,"",MAX(P36,INDEX(Lookups!$Y$5:$Y$12,MATCH(Inputs!$G$9,Lookups!$N$5:$N$12,0)))) | Q43: =IF(Q6=0,"",MAX(Q36,INDEX(Lookups!$Y$5:$Y$12,MATCH(Inputs!$G$9,Lookups!$N$5:$N$12,0)))) | R43: =IF(R6=0,"",MAX(R36,INDEX(Lookups!$Y$5:$Y$12,MATCH(Inputs!$G$9,Lookups!$N$5:$N$12,0))))
B44: GVA supported in Gateshead over the period (present value, after optimism bias) | C44: £ | D44: =IF(D6=0,"",D38*D42*D14*(1-CHOOSE(D43,0,0.05,0.1,0.15,0.25,0.4))) | E44: =IF(E6=0,"",E38*E42*E14*(1-CHOOSE(E43,0,0.05,0.1,0.15,0.25,0.4))) | F44: =IF(F6=0,"",F38*F42*F14*(1-CHOOSE(F43,0,0.05,0.1,0.15,0.25,0.4))) | G44: =IF(G6=0,"",G38*G42*G14*(1-CHOOSE(G43,0,0.05,0.1,0.15,0.25,0.4))) | H44: =IF(H6=0,"",H38*H42*H14*(1-CHOOSE(H43,0,0.05,0.1,0.15,0.25,0.4))) | I44: =IF(I6=0,"",I38*I42*I14*(1-CHOOSE(I43,0,0.05,0.1,0.15,0.25,0.4))) | J44: =IF(J6=0,"",J38*J42*J14*(1-CHOOSE(J43,0,0.05,0.1,0.15,0.25,0.4))) | K44: =IF(K6=0,"",K38*K42*K14*(1-CHOOSE(K43,0,0.05,0.1,0.15,0.25,0.4))) | ... R44: =IF(R6=0,"",R38*R42*R14*(1-CHOOSE(R43,0,0.05,0.1,0.15,0.25,0.4)))
B45: Gross FTE per business or group hosted | C45: FTE | D45: =IF(D6=0,"",D35/MAX(1,N(Inputs!$C$49))) | E45: =IF(E6=0,"",E35/MAX(1,N(Inputs!$C$49))) | F45: =IF(F6=0,"",F35/MAX(1,N(Inputs!$C$49))) | G45: =IF(G6=0,"",G35/MAX(1,N(Inputs!$D$49))) | H45: =IF(H6=0,"",H35/MAX(1,N(Inputs!$D$49))) | I45: =IF(I6=0,"",I35/MAX(1,N(Inputs!$D$49))) | J45: =IF(J6=0,"",J35/MAX(1,N(Inputs!$E$49))) | K45: =IF(K6=0,"",K35/MAX(1,N(Inputs!$E$49))) | L45: =IF(L6=0,"",L35/MAX(1,N(Inputs!$E$49))) | M45: =IF(M6=0,"",M35/MAX(1,N(Inputs!$F$49))) | N45: =IF(N6=0,"",N35/MAX(1,N(Inputs!$F$49))) | O45: =IF(O6=0,"",O35/MAX(1,N(Inputs!$F$49))) | P45: =IF(P6=0,"",P35/MAX(1,N(Inputs!$G$49))) | Q45: =IF(Q6=0,"",Q35/MAX(1,N(Inputs!$G$49))) | R45: =IF(R6=0,"",R35/MAX(1,N(Inputs!$G$49)))
B46: Value of the space
B47: Market rent (rateable value uprated) | C47: £ a year | D47: =IF(D6=0,"",Inputs!$C$13*Assumptions!$O$33) | E47: =IF(E6=0,"",Inputs!$C$13*Assumptions!$O$33) | F47: =IF(F6=0,"",Inputs!$C$13*Assumptions!$O$33) | G47: =IF(G6=0,"",Inputs!$D$13*Assumptions!$O$33) | H47: =IF(H6=0,"",Inputs!$D$13*Assumptions!$O$33) | I47: =IF(I6=0,"",Inputs!$D$13*Assumptions!$O$33) | J47: =IF(J6=0,"",Inputs!$E$13*Assumptions!$O$33) | K47: =IF(K6=0,"",Inputs!$E$13*Assumptions!$O$33) | L47: =IF(L6=0,"",Inputs!$E$13*Assumptions!$O$33) | M47: =IF(M6=0,"",Inputs!$F$13*Assumptions!$O$33) | N47: =IF(N6=0,"",Inputs!$F$13*Assumptions!$O$33) | O47: =IF(O6=0,"",Inputs!$F$13*Assumptions!$O$33) | P47: =IF(P6=0,"",Inputs!$G$13*Assumptions!$O$33) | Q47: =IF(Q6=0,"",Inputs!$G$13*Assumptions!$O$33) | R47: =IF(R6=0,"",Inputs!$G$13*Assumptions!$O$33)
B48: Lower of rent paid and market rent | C48: £ a year | D48: =IF(D6=0,"",MIN(N(Inputs!$C$22),D47)) | E48: =IF(E6=0,"",MIN(N(Inputs!$C$22),E47)) | F48: =IF(F6=0,"",MIN(N(Inputs!$C$22),F47)) | G48: =IF(G6=0,"",MIN(N(Inputs!$D$22),G47)) | H48: =IF(H6=0,"",MIN(N(Inputs!$D$22),H47)) | I48: =IF(I6=0,"",MIN(N(Inputs!$D$22),I47)) | J48: =IF(J6=0,"",MIN(N(Inputs!$E$22),J47)) | K48: =IF(K6=0,"",MIN(N(Inputs!$E$22),K47)) | L48: =IF(L6=0,"",MIN(N(Inputs!$E$22),L47)) | M48: =IF(M6=0,"",MIN(N(Inputs!$F$22),M47)) | N48: =IF(N6=0,"",MIN(N(Inputs!$F$22),N47)) | O48: =IF(O6=0,"",MIN(N(Inputs!$F$22),O47)) | P48: =IF(P6=0,"",MIN(N(Inputs!$G$22),P47)) | Q48: =IF(Q6=0,"",MIN(N(Inputs!$G$22),Q47)) | R48: =IF(R6=0,"",MIN(N(Inputs!$G$22),R47))
B49: Higher of rent paid and market rent | C49: £ a year | D49: =IF(D6=0,"",MAX(N(Inputs!$C$22),D47)) | E49: =IF(E6=0,"",MAX(N(Inputs!$C$22),E47)) | F49: =IF(F6=0,"",MAX(N(Inputs!$C$22),F47)) | G49: =IF(G6=0,"",MAX(N(Inputs!$D$22),G47)) | H49: =IF(H6=0,"",MAX(N(Inputs!$D$22),H47)) | I49: =IF(I6=0,"",MAX(N(Inputs!$D$22),I47)) | J49: =IF(J6=0,"",MAX(N(Inputs!$E$22),J47)) | K49: =IF(K6=0,"",MAX(N(Inputs!$E$22),K47)) | L49: =IF(L6=0,"",MAX(N(Inputs!$E$22),L47)) | M49: =IF(M6=0,"",MAX(N(Inputs!$F$22),M47)) | N49: =IF(N6=0,"",MAX(N(Inputs!$F$22),N47)) | O49: =IF(O6=0,"",MAX(N(Inputs!$F$22),O47)) | P49: =IF(P6=0,"",MAX(N(Inputs!$G$22),P47)) | Q49: =IF(Q6=0,"",MAX(N(Inputs!$G$22),Q47)) | R49: =IF(R6=0,"",MAX(N(Inputs!$G$22),R47))
B50: Value of the space to the occupier | C50: £ a year | D50: =IF(D6=0,"",CHOOSE(1,D48,(D48+D49)/2,D49)) | E50: =IF(E6=0,"",CHOOSE(2,E48,(E48+E49)/2,E49)) | F50: =IF(F6=0,"",CHOOSE(3,F48,(F48+F49)/2,F49)) | G50: =IF(G6=0,"",CHOOSE(1,G48,(G48+G49)/2,G49)) | H50: =IF(H6=0,"",CHOOSE(2,H48,(H48+H49)/2,H49)) | I50: =IF(I6=0,"",CHOOSE(3,I48,(I48+I49)/2,I49)) | J50: =IF(J6=0,"",CHOOSE(1,J48,(J48+J49)/2,J49)) | K50: =IF(K6=0,"",CHOOSE(2,K48,(K48+K49)/2,K49)) | L50: =IF(L6=0,"",CHOOSE(3,L48,(L48+L49)/2,L49)) | M50: =IF(M6=0,"",CHOOSE(1,M48,(M48+M49)/2,M49)) | N50: =IF(N6=0,"",CHOOSE(2,N48,(N48+N49)/2,N49)) | O50: =IF(O6=0,"",CHOOSE(3,O48,(O48+O49)/2,O49)) | P50: =IF(P6=0,"",CHOOSE(1,P48,(P48+P49)/2,P49)) | Q50: =IF(Q6=0,"",CHOOSE(2,Q48,(Q48+Q49)/2,Q49)) | R50: =IF(R6=0,"",CHOOSE(3,R48,(R48+R49)/2,R49))
B51: Additional value of the space | C51: £ a year | D51: =IF(D6=0,"",IF(D24=1,D50*D25,D50-D22*D47)) | E51: =IF(E6=0,"",IF(E24=1,E50*E25,E50-E22*E47)) | F51: =IF(F6=0,"",IF(F24=1,F50*F25,F50-F22*F47)) | G51: =IF(G6=0,"",IF(G24=1,G50*G25,G50-G22*G47)) | H51: =IF(H6=0,"",IF(H24=1,H50*H25,H50-H22*H47)) | I51: =IF(I6=0,"",IF(I24=1,I50*I25,I50-I22*I47)) | J51: =IF(J6=0,"",IF(J24=1,J50*J25,J50-J22*J47)) | K51: =IF(K6=0,"",IF(K24=1,K50*K25,K50-K22*K47)) | ... R51: =IF(R6=0,"",IF(R24=1,R50*R25,R50-R22*R47))
B52: Grade (weakest of V1, V2 and the let-anyway figure) | D52: =IF(D6=0,"",MAX(Assumptions!$Q$31,Assumptions!$Q$32,D23)) | E52: =IF(E6=0,"",MAX(Assumptions!$Q$31,Assumptions!$Q$32,E23)) | F52: =IF(F6=0,"",MAX(Assumptions!$Q$31,Assumptions!$Q$32,F23)) | G52: =IF(G6=0,"",MAX(Assumptions!$Q$31,Assumptions!$Q$32,G23)) | H52: =IF(H6=0,"",MAX(Assumptions!$Q$31,Assumptions!$Q$32,H23)) | I52: =IF(I6=0,"",MAX(Assumptions!$Q$31,Assumptions!$Q$32,I23)) | J52: =IF(J6=0,"",MAX(Assumptions!$Q$31,Assumptions!$Q$32,J23)) | K52: =IF(K6=0,"",MAX(Assumptions!$Q$31,Assumptions!$Q$32,K23)) | ... R52: =IF(R6=0,"",MAX(Assumptions!$Q$31,Assumptions!$Q$32,R23))
B53: Value of the space, present value after optimism bias (none on a disbenefit) | C53: £ | D53: =IF(D6=0,"",D51*(1-IF(D51>0,CHOOSE(D52,0,0.05,0.1,0.15,0.25,0.4),0))*D14) | E53: =IF(E6=0,"",E51*(1-IF(E51>0,CHOOSE(E52,0,0.05,0.1,0.15,0.25,0.4),0))*E14) | F53: =IF(F6=0,"",F51*(1-IF(F51>0,CHOOSE(F52,0,0.05,0.1,0.15,0.25,0.4),0))*F14) | G53: =IF(G6=0,"",G51*(1-IF(G51>0,CHOOSE(G52,0,0.05,0.1,0.15,0.25,0.4),0))*G14) | H53: =IF(H6=0,"",H51*(1-IF(H51>0,CHOOSE(H52,0,0.05,0.1,0.15,0.25,0.4),0))*H14) | I53: =IF(I6=0,"",I51*(1-IF(I51>0,CHOOSE(I52,0,0.05,0.1,0.15,0.25,0.4),0))*I14) | J53: =IF(J6=0,"",J51*(1-IF(J51>0,CHOOSE(J52,0,0.05,0.1,0.15,0.25,0.4),0))*J14) | K53: =IF(K6=0,"",K51*(1-IF(K51>0,CHOOSE(K52,0,0.05,0.1,0.15,0.25,0.4),0))*K14) | ... R53: =IF(R6=0,"",R51*(1-IF(R51>0,CHOOSE(R52,0,0.05,0.1,0.15,0.25,0.4),0))*R14)
B54: Social value
B55: Volunteering | C55: £ a year | D55: =IF(D6=0,"",N(Inputs!$C$41)*Assumptions!$N$80*D26) | E55: =IF(E6=0,"",N(Inputs!$C$41)*Assumptions!$O$80*E26) | F55: =IF(F6=0,"",N(Inputs!$C$41)*Assumptions!$P$80*F26) | G55: =IF(G6=0,"",N(Inputs!$D$41)*Assumptions!$N$80*G26) | H55: =IF(H6=0,"",N(Inputs!$D$41)*Assumptions!$O$80*H26) | I55: =IF(I6=0,"",N(Inputs!$D$41)*Assumptions!$P$80*I26) | J55: =IF(J6=0,"",N(Inputs!$E$41)*Assumptions!$N$80*J26) | K55: =IF(K6=0,"",N(Inputs!$E$41)*Assumptions!$O$80*K26) | L55: =IF(L6=0,"",N(Inputs!$E$41)*Assumptions!$P$80*L26) | M55: =IF(M6=0,"",N(Inputs!$F$41)*Assumptions!$N$80*M26) | N55: =IF(N6=0,"",N(Inputs!$F$41)*Assumptions!$O$80*N26) | O55: =IF(O6=0,"",N(Inputs!$F$41)*Assumptions!$P$80*O26) | P55: =IF(P6=0,"",N(Inputs!$G$41)*Assumptions!$N$80*P26) | Q55: =IF(Q6=0,"",N(Inputs!$G$41)*Assumptions!$O$80*Q26) | R55: =IF(R6=0,"",N(Inputs!$G$41)*Assumptions!$P$80*R26)
B56: Volunteering, present value after optimism bias | C56: £ | D56: =IF(D6=0,"",D55*(1-CHOOSE(Assumptions!$Q$80,0,0.05,0.1,0.15,0.25,0.4))*D15) | E56: =IF(E6=0,"",E55*(1-CHOOSE(Assumptions!$Q$80,0,0.05,0.1,0.15,0.25,0.4))*E15) | F56: =IF(F6=0,"",F55*(1-CHOOSE(Assumptions!$Q$80,0,0.05,0.1,0.15,0.25,0.4))*F15) | G56: =IF(G6=0,"",G55*(1-CHOOSE(Assumptions!$Q$80,0,0.05,0.1,0.15,0.25,0.4))*G15) | H56: =IF(H6=0,"",H55*(1-CHOOSE(Assumptions!$Q$80,0,0.05,0.1,0.15,0.25,0.4))*H15) | I56: =IF(I6=0,"",I55*(1-CHOOSE(Assumptions!$Q$80,0,0.05,0.1,0.15,0.25,0.4))*I15) | J56: =IF(J6=0,"",J55*(1-CHOOSE(Assumptions!$Q$80,0,0.05,0.1,0.15,0.25,0.4))*J15) | K56: =IF(K6=0,"",K55*(1-CHOOSE(Assumptions!$Q$80,0,0.05,0.1,0.15,0.25,0.4))*K15) | ... R56: =IF(R6=0,"",R55*(1-CHOOSE(Assumptions!$Q$80,0,0.05,0.1,0.15,0.25,0.4))*R15)
B57: Value per regular participant | C57: £ a year | D57: =IF(D6=0,"",IFERROR(INDEX(L_GroupValue,MATCH(Inputs!$C$43,L_Group,0)),INDEX(L_GroupValue,1))) | E57: =IF(E6=0,"",IFERROR(INDEX(L_GroupValue,MATCH(Inputs!$C$43,L_Group,0)),INDEX(L_GroupValue,1))) | F57: =IF(F6=0,"",IFERROR(INDEX(L_GroupValue,MATCH(Inputs!$C$43,L_Group,0)),INDEX(L_GroupValue,1))) | G57: =IF(G6=0,"",IFERROR(INDEX(L_GroupValue,MATCH(Inputs!$D$43,L_Group,0)),INDEX(L_GroupValue,1))) | H57: =IF(H6=0,"",IFERROR(INDEX(L_GroupValue,MATCH(Inputs!$D$43,L_Group,0)),INDEX(L_GroupValue,1))) | I57: =IF(I6=0,"",IFERROR(INDEX(L_GroupValue,MATCH(Inputs!$D$43,L_Group,0)),INDEX(L_GroupValue,1))) | J57: =IF(J6=0,"",IFERROR(INDEX(L_GroupValue,MATCH(Inputs!$E$43,L_Group,0)),INDEX(L_GroupValue,1))) | K57: =IF(K6=0,"",IFERROR(INDEX(L_GroupValue,MATCH(Inputs!$E$43,L_Group,0)),INDEX(L_GroupValue,1))) | L57: =IF(L6=0,"",IFERROR(INDEX(L_GroupValue,MATCH(Inputs!$E$43,L_Group,0)),INDEX(L_GroupValue,1))) | M57: =IF(M6=0,"",IFERROR(INDEX(L_GroupValue,MATCH(Inputs!$F$43,L_Group,0)),INDEX(L_GroupValue,1))) | N57: =IF(N6=0,"",IFERROR(INDEX(L_GroupValue,MATCH(Inputs!$F$43,L_Group,0)),INDEX(L_GroupValue,1))) | O57: =IF(O6=0,"",IFERROR(INDEX(L_GroupValue,MATCH(Inputs!$F$43,L_Group,0)),INDEX(L_GroupValue,1))) | P57: =IF(P6=0,"",IFERROR(INDEX(L_GroupValue,MATCH(Inputs!$G$43,L_Group,0)),INDEX(L_GroupValue,1))) | Q57: =IF(Q6=0,"",IFERROR(INDEX(L_GroupValue,MATCH(Inputs!$G$43,L_Group,0)),INDEX(L_GroupValue,1))) | R57: =IF(R6=0,"",IFERROR(INDEX(L_GroupValue,MATCH(Inputs!$G$43,L_Group,0)),INDEX(L_GroupValue,1)))
B58: Regular participation | C58: £ a year | D58: =IF(D6=0,"",N(Inputs!$C$42)*D57*D26) | E58: =IF(E6=0,"",N(Inputs!$C$42)*E57*E26) | F58: =IF(F6=0,"",N(Inputs!$C$42)*F57*F26) | G58: =IF(G6=0,"",N(Inputs!$D$42)*G57*G26) | H58: =IF(H6=0,"",N(Inputs!$D$42)*H57*H26) | I58: =IF(I6=0,"",N(Inputs!$D$42)*I57*I26) | J58: =IF(J6=0,"",N(Inputs!$E$42)*J57*J26) | K58: =IF(K6=0,"",N(Inputs!$E$42)*K57*K26) | L58: =IF(L6=0,"",N(Inputs!$E$42)*L57*L26) | M58: =IF(M6=0,"",N(Inputs!$F$42)*M57*M26) | N58: =IF(N6=0,"",N(Inputs!$F$42)*N57*N26) | O58: =IF(O6=0,"",N(Inputs!$F$42)*O57*O26) | P58: =IF(P6=0,"",N(Inputs!$G$42)*P57*P26) | Q58: =IF(Q6=0,"",N(Inputs!$G$42)*Q57*Q26) | R58: =IF(R6=0,"",N(Inputs!$G$42)*R57*R26)
B59: Regular participation, present value after optimism bias | C59: £ | D59: =IF(D6=0,"",D58*(1-CHOOSE(Assumptions!$Q$84,0,0.05,0.1,0.15,0.25,0.4))*D15) | E59: =IF(E6=0,"",E58*(1-CHOOSE(Assumptions!$Q$84,0,0.05,0.1,0.15,0.25,0.4))*E15) | F59: =IF(F6=0,"",F58*(1-CHOOSE(Assumptions!$Q$84,0,0.05,0.1,0.15,0.25,0.4))*F15) | G59: =IF(G6=0,"",G58*(1-CHOOSE(Assumptions!$Q$84,0,0.05,0.1,0.15,0.25,0.4))*G15) | H59: =IF(H6=0,"",H58*(1-CHOOSE(Assumptions!$Q$84,0,0.05,0.1,0.15,0.25,0.4))*H15) | I59: =IF(I6=0,"",I58*(1-CHOOSE(Assumptions!$Q$84,0,0.05,0.1,0.15,0.25,0.4))*I15) | J59: =IF(J6=0,"",J58*(1-CHOOSE(Assumptions!$Q$84,0,0.05,0.1,0.15,0.25,0.4))*J15) | K59: =IF(K6=0,"",K58*(1-CHOOSE(Assumptions!$Q$84,0,0.05,0.1,0.15,0.25,0.4))*K15) | ... R59: =IF(R6=0,"",R58*(1-CHOOSE(Assumptions!$Q$84,0,0.05,0.1,0.15,0.25,0.4))*R15)
B60: Jobs filled by previously unemployed residents | C60: people | D60: =IF(D6=0,"",IF(Inputs!$C$44<>"",Inputs!$C$44*D25,D38*Assumptions!$N$82/100)) | E60: =IF(E6=0,"",IF(Inputs!$C$44<>"",Inputs!$C$44*E25,E38*Assumptions!$O$82/100)) | F60: =IF(F6=0,"",IF(Inputs!$C$44<>"",Inputs!$C$44*F25,F38*Assumptions!$P$82/100)) | G60: =IF(G6=0,"",IF(Inputs!$D$44<>"",Inputs!$D$44*G25,G38*Assumptions!$N$82/100)) | H60: =IF(H6=0,"",IF(Inputs!$D$44<>"",Inputs!$D$44*H25,H38*Assumptions!$O$82/100)) | I60: =IF(I6=0,"",IF(Inputs!$D$44<>"",Inputs!$D$44*I25,I38*Assumptions!$P$82/100)) | J60: =IF(J6=0,"",IF(Inputs!$E$44<>"",Inputs!$E$44*J25,J38*Assumptions!$N$82/100)) | K60: =IF(K6=0,"",IF(Inputs!$E$44<>"",Inputs!$E$44*K25,K38*Assumptions!$O$82/100)) | L60: =IF(L6=0,"",IF(Inputs!$E$44<>"",Inputs!$E$44*L25,L38*Assumptions!$P$82/100)) | M60: =IF(M6=0,"",IF(Inputs!$F$44<>"",Inputs!$F$44*M25,M38*Assumptions!$N$82/100)) | N60: =IF(N6=0,"",IF(Inputs!$F$44<>"",Inputs!$F$44*N25,N38*Assumptions!$O$82/100)) | O60: =IF(O6=0,"",IF(Inputs!$F$44<>"",Inputs!$F$44*O25,O38*Assumptions!$P$82/100)) | P60: =IF(P6=0,"",IF(Inputs!$G$44<>"",Inputs!$G$44*P25,P38*Assumptions!$N$82/100)) | Q60: =IF(Q6=0,"",IF(Inputs!$G$44<>"",Inputs!$G$44*Q25,Q38*Assumptions!$O$82/100)) | R60: =IF(R6=0,"",IF(Inputs!$G$44<>"",Inputs!$G$44*R25,R38*Assumptions!$P$82/100))
B61: Grade | D61: =IF(D6=0,"",IF(Inputs!$C$44<>"",MAX(Assumptions!$Q$81,Assumptions!$Q$83),MAX(Assumptions!$Q$81,Assumptions!$Q$82,Assumptions!$Q$83,D36))) | E61: =IF(E6=0,"",IF(Inputs!$C$44<>"",MAX(Assumptions!$Q$81,Assumptions!$Q$83),MAX(Assumptions!$Q$81,Assumptions!$Q$82,Assumptions!$Q$83,E36))) | F61: =IF(F6=0,"",IF(Inputs!$C$44<>"",MAX(Assumptions!$Q$81,Assumptions!$Q$83),MAX(Assumptions!$Q$81,Assumptions!$Q$82,Assumptions!$Q$83,F36))) | G61: =IF(G6=0,"",IF(Inputs!$D$44<>"",MAX(Assumptions!$Q$81,Assumptions!$Q$83),MAX(Assumptions!$Q$81,Assumptions!$Q$82,Assumptions!$Q$83,G36))) | H61: =IF(H6=0,"",IF(Inputs!$D$44<>"",MAX(Assumptions!$Q$81,Assumptions!$Q$83),MAX(Assumptions!$Q$81,Assumptions!$Q$82,Assumptions!$Q$83,H36))) | I61: =IF(I6=0,"",IF(Inputs!$D$44<>"",MAX(Assumptions!$Q$81,Assumptions!$Q$83),MAX(Assumptions!$Q$81,Assumptions!$Q$82,Assumptions!$Q$83,I36))) | J61: =IF(J6=0,"",IF(Inputs!$E$44<>"",MAX(Assumptions!$Q$81,Assumptions!$Q$83),MAX(Assumptions!$Q$81,Assumptions!$Q$82,Assumptions!$Q$83,J36))) | K61: =IF(K6=0,"",IF(Inputs!$E$44<>"",MAX(Assumptions!$Q$81,Assumptions!$Q$83),MAX(Assumptions!$Q$81,Assumptions!$Q$82,Assumptions!$Q$83,K36))) | L61: =IF(L6=0,"",IF(Inputs!$E$44<>"",MAX(Assumptions!$Q$81,Assumptions!$Q$83),MAX(Assumptions!$Q$81,Assumptions!$Q$82,Assumptions!$Q$83,L36))) | M61: =IF(M6=0,"",IF(Inputs!$F$44<>"",MAX(Assumptions!$Q$81,Assumptions!$Q$83),MAX(Assumptions!$Q$81,Assumptions!$Q$82,Assumptions!$Q$83,M36))) | N61: =IF(N6=0,"",IF(Inputs!$F$44<>"",MAX(Assumptions!$Q$81,Assumptions!$Q$83),MAX(Assumptions!$Q$81,Assumptions!$Q$82,Assumptions!$Q$83,N36))) | O61: =IF(O6=0,"",IF(Inputs!$F$44<>"",MAX(Assumptions!$Q$81,Assumptions!$Q$83),MAX(Assumptions!$Q$81,Assumptions!$Q$82,Assumptions!$Q$83,O36))) | P61: =IF(P6=0,"",IF(Inputs!$G$44<>"",MAX(Assumptions!$Q$81,Assumptions!$Q$83),MAX(Assumptions!$Q$81,Assumptions!$Q$82,Assumptions!$Q$83,P36))) | Q61: =IF(Q6=0,"",IF(Inputs!$G$44<>"",MAX(Assumptions!$Q$81,Assumptions!$Q$83),MAX(Assumptions!$Q$81,Assumptions!$Q$82,Assumptions!$Q$83,Q36))) | R61: =IF(R6=0,"",IF(Inputs!$G$44<>"",MAX(Assumptions!$Q$81,Assumptions!$Q$83),MAX(Assumptions!$Q$81,Assumptions!$Q$82,Assumptions!$Q$83,R36)))
B62: Employment wellbeing | C62: £ a year | D62: =IF(D6=0,"",D60*(1-Assumptions!$O$83/100)*Assumptions!$N$81) | E62: =IF(E6=0,"",E60*(1-Assumptions!$O$83/100)*Assumptions!$O$81) | F62: =IF(F6=0,"",F60*(1-Assumptions!$O$83/100)*Assumptions!$P$81) | G62: =IF(G6=0,"",G60*(1-Assumptions!$O$83/100)*Assumptions!$N$81) | H62: =IF(H6=0,"",H60*(1-Assumptions!$O$83/100)*Assumptions!$O$81) | I62: =IF(I6=0,"",I60*(1-Assumptions!$O$83/100)*Assumptions!$P$81) | J62: =IF(J6=0,"",J60*(1-Assumptions!$O$83/100)*Assumptions!$N$81) | K62: =IF(K6=0,"",K60*(1-Assumptions!$O$83/100)*Assumptions!$O$81) | L62: =IF(L6=0,"",L60*(1-Assumptions!$O$83/100)*Assumptions!$P$81) | M62: =IF(M6=0,"",M60*(1-Assumptions!$O$83/100)*Assumptions!$N$81) | N62: =IF(N6=0,"",N60*(1-Assumptions!$O$83/100)*Assumptions!$O$81) | O62: =IF(O6=0,"",O60*(1-Assumptions!$O$83/100)*Assumptions!$P$81) | P62: =IF(P6=0,"",P60*(1-Assumptions!$O$83/100)*Assumptions!$N$81) | Q62: =IF(Q6=0,"",Q60*(1-Assumptions!$O$83/100)*Assumptions!$O$81) | R62: =IF(R6=0,"",R60*(1-Assumptions!$O$83/100)*Assumptions!$P$81)
B63: Employment wellbeing, present value after optimism bias | C63: £ | D63: =IF(D6=0,"",D62*(1-CHOOSE(D61,0,0.05,0.1,0.15,0.25,0.4))*D15) | E63: =IF(E6=0,"",E62*(1-CHOOSE(E61,0,0.05,0.1,0.15,0.25,0.4))*E15) | F63: =IF(F6=0,"",F62*(1-CHOOSE(F61,0,0.05,0.1,0.15,0.25,0.4))*F15) | G63: =IF(G6=0,"",G62*(1-CHOOSE(G61,0,0.05,0.1,0.15,0.25,0.4))*G15) | H63: =IF(H6=0,"",H62*(1-CHOOSE(H61,0,0.05,0.1,0.15,0.25,0.4))*H15) | I63: =IF(I6=0,"",I62*(1-CHOOSE(I61,0,0.05,0.1,0.15,0.25,0.4))*I15) | J63: =IF(J6=0,"",J62*(1-CHOOSE(J61,0,0.05,0.1,0.15,0.25,0.4))*J15) | K63: =IF(K6=0,"",K62*(1-CHOOSE(K61,0,0.05,0.1,0.15,0.25,0.4))*K15) | ... R63: =IF(R6=0,"",R62*(1-CHOOSE(R61,0,0.05,0.1,0.15,0.25,0.4))*R15)
B64: Cost of keeping the unit empty, avoided (after a let anyway) | C64: £ a year | D64: =IF(D6=0,"",IF(N(Inputs!$C$17)>0,Inputs!$C$17,IF(Inputs!$C$15="Council",N(Inputs!$C$16)*Assumptions!$O$28/100,0))*D25) | E64: =IF(E6=0,"",IF(N(Inputs!$C$17)>0,Inputs!$C$17,IF(Inputs!$C$15="Council",N(Inputs!$C$16)*Assumptions!$O$28/100,0))*E25) | F64: =IF(F6=0,"",IF(N(Inputs!$C$17)>0,Inputs!$C$17,IF(Inputs!$C$15="Council",N(Inputs!$C$16)*Assumptions!$O$28/100,0))*F25) | G64: =IF(G6=0,"",IF(N(Inputs!$D$17)>0,Inputs!$D$17,IF(Inputs!$D$15="Council",N(Inputs!$D$16)*Assumptions!$O$28/100,0))*G25) | H64: =IF(H6=0,"",IF(N(Inputs!$D$17)>0,Inputs!$D$17,IF(Inputs!$D$15="Council",N(Inputs!$D$16)*Assumptions!$O$28/100,0))*H25) | I64: =IF(I6=0,"",IF(N(Inputs!$D$17)>0,Inputs!$D$17,IF(Inputs!$D$15="Council",N(Inputs!$D$16)*Assumptions!$O$28/100,0))*I25) | J64: =IF(J6=0,"",IF(N(Inputs!$E$17)>0,Inputs!$E$17,IF(Inputs!$E$15="Council",N(Inputs!$E$16)*Assumptions!$O$28/100,0))*J25) | K64: =IF(K6=0,"",IF(N(Inputs!$E$17)>0,Inputs!$E$17,IF(Inputs!$E$15="Council",N(Inputs!$E$16)*Assumptions!$O$28/100,0))*K25) | L64: =IF(L6=0,"",IF(N(Inputs!$E$17)>0,Inputs!$E$17,IF(Inputs!$E$15="Council",N(Inputs!$E$16)*Assumptions!$O$28/100,0))*L25) | M64: =IF(M6=0,"",IF(N(Inputs!$F$17)>0,Inputs!$F$17,IF(Inputs!$F$15="Council",N(Inputs!$F$16)*Assumptions!$O$28/100,0))*M25) | N64: =IF(N6=0,"",IF(N(Inputs!$F$17)>0,Inputs!$F$17,IF(Inputs!$F$15="Council",N(Inputs!$F$16)*Assumptions!$O$28/100,0))*N25) | O64: =IF(O6=0,"",IF(N(Inputs!$F$17)>0,Inputs!$F$17,IF(Inputs!$F$15="Council",N(Inputs!$F$16)*Assumptions!$O$28/100,0))*O25) | P64: =IF(P6=0,"",IF(N(Inputs!$G$17)>0,Inputs!$G$17,IF(Inputs!$G$15="Council",N(Inputs!$G$16)*Assumptions!$O$28/100,0))*P25) | Q64: =IF(Q6=0,"",IF(N(Inputs!$G$17)>0,Inputs!$G$17,IF(Inputs!$G$15="Council",N(Inputs!$G$16)*Assumptions!$O$28/100,0))*Q25) | R64: =IF(R6=0,"",IF(N(Inputs!$G$17)>0,Inputs!$G$17,IF(Inputs!$G$15="Council",N(Inputs!$G$16)*Assumptions!$O$28/100,0))*R25)
B65: Grade | D65: =IF(D6=0,"",IF(N(Inputs!$C$17)>0,4,6)) | E65: =IF(E6=0,"",IF(N(Inputs!$C$17)>0,4,6)) | F65: =IF(F6=0,"",IF(N(Inputs!$C$17)>0,4,6)) | G65: =IF(G6=0,"",IF(N(Inputs!$D$17)>0,4,6)) | H65: =IF(H6=0,"",IF(N(Inputs!$D$17)>0,4,6)) | I65: =IF(I6=0,"",IF(N(Inputs!$D$17)>0,4,6)) | J65: =IF(J6=0,"",IF(N(Inputs!$E$17)>0,4,6)) | K65: =IF(K6=0,"",IF(N(Inputs!$E$17)>0,4,6)) | L65: =IF(L6=0,"",IF(N(Inputs!$E$17)>0,4,6)) | M65: =IF(M6=0,"",IF(N(Inputs!$F$17)>0,4,6)) | N65: =IF(N6=0,"",IF(N(Inputs!$F$17)>0,4,6)) | O65: =IF(O6=0,"",IF(N(Inputs!$F$17)>0,4,6)) | P65: =IF(P6=0,"",IF(N(Inputs!$G$17)>0,4,6)) | Q65: =IF(Q6=0,"",IF(N(Inputs!$G$17)>0,4,6)) | R65: =IF(R6=0,"",IF(N(Inputs!$G$17)>0,4,6))
B66: Avoided empty-unit costs to a private owner, present value | C66: £ | D66: =IF(D6=0,"",IF(Inputs!$C$15="Private",D64,0)*(1-CHOOSE(D65,0,0.05,0.1,0.15,0.25,0.4))*D14) | E66: =IF(E6=0,"",IF(Inputs!$C$15="Private",E64,0)*(1-CHOOSE(E65,0,0.05,0.1,0.15,0.25,0.4))*E14) | F66: =IF(F6=0,"",IF(Inputs!$C$15="Private",F64,0)*(1-CHOOSE(F65,0,0.05,0.1,0.15,0.25,0.4))*F14) | G66: =IF(G6=0,"",IF(Inputs!$D$15="Private",G64,0)*(1-CHOOSE(G65,0,0.05,0.1,0.15,0.25,0.4))*G14) | H66: =IF(H6=0,"",IF(Inputs!$D$15="Private",H64,0)*(1-CHOOSE(H65,0,0.05,0.1,0.15,0.25,0.4))*H14) | I66: =IF(I6=0,"",IF(Inputs!$D$15="Private",I64,0)*(1-CHOOSE(I65,0,0.05,0.1,0.15,0.25,0.4))*I14) | J66: =IF(J6=0,"",IF(Inputs!$E$15="Private",J64,0)*(1-CHOOSE(J65,0,0.05,0.1,0.15,0.25,0.4))*J14) | K66: =IF(K6=0,"",IF(Inputs!$E$15="Private",K64,0)*(1-CHOOSE(K65,0,0.05,0.1,0.15,0.25,0.4))*K14) | L66: =IF(L6=0,"",IF(Inputs!$E$15="Private",L64,0)*(1-CHOOSE(L65,0,0.05,0.1,0.15,0.25,0.4))*L14) | M66: =IF(M6=0,"",IF(Inputs!$F$15="Private",M64,0)*(1-CHOOSE(M65,0,0.05,0.1,0.15,0.25,0.4))*M14) | N66: =IF(N6=0,"",IF(Inputs!$F$15="Private",N64,0)*(1-CHOOSE(N65,0,0.05,0.1,0.15,0.25,0.4))*N14) | O66: =IF(O6=0,"",IF(Inputs!$F$15="Private",O64,0)*(1-CHOOSE(O65,0,0.05,0.1,0.15,0.25,0.4))*O14) | P66: =IF(P6=0,"",IF(Inputs!$G$15="Private",P64,0)*(1-CHOOSE(P65,0,0.05,0.1,0.15,0.25,0.4))*P14) | Q66: =IF(Q6=0,"",IF(Inputs!$G$15="Private",Q64,0)*(1-CHOOSE(Q65,0,0.05,0.1,0.15,0.25,0.4))*Q14) | R66: =IF(R6=0,"",IF(Inputs!$G$15="Private",R64,0)*(1-CHOOSE(R65,0,0.05,0.1,0.15,0.25,0.4))*R14)
B67: Discounted years of a permanent let after the occupation | D67: =IF(D6=0,"",(1+Settings!$B$6)^-ROUNDUP(D8,0)*(1-(1+Settings!$B$6)^-Assumptions!$O$95)/(1-(1+Settings!$B$6)^-1)) | E67: =IF(E6=0,"",(1+Settings!$B$6)^-ROUNDUP(E8,0)*(1-(1+Settings!$B$6)^-Assumptions!$O$95)/(1-(1+Settings!$B$6)^-1)) | F67: =IF(F6=0,"",(1+Settings!$B$6)^-ROUNDUP(F8,0)*(1-(1+Settings!$B$6)^-Assumptions!$O$95)/(1-(1+Settings!$B$6)^-1)) | G67: =IF(G6=0,"",(1+Settings!$B$6)^-ROUNDUP(G8,0)*(1-(1+Settings!$B$6)^-Assumptions!$O$95)/(1-(1+Settings!$B$6)^-1)) | H67: =IF(H6=0,"",(1+Settings!$B$6)^-ROUNDUP(H8,0)*(1-(1+Settings!$B$6)^-Assumptions!$O$95)/(1-(1+Settings!$B$6)^-1)) | I67: =IF(I6=0,"",(1+Settings!$B$6)^-ROUNDUP(I8,0)*(1-(1+Settings!$B$6)^-Assumptions!$O$95)/(1-(1+Settings!$B$6)^-1)) | J67: =IF(J6=0,"",(1+Settings!$B$6)^-ROUNDUP(J8,0)*(1-(1+Settings!$B$6)^-Assumptions!$O$95)/(1-(1+Settings!$B$6)^-1)) | K67: =IF(K6=0,"",(1+Settings!$B$6)^-ROUNDUP(K8,0)*(1-(1+Settings!$B$6)^-Assumptions!$O$95)/(1-(1+Settings!$B$6)^-1)) | ... R67: =IF(R6=0,"",(1+Settings!$B$6)^-ROUNDUP(R8,0)*(1-(1+Settings!$B$6)^-Assumptions!$O$95)/(1-(1+Settings!$B$6)^-1))
B68: Legacy of a permanent let, present value after optimism bias | C68: £ | D68: =IF(D6=0,"",N(Inputs!$C$53)*D47*D67*(1-CHOOSE(6,0,0.05,0.1,0.15,0.25,0.4))) | E68: =IF(E6=0,"",N(Inputs!$C$53)*E47*E67*(1-CHOOSE(6,0,0.05,0.1,0.15,0.25,0.4))) | F68: =IF(F6=0,"",N(Inputs!$C$53)*F47*F67*(1-CHOOSE(6,0,0.05,0.1,0.15,0.25,0.4))) | G68: =IF(G6=0,"",N(Inputs!$D$53)*G47*G67*(1-CHOOSE(6,0,0.05,0.1,0.15,0.25,0.4))) | H68: =IF(H6=0,"",N(Inputs!$D$53)*H47*H67*(1-CHOOSE(6,0,0.05,0.1,0.15,0.25,0.4))) | I68: =IF(I6=0,"",N(Inputs!$D$53)*I47*I67*(1-CHOOSE(6,0,0.05,0.1,0.15,0.25,0.4))) | J68: =IF(J6=0,"",N(Inputs!$E$53)*J47*J67*(1-CHOOSE(6,0,0.05,0.1,0.15,0.25,0.4))) | K68: =IF(K6=0,"",N(Inputs!$E$53)*K47*K67*(1-CHOOSE(6,0,0.05,0.1,0.15,0.25,0.4))) | L68: =IF(L6=0,"",N(Inputs!$E$53)*L47*L67*(1-CHOOSE(6,0,0.05,0.1,0.15,0.25,0.4))) | M68: =IF(M6=0,"",N(Inputs!$F$53)*M47*M67*(1-CHOOSE(6,0,0.05,0.1,0.15,0.25,0.4))) | N68: =IF(N6=0,"",N(Inputs!$F$53)*N47*N67*(1-CHOOSE(6,0,0.05,0.1,0.15,0.25,0.4))) | O68: =IF(O6=0,"",N(Inputs!$F$53)*O47*O67*(1-CHOOSE(6,0,0.05,0.1,0.15,0.25,0.4))) | P68: =IF(P6=0,"",N(Inputs!$G$53)*P47*P67*(1-CHOOSE(6,0,0.05,0.1,0.15,0.25,0.4))) | Q68: =IF(Q6=0,"",N(Inputs!$G$53)*Q47*Q67*(1-CHOOSE(6,0,0.05,0.1,0.15,0.25,0.4))) | R68: =IF(R6=0,"",N(Inputs!$G$53)*R47*R67*(1-CHOOSE(6,0,0.05,0.1,0.15,0.25,0.4)))
B69: Business rates and rent (transfers)
B70: Multiplier while occupied | D70: =IF(D6=0,"",IF(Inputs!$C$13>=500000,'Static Data'!$B$10,IF(Inputs!$C$13<51000,IF(Inputs!$C$25="Yes",'Static Data'!$B$7,'Static Data'!$B$6),IF(Inputs!$C$25="Yes",'Static Data'!$B$9,'Static Data'!$B$8)))) | E70: =IF(E6=0,"",IF(Inputs!$C$13>=500000,'Static Data'!$B$10,IF(Inputs!$C$13<51000,IF(Inputs!$C$25="Yes",'Static Data'!$B$7,'Static Data'!$B$6),IF(Inputs!$C$25="Yes",'Static Data'!$B$9,'Static Data'!$B$8)))) | F70: =IF(F6=0,"",IF(Inputs!$C$13>=500000,'Static Data'!$B$10,IF(Inputs!$C$13<51000,IF(Inputs!$C$25="Yes",'Static Data'!$B$7,'Static Data'!$B$6),IF(Inputs!$C$25="Yes",'Static Data'!$B$9,'Static Data'!$B$8)))) | G70: =IF(G6=0,"",IF(Inputs!$D$13>=500000,'Static Data'!$B$10,IF(Inputs!$D$13<51000,IF(Inputs!$D$25="Yes",'Static Data'!$B$7,'Static Data'!$B$6),IF(Inputs!$D$25="Yes",'Static Data'!$B$9,'Static Data'!$B$8)))) | H70: =IF(H6=0,"",IF(Inputs!$D$13>=500000,'Static Data'!$B$10,IF(Inputs!$D$13<51000,IF(Inputs!$D$25="Yes",'Static Data'!$B$7,'Static Data'!$B$6),IF(Inputs!$D$25="Yes",'Static Data'!$B$9,'Static Data'!$B$8)))) | I70: =IF(I6=0,"",IF(Inputs!$D$13>=500000,'Static Data'!$B$10,IF(Inputs!$D$13<51000,IF(Inputs!$D$25="Yes",'Static Data'!$B$7,'Static Data'!$B$6),IF(Inputs!$D$25="Yes",'Static Data'!$B$9,'Static Data'!$B$8)))) | J70: =IF(J6=0,"",IF(Inputs!$E$13>=500000,'Static Data'!$B$10,IF(Inputs!$E$13<51000,IF(Inputs!$E$25="Yes",'Static Data'!$B$7,'Static Data'!$B$6),IF(Inputs!$E$25="Yes",'Static Data'!$B$9,'Static Data'!$B$8)))) | K70: =IF(K6=0,"",IF(Inputs!$E$13>=500000,'Static Data'!$B$10,IF(Inputs!$E$13<51000,IF(Inputs!$E$25="Yes",'Static Data'!$B$7,'Static Data'!$B$6),IF(Inputs!$E$25="Yes",'Static Data'!$B$9,'Static Data'!$B$8)))) | L70: =IF(L6=0,"",IF(Inputs!$E$13>=500000,'Static Data'!$B$10,IF(Inputs!$E$13<51000,IF(Inputs!$E$25="Yes",'Static Data'!$B$7,'Static Data'!$B$6),IF(Inputs!$E$25="Yes",'Static Data'!$B$9,'Static Data'!$B$8)))) | M70: =IF(M6=0,"",IF(Inputs!$F$13>=500000,'Static Data'!$B$10,IF(Inputs!$F$13<51000,IF(Inputs!$F$25="Yes",'Static Data'!$B$7,'Static Data'!$B$6),IF(Inputs!$F$25="Yes",'Static Data'!$B$9,'Static Data'!$B$8)))) | N70: =IF(N6=0,"",IF(Inputs!$F$13>=500000,'Static Data'!$B$10,IF(Inputs!$F$13<51000,IF(Inputs!$F$25="Yes",'Static Data'!$B$7,'Static Data'!$B$6),IF(Inputs!$F$25="Yes",'Static Data'!$B$9,'Static Data'!$B$8)))) | O70: =IF(O6=0,"",IF(Inputs!$F$13>=500000,'Static Data'!$B$10,IF(Inputs!$F$13<51000,IF(Inputs!$F$25="Yes",'Static Data'!$B$7,'Static Data'!$B$6),IF(Inputs!$F$25="Yes",'Static Data'!$B$9,'Static Data'!$B$8)))) | P70: =IF(P6=0,"",IF(Inputs!$G$13>=500000,'Static Data'!$B$10,IF(Inputs!$G$13<51000,IF(Inputs!$G$25="Yes",'Static Data'!$B$7,'Static Data'!$B$6),IF(Inputs!$G$25="Yes",'Static Data'!$B$9,'Static Data'!$B$8)))) | Q70: =IF(Q6=0,"",IF(Inputs!$G$13>=500000,'Static Data'!$B$10,IF(Inputs!$G$13<51000,IF(Inputs!$G$25="Yes",'Static Data'!$B$7,'Static Data'!$B$6),IF(Inputs!$G$25="Yes",'Static Data'!$B$9,'Static Data'!$B$8)))) | R70: =IF(R6=0,"",IF(Inputs!$G$13>=500000,'Static Data'!$B$10,IF(Inputs!$G$13<51000,IF(Inputs!$G$25="Yes",'Static Data'!$B$7,'Static Data'!$B$6),IF(Inputs!$G$25="Yes",'Static Data'!$B$9,'Static Data'!$B$8))))
B71: Rates bill while occupied | C71: £ a year | D71: =IF(D6=0,"",Inputs!$C$13*D70) | E71: =IF(E6=0,"",Inputs!$C$13*E70) | F71: =IF(F6=0,"",Inputs!$C$13*F70) | G71: =IF(G6=0,"",Inputs!$D$13*G70) | H71: =IF(H6=0,"",Inputs!$D$13*H70) | I71: =IF(I6=0,"",Inputs!$D$13*I70) | J71: =IF(J6=0,"",Inputs!$E$13*J70) | K71: =IF(K6=0,"",Inputs!$E$13*K70) | L71: =IF(L6=0,"",Inputs!$E$13*L70) | M71: =IF(M6=0,"",Inputs!$F$13*M70) | N71: =IF(N6=0,"",Inputs!$F$13*N70) | O71: =IF(O6=0,"",Inputs!$F$13*O70) | P71: =IF(P6=0,"",Inputs!$G$13*P70) | Q71: =IF(Q6=0,"",Inputs!$G$13*Q70) | R71: =IF(R6=0,"",Inputs!$G$13*R70)
B72: Mandatory or small business relief | C72: share | D72: =IF(D6=0,"",IF(Inputs!$C$24="Charity",'Static Data'!$B$14,IF(Inputs!$C$24="Small business (only property)",IF(Inputs!$C$13<='Static Data'!$B$12,1,IF(Inputs!$C$13<'Static Data'!$B$13,('Static Data'!$B$13-Inputs!$C$13)/('Static Data'!$B$13-'Static Data'!$B$12),0)),0))) | E72: =IF(E6=0,"",IF(Inputs!$C$24="Charity",'Static Data'!$B$14,IF(Inputs!$C$24="Small business (only property)",IF(Inputs!$C$13<='Static Data'!$B$12,1,IF(Inputs!$C$13<'Static Data'!$B$13,('Static Data'!$B$13-Inputs!$C$13)/('Static Data'!$B$13-'Static Data'!$B$12),0)),0))) | F72: =IF(F6=0,"",IF(Inputs!$C$24="Charity",'Static Data'!$B$14,IF(Inputs!$C$24="Small business (only property)",IF(Inputs!$C$13<='Static Data'!$B$12,1,IF(Inputs!$C$13<'Static Data'!$B$13,('Static Data'!$B$13-Inputs!$C$13)/('Static Data'!$B$13-'Static Data'!$B$12),0)),0))) | G72: =IF(G6=0,"",IF(Inputs!$D$24="Charity",'Static Data'!$B$14,IF(Inputs!$D$24="Small business (only property)",IF(Inputs!$D$13<='Static Data'!$B$12,1,IF(Inputs!$D$13<'Static Data'!$B$13,('Static Data'!$B$13-Inputs!$D$13)/('Static Data'!$B$13-'Static Data'!$B$12),0)),0))) | H72: =IF(H6=0,"",IF(Inputs!$D$24="Charity",'Static Data'!$B$14,IF(Inputs!$D$24="Small business (only property)",IF(Inputs!$D$13<='Static Data'!$B$12,1,IF(Inputs!$D$13<'Static Data'!$B$13,('Static Data'!$B$13-Inputs!$D$13)/('Static Data'!$B$13-'Static Data'!$B$12),0)),0))) | I72: =IF(I6=0,"",IF(Inputs!$D$24="Charity",'Static Data'!$B$14,IF(Inputs!$D$24="Small business (only property)",IF(Inputs!$D$13<='Static Data'!$B$12,1,IF(Inputs!$D$13<'Static Data'!$B$13,('Static Data'!$B$13-Inputs!$D$13)/('Static Data'!$B$13-'Static Data'!$B$12),0)),0))) | J72: =IF(J6=0,"",IF(Inputs!$E$24="Charity",'Static Data'!$B$14,IF(Inputs!$E$24="Small business (only property)",IF(Inputs!$E$13<='Static Data'!$B$12,1,IF(Inputs!$E$13<'Static Data'!$B$13,('Static Data'!$B$13-Inputs!$E$13)/('Static Data'!$B$13-'Static Data'!$B$12),0)),0))) | K72: =IF(K6=0,"",IF(Inputs!$E$24="Charity",'Static Data'!$B$14,IF(Inputs!$E$24="Small business (only property)",IF(Inputs!$E$13<='Static Data'!$B$12,1,IF(Inputs!$E$13<'Static Data'!$B$13,('Static Data'!$B$13-Inputs!$E$13)/('Static Data'!$B$13-'Static Data'!$B$12),0)),0))) | L72: =IF(L6=0,"",IF(Inputs!$E$24="Charity",'Static Data'!$B$14,IF(Inputs!$E$24="Small business (only property)",IF(Inputs!$E$13<='Static Data'!$B$12,1,IF(Inputs!$E$13<'Static Data'!$B$13,('Static Data'!$B$13-Inputs!$E$13)/('Static Data'!$B$13-'Static Data'!$B$12),0)),0))) | M72: =IF(M6=0,"",IF(Inputs!$F$24="Charity",'Static Data'!$B$14,IF(Inputs!$F$24="Small business (only property)",IF(Inputs!$F$13<='Static Data'!$B$12,1,IF(Inputs!$F$13<'Static Data'!$B$13,('Static Data'!$B$13-Inputs!$F$13)/('Static Data'!$B$13-'Static Data'!$B$12),0)),0))) | N72: =IF(N6=0,"",IF(Inputs!$F$24="Charity",'Static Data'!$B$14,IF(Inputs!$F$24="Small business (only property)",IF(Inputs!$F$13<='Static Data'!$B$12,1,IF(Inputs!$F$13<'Static Data'!$B$13,('Static Data'!$B$13-Inputs!$F$13)/('Static Data'!$B$13-'Static Data'!$B$12),0)),0))) | O72: =IF(O6=0,"",IF(Inputs!$F$24="Charity",'Static Data'!$B$14,IF(Inputs!$F$24="Small business (only property)",IF(Inputs!$F$13<='Static Data'!$B$12,1,IF(Inputs!$F$13<'Static Data'!$B$13,('Static Data'!$B$13-Inputs!$F$13)/('Static Data'!$B$13-'Static Data'!$B$12),0)),0))) | P72: =IF(P6=0,"",IF(Inputs!$G$24="Charity",'Static Data'!$B$14,IF(Inputs!$G$24="Small business (only property)",IF(Inputs!$G$13<='Static Data'!$B$12,1,IF(Inputs!$G$13<'Static Data'!$B$13,('Static Data'!$B$13-Inputs!$G$13)/('Static Data'!$B$13-'Static Data'!$B$12),0)),0))) | Q72: =IF(Q6=0,"",IF(Inputs!$G$24="Charity",'Static Data'!$B$14,IF(Inputs!$G$24="Small business (only property)",IF(Inputs!$G$13<='Static Data'!$B$12,1,IF(Inputs!$G$13<'Static Data'!$B$13,('Static Data'!$B$13-Inputs!$G$13)/('Static Data'!$B$13-'Static Data'!$B$12),0)),0))) | R72: =IF(R6=0,"",IF(Inputs!$G$24="Charity",'Static Data'!$B$14,IF(Inputs!$G$24="Small business (only property)",IF(Inputs!$G$13<='Static Data'!$B$12,1,IF(Inputs!$G$13<'Static Data'!$B$13,('Static Data'!$B$13-Inputs!$G$13)/('Static Data'!$B$13-'Static Data'!$B$12),0)),0)))
B73: Total relief | C73: share | D73: =IF(D6=0,"",D72+(1-D72)*N(Inputs!$C$26)) | E73: =IF(E6=0,"",E72+(1-E72)*N(Inputs!$C$26)) | F73: =IF(F6=0,"",F72+(1-F72)*N(Inputs!$C$26)) | G73: =IF(G6=0,"",G72+(1-G72)*N(Inputs!$D$26)) | H73: =IF(H6=0,"",H72+(1-H72)*N(Inputs!$D$26)) | I73: =IF(I6=0,"",I72+(1-I72)*N(Inputs!$D$26)) | J73: =IF(J6=0,"",J72+(1-J72)*N(Inputs!$E$26)) | K73: =IF(K6=0,"",K72+(1-K72)*N(Inputs!$E$26)) | L73: =IF(L6=0,"",L72+(1-L72)*N(Inputs!$E$26)) | M73: =IF(M6=0,"",M72+(1-M72)*N(Inputs!$F$26)) | N73: =IF(N6=0,"",N72+(1-N72)*N(Inputs!$F$26)) | O73: =IF(O6=0,"",O72+(1-O72)*N(Inputs!$F$26)) | P73: =IF(P6=0,"",P72+(1-P72)*N(Inputs!$G$26)) | Q73: =IF(Q6=0,"",Q72+(1-Q72)*N(Inputs!$G$26)) | R73: =IF(R6=0,"",R72+(1-R72)*N(Inputs!$G$26))
B74: Rates paid while occupied | C74: £ a year | D74: =IF(D6=0,"",D71*(1-D73)) | E74: =IF(E6=0,"",E71*(1-E73)) | F74: =IF(F6=0,"",F71*(1-F73)) | G74: =IF(G6=0,"",G71*(1-G73)) | H74: =IF(H6=0,"",H71*(1-H73)) | I74: =IF(I6=0,"",I71*(1-I73)) | J74: =IF(J6=0,"",J71*(1-J73)) | K74: =IF(K6=0,"",K71*(1-K73)) | ... R74: =IF(R6=0,"",R71*(1-R73))
B75: Rates paid if left empty (Business as Usual) | C75: £ a year | D75: =IF(D6=0,"",IF(OR(Inputs!$C$13<'Static Data'!$B$11,Inputs!$C$14="Yes",Inputs!$C$15="Council"),0,Inputs!$C$13*IF(Inputs!$C$13>=500000,'Static Data'!$B$10,IF(Inputs!$C$13<51000,'Static Data'!$B$6,'Static Data'!$B$8)))) | E75: =IF(E6=0,"",IF(OR(Inputs!$C$13<'Static Data'!$B$11,Inputs!$C$14="Yes",Inputs!$C$15="Council"),0,Inputs!$C$13*IF(Inputs!$C$13>=500000,'Static Data'!$B$10,IF(Inputs!$C$13<51000,'Static Data'!$B$6,'Static Data'!$B$8)))) | F75: =IF(F6=0,"",IF(OR(Inputs!$C$13<'Static Data'!$B$11,Inputs!$C$14="Yes",Inputs!$C$15="Council"),0,Inputs!$C$13*IF(Inputs!$C$13>=500000,'Static Data'!$B$10,IF(Inputs!$C$13<51000,'Static Data'!$B$6,'Static Data'!$B$8)))) | G75: =IF(G6=0,"",IF(OR(Inputs!$D$13<'Static Data'!$B$11,Inputs!$D$14="Yes",Inputs!$D$15="Council"),0,Inputs!$D$13*IF(Inputs!$D$13>=500000,'Static Data'!$B$10,IF(Inputs!$D$13<51000,'Static Data'!$B$6,'Static Data'!$B$8)))) | H75: =IF(H6=0,"",IF(OR(Inputs!$D$13<'Static Data'!$B$11,Inputs!$D$14="Yes",Inputs!$D$15="Council"),0,Inputs!$D$13*IF(Inputs!$D$13>=500000,'Static Data'!$B$10,IF(Inputs!$D$13<51000,'Static Data'!$B$6,'Static Data'!$B$8)))) | I75: =IF(I6=0,"",IF(OR(Inputs!$D$13<'Static Data'!$B$11,Inputs!$D$14="Yes",Inputs!$D$15="Council"),0,Inputs!$D$13*IF(Inputs!$D$13>=500000,'Static Data'!$B$10,IF(Inputs!$D$13<51000,'Static Data'!$B$6,'Static Data'!$B$8)))) | J75: =IF(J6=0,"",IF(OR(Inputs!$E$13<'Static Data'!$B$11,Inputs!$E$14="Yes",Inputs!$E$15="Council"),0,Inputs!$E$13*IF(Inputs!$E$13>=500000,'Static Data'!$B$10,IF(Inputs!$E$13<51000,'Static Data'!$B$6,'Static Data'!$B$8)))) | K75: =IF(K6=0,"",IF(OR(Inputs!$E$13<'Static Data'!$B$11,Inputs!$E$14="Yes",Inputs!$E$15="Council"),0,Inputs!$E$13*IF(Inputs!$E$13>=500000,'Static Data'!$B$10,IF(Inputs!$E$13<51000,'Static Data'!$B$6,'Static Data'!$B$8)))) | L75: =IF(L6=0,"",IF(OR(Inputs!$E$13<'Static Data'!$B$11,Inputs!$E$14="Yes",Inputs!$E$15="Council"),0,Inputs!$E$13*IF(Inputs!$E$13>=500000,'Static Data'!$B$10,IF(Inputs!$E$13<51000,'Static Data'!$B$6,'Static Data'!$B$8)))) | M75: =IF(M6=0,"",IF(OR(Inputs!$F$13<'Static Data'!$B$11,Inputs!$F$14="Yes",Inputs!$F$15="Council"),0,Inputs!$F$13*IF(Inputs!$F$13>=500000,'Static Data'!$B$10,IF(Inputs!$F$13<51000,'Static Data'!$B$6,'Static Data'!$B$8)))) | N75: =IF(N6=0,"",IF(OR(Inputs!$F$13<'Static Data'!$B$11,Inputs!$F$14="Yes",Inputs!$F$15="Council"),0,Inputs!$F$13*IF(Inputs!$F$13>=500000,'Static Data'!$B$10,IF(Inputs!$F$13<51000,'Static Data'!$B$6,'Static Data'!$B$8)))) | O75: =IF(O6=0,"",IF(OR(Inputs!$F$13<'Static Data'!$B$11,Inputs!$F$14="Yes",Inputs!$F$15="Council"),0,Inputs!$F$13*IF(Inputs!$F$13>=500000,'Static Data'!$B$10,IF(Inputs!$F$13<51000,'Static Data'!$B$6,'Static Data'!$B$8)))) | P75: =IF(P6=0,"",IF(OR(Inputs!$G$13<'Static Data'!$B$11,Inputs!$G$14="Yes",Inputs!$G$15="Council"),0,Inputs!$G$13*IF(Inputs!$G$13>=500000,'Static Data'!$B$10,IF(Inputs!$G$13<51000,'Static Data'!$B$6,'Static Data'!$B$8)))) | Q75: =IF(Q6=0,"",IF(OR(Inputs!$G$13<'Static Data'!$B$11,Inputs!$G$14="Yes",Inputs!$G$15="Council"),0,Inputs!$G$13*IF(Inputs!$G$13>=500000,'Static Data'!$B$10,IF(Inputs!$G$13<51000,'Static Data'!$B$6,'Static Data'!$B$8)))) | R75: =IF(R6=0,"",IF(OR(Inputs!$G$13<'Static Data'!$B$11,Inputs!$G$14="Yes",Inputs!$G$15="Council"),0,Inputs!$G$13*IF(Inputs!$G$13>=500000,'Static Data'!$B$10,IF(Inputs!$G$13<51000,'Static Data'!$B$6,'Static Data'!$B$8))))
B76: Empty exemption restarted after the occupation, present value | C76: £ | D76: =IF(D6=0,"",IF(D7*52/12>='Static Data'!$B$15,'Static Data'!$B$16/12*D75*D16,0)) | E76: =IF(E6=0,"",IF(E7*52/12>='Static Data'!$B$15,'Static Data'!$B$16/12*E75*E16,0)) | F76: =IF(F6=0,"",IF(F7*52/12>='Static Data'!$B$15,'Static Data'!$B$16/12*F75*F16,0)) | G76: =IF(G6=0,"",IF(G7*52/12>='Static Data'!$B$15,'Static Data'!$B$16/12*G75*G16,0)) | H76: =IF(H6=0,"",IF(H7*52/12>='Static Data'!$B$15,'Static Data'!$B$16/12*H75*H16,0)) | I76: =IF(I6=0,"",IF(I7*52/12>='Static Data'!$B$15,'Static Data'!$B$16/12*I75*I16,0)) | J76: =IF(J6=0,"",IF(J7*52/12>='Static Data'!$B$15,'Static Data'!$B$16/12*J75*J16,0)) | K76: =IF(K6=0,"",IF(K7*52/12>='Static Data'!$B$15,'Static Data'!$B$16/12*K75*K16,0)) | ... R76: =IF(R6=0,"",IF(R7*52/12>='Static Data'!$B$15,'Static Data'!$B$16/12*R75*R16,0))
B77: Rates a blocked commercial tenant would have paid, present value (lost, no recipient) | C77: £ | D77: =IF(D6=0,"",IF(D24=1,0,-D22*D71*D14)) | E77: =IF(E6=0,"",IF(E24=1,0,-E22*E71*E14)) | F77: =IF(F6=0,"",IF(F24=1,0,-F22*F71*F14)) | G77: =IF(G6=0,"",IF(G24=1,0,-G22*G71*G14)) | H77: =IF(H6=0,"",IF(H24=1,0,-H22*H71*H14)) | I77: =IF(I6=0,"",IF(I24=1,0,-I22*I71*I14)) | J77: =IF(J6=0,"",IF(J24=1,0,-J22*J71*J14)) | K77: =IF(K6=0,"",IF(K24=1,0,-K22*K71*K14)) | ... R77: =IF(R6=0,"",IF(R24=1,0,-R22*R71*R14))
B78: Change in public rates income, present value | C78: £ | D78: =IF(D6=0,"",IF(D24=1,D25*((D74-D75)*D14-D76),(D74-D25*D75)*D14-D25*D76+D77)) | E78: =IF(E6=0,"",IF(E24=1,E25*((E74-E75)*E14-E76),(E74-E25*E75)*E14-E25*E76+E77)) | F78: =IF(F6=0,"",IF(F24=1,F25*((F74-F75)*F14-F76),(F74-F25*F75)*F14-F25*F76+F77)) | G78: =IF(G6=0,"",IF(G24=1,G25*((G74-G75)*G14-G76),(G74-G25*G75)*G14-G25*G76+G77)) | H78: =IF(H6=0,"",IF(H24=1,H25*((H74-H75)*H14-H76),(H74-H25*H75)*H14-H25*H76+H77)) | I78: =IF(I6=0,"",IF(I24=1,I25*((I74-I75)*I14-I76),(I74-I25*I75)*I14-I25*I76+I77)) | J78: =IF(J6=0,"",IF(J24=1,J25*((J74-J75)*J14-J76),(J74-J25*J75)*J14-J25*J76+J77)) | K78: =IF(K6=0,"",IF(K24=1,K25*((K74-K75)*K14-K76),(K74-K25*K75)*K14-K25*K76+K77)) | ... R78: =IF(R6=0,"",IF(R24=1,R25*((R74-R75)*R14-R76),(R74-R25*R75)*R14-R25*R76+R77))
